Workbook

Sheet LEEME
A1: Base de conocimiento de minutas — Asistente Red IDBI
A2: Para qué sirve | B2: Cargar las minutas técnicas hechas a mano (PDF) en la base de datos, con el mismo vocabulario del chat de 76 nodos, para que el motor de recomendaciones aprenda de casos reales.
A3: Qué ya trae | B3: 44 minutas manuales cargadas (MH-001 a MH-044), 67 reglas de recomendación + 13 acciones estándar, 10 reglas de validación, 13 equipos y 27 umbrales.
A4: Cómo agregar una minuta | B4: 1) kb_minuta: una fila nueva con el siguiente minuta_id (MH-045…). 2) kb_minuta_respuesta: lo que el PDF responde de las preguntas del flujo (ver ref_preguntas). 3) kb_minuta_hallazgo: antecedentes, desarrollo y observaciones. 4) kb_minuta_recomendacion: cada recomendación y siguiente acción, con su regla_id. 5) kb_minuta_equipo y kb_minuta_evidencia.
A5: Colores | B5: Amarillo = filas vacías para llenar. Gris = fórmula, no escribir. Azul = encabezado (nombre de columna en la base, no cambiar).
A6: Valores | B6: Usa los códigos de las listas desplegables (hoja catalogos): son los mismos del flujo (ej. FAST_FOOD, CABLE_RED, SI/NO). Si la respuesta es Otro, escribe OTRO: seguido del texto (ej. OTRO: Yachay Telecomunicaciones, OTRO: Cocina 2).
A7: Respuestas | B7: confianza = EXPLICITO si la minuta lo dice tal cual; INFERIDO si se deduce. alcance solo para preguntas que se repiten (L_CAJAS:1, L_IMPRESORAS:2).
A8: Recomendaciones | B8: Cada fila debe tener regla_id. Si ninguna regla calza, crea una nueva en kb_regla_recomendacion (R29, R30…) y úsala. La hoja resumen avisa cuántas quedan sin regla.
A9: Estado del local | B9: P08 ya no es el motivo de visita: es el estado del local (En operación, En obra, Por inaugurar, Ya cuenta con un sistema de punto de venta anterior, Otro). En las minutas cargadas solo se llenó donde la minuta lo deja claro; las demás quedan en blanco.
A10: Pasos a seguir, observaciones y anexos | B10: Los pasos a seguir (cliente / ID) se generan solos y el técnico los edita (hoja kb_accion_siguiente). Después del análisis se abre un apartado de observaciones con selección múltiple: observaciones del técnico, serie de facturación, ¿el cliente acepta la recomendación? (Sí/No/Otro), método de pago y Otro (hoja kb_observacion_opcion). Va en la minuta después de las recomendaciones. Los enlaces de video del local van como anexos (P49a).
A11: Speedtest y WiFi por zona | B11: El speedtest del plan (E1) se hace por cable directo al router principal (Cat6, puerto RJ45 gigabit); por WiFi no vale. V01: la mejor de 2 pruebas por cable debe llegar al 70 % del plan; entre 85 y 95 Mbps con plan mayor = limitada a 100 Mbps (R65); ping con carga > 300 ms = saturación (R66, observación). El WiFi se revisa por zona (opcional) con umbrales para el punto de venta (kb_umbral).
A12: Canales y evidencias | B12: Canales de atención (Mesa, Recojo, Para llevar, Backoffice, Delivery, Otro) con sus zonas sugeridas + Otro (hoja kb_canal_atencion). Fotos obligatorias: frontis, cada lugar de preparación, cada zona de atención y cada caja (hoja kb_evidencia_obligatoria). La IA valida que la foto sea la pedida y legible comparándola con el dataset de referencias (hojas kb_evidencia_tipo y kb_evidencia_referencia).
A13: Prueba retrospectiva | B13: Motor vs. minutas reales: 81.7 % de coincidencia en 126 decisiones comparables (hoja kb_prueba_retrospectiva).
... A23: Detalle técnico | B23: docs/base-conocimiento/BASE_CONOCIMIENTO_MINUTAS.md explica las tablas, el importador y cómo usarlas en las recomendaciones.

Sheet resumen
A1: Indicador | B1: Valor | C1: Cómo se calcula
A2: Minutas cargadas | B2: =COUNTA(kb_minuta!$A$2:$A$2000) | C2: Filas con minuta_id en kb_minuta
A3: Respuestas del flujo extraídas | B3: =COUNTA(kb_minuta_respuesta!$A$2:$A$2000) | C3: Filas en kb_minuta_respuesta
A4: · explícitas | B4: =COUNTIF(kb_minuta_respuesta!$E$2:$E$2000,"EXPLICITO")
A5: · inferidas | B5: =COUNTIF(kb_minuta_respuesta!$E$2:$E$2000,"INFERIDO")
A6: Hallazgos | B6: =COUNTA(kb_minuta_hallazgo!$A$2:$A$2000)
A7: Recomendaciones (sin acciones) | B7: =COUNTIF(kb_minuta_recomendacion!$C$2:$C$2000,"RECOMENDACION")
A8: Siguientes acciones | B8: =COUNTIF(kb_minuta_recomendacion!$C$2:$C$2000,"ACCION*") | C8: ACCION_ID + ACCION_CLIENTE
A9: Recomendaciones sin regla vinculada | B9: =COUNTIFS(kb_minuta_recomendacion!$A$2:$A$2000,"<>",kb_minuta_recomendacion!$D$2:$D$2000,"") | C9: Deben quedar en 0 antes de cargar
A10: Reglas en la base | B10: =COUNTA(kb_regla_recomendacion!$A$2:$A$200)
A11: Reglas respaldadas por al menos una minuta | B11: =COUNTIF(kb_regla_recomendacion!$M$2:$M$200,">0")
A12: Equipos registrados en minutas | B12: =COUNTA(kb_minuta_equipo!$A$2:$A$2000)
A13: Evidencias referenciadas | B13: =COUNTA(kb_minuta_evidencia!$A$2:$A$2000)
A14: Credenciales (confidencial) | B14: =COUNTA(kb_minuta_credencial!$A$2:$A$2000) | C14: Hoja kb_minuta_credencial
A16: Top reglas por frecuencia en minutas: ordena la hoja kb_regla_recomendacion por veces_en_minutas.

Sheet kb_minuta
A1: minuta_id | B1: nombre_cliente | C1: nombre_local | D1: direccion | E1: distrito | F1: fecha_visita | G1: hora | H1: estado_local | I1: antecedentes | J1: tipo_negocio | K1: pisos | L1: cajas | M1: proveedor_internet | N1: tipo_conexion | O1: velocidad_contratada_mbps | P1: bajada_mbps | Q1: subida_mbps | R1: segmento_red | S1: estado_final | T1: asistentes_id | U1: contacto_cliente | V1: requiere_segunda_visita | W1: archivo_pdf | X1: observaciones_carga | Y1: n_respuestas | Z1: n_recomendaciones | AA1: n_acciones
A2: MH-001 | B2: Sicilia | C2: Sicilia – Patio Gastronómico Refugio | D2: Patio Gastronómico Refugio | F2: 45202 | G2: 10:00 | I2: Entrega y configuración de impresoras, creación de tienda y zonas de trabajo en IDPos | J2: RESTAURANTE | S2: SIN_DATO | T2: Kevin Flores, Yomira Mora | U2: Kathy | V2: SI | W2: sicilia.pdf | X2: Dirección exacta no indicada en la minuta. | Y2: =IF(A2="","",COUNTIF(kb_minuta_respuesta!$A$2:$A$2000,A2)) | Z2: =IF(A2="","",COUNTIFS(kb_minuta_recomendacion!$A$2:$A$2000,A2,kb_minuta_recomendacion!$C$2:$C$2000,"RECOMENDACION")) | AA2: =IF(A2="","",COUNTIF(kb_minuta_recomendacion!$A$2:$A$2000,A2)-Z2)
A3: MH-002 | B3: Don Oscar | C3: Don Oscar | D3: Calle Alcanfores 151, Miraflores 15074 | E3: Miraflores | F3: 45227 | G3: 10:00 | H3: EN_OPERACION | I3: Revisión del sistema de impresión del Raspberry y capacitación sobre creación de cupones | J3: REST_PESCADOS | S3: SIN_DATO | T3: Yomira Mora | U3: Piero | V3: NO | W3: donoscar.pdf | Y3: =IF(A3="","",COUNTIF(kb_minuta_respuesta!$A$2:$A$2000,A3)) | Z3: =IF(A3="","",COUNTIFS(kb_minuta_recomendacion!$A$2:$A$2000,A3,kb_minuta_recomendacion!$C$2:$C$2000,"RECOMENDACION")) | AA3: =IF(A3="","",COUNTIF(kb_minuta_recomendacion!$A$2:$A$2000,A3)-Z3)
A4: MH-003 | B4: Barrio Pesquero | C4: Barrio Pesquero | D4: Av. Gral. Antonio Álvarez de Arenales 1746, Lince 15073 | E4: Lince | F4: 45239 | G4: 16:00 | H4: EN_OPERACION | I4: Los programas de impresión no funcionan hasta que se reinicia el internet | J4: REST_PESCADOS | S4: SIN_DATO | T4: Yomira Mora | U4: Giancarlo Sanguinetti | V4: NO | W4: barrio.pdf | Y4: =IF(A4="","",COUNTIF(kb_minuta_respuesta!$A$2:$A$2000,A4)) | Z4: =IF(A4="","",COUNTIFS(kb_minuta_recomendacion!$A$2:$A$2000,A4,kb_minuta_recomendacion!$C$2:$C$2000,"RECOMENDACION")) | AA4: =IF(A4="","",COUNTIF(kb_minuta_recomendacion!$A$2:$A$2000,A4)-Z4)
A5: MH-004 | B5: Rock & Burgers | C5: Rock & Burgers – Huaral | D5: C. Luis Colán 242, Huaral 15201 | E5: Huaral | F5: 46173 | G5: 16:00 | I5: Evaluación de red para implementar el sistema (inicio 01/06/2026) | J5: FAST_FOOD | K5: 3 | M5: CLARO | N5: FIBRA | P5: 91.5 | Q5: 92.49 | R5: 192.168.100.0/24 | S5: APTO | T5: Yomira Mora | U5: Gianfranco (equipo operativo) | V5: NO | W5: rock.pdf | X5: La minuta trae acceso remoto (AnyDesk): ver hoja kb_minuta_credencial. Tecnología de impresiones: wrapper Windows. | Y5: =IF(A5="","",COUNTIF(kb_minuta_respuesta!$A$2:$A$2000,A5)) | Z5: =IF(A5="","",COUNTIFS(kb_minuta_recomendacion!$A$2:$A$2000,A5,kb_minuta_recomendacion!$C$2:$C$2000,"RECOMENDACION")) | AA5: =IF(A5="","",COUNTIF(kb_minuta_recomendacion!$A$2:$A$2000,A5)-Z5)
A6: MH-005 | B6: Dorcher Bier | C6: Dorcher San Miguel | D6: Dorcher San Miguel | E6: San Miguel | F6: 45030 | G6: 10:30 | H6: EN_OPERACION | I6: Sin conexión a internet y sin impresión de comandas ni comprobantes | J6: RESTOBAR | K6: 2 | L6: 3 | M6: MOVISTAR | P6: 94.01 | Q6: 94.43 | S6: SIN_DATO | T6: Arturo Contreras | U6: Karla Sandoval | W6: Visita_Tecnica_DORCHER_SM_14-04-23.pdf | X6: Dos redes (Claro y Movistar). Ese día los equipos se pasaron a Movistar; velocidad medida tras cambiar el switch. Tipo de negocio inferido (cervecería). | Y6: =IF(A6="","",COUNTIF(kb_minuta_respuesta!$A$2:$A$2000,A6)) | Z6: =IF(A6="","",COUNTIFS(kb_minuta_recomendacion!$A$2:$A$2000,A6,kb_minuta_recomendacion!$C$2:$C$2000,"RECOMENDACION")) | AA6: =IF(A6="","",COUNTIF(kb_minuta_recomendacion!$A$2:$A$2000,A6)-Z6)
A7: MH-006 | B7: Dorcher Bier | C7: Dorcher San Miguel | D7: Dorcher San Miguel | E7: San Miguel | F7: 45073 | G7: 16:00 | H7: EN_OPERACION | I7: Impresoras sin imprimir: el cableado del segundo piso se movió entre las redes Claro y Movistar | J7: RESTOBAR | K7: 2 | L7: 3 | M7: CLARO | P7: 93.37 | Q7: 32.36 | S7: SIN_DATO | T7: Arturo Contreras | W7: VISITA_TECNICA_DORCHER_SM_27-05-23.pdf | X7: Todos los equipos se reconfiguraron en la red Claro. Velocidad de la PC Caja 2 (las otras ~92 Mbps). Contacto del cliente vacío en la minuta. | Y7: =IF(A7="","",COUNTIF(kb_minuta_respuesta!$A$2:$A$2000,A7)) | Z7: =IF(A7="","",COUNTIFS(kb_minuta_recomendacion!$A$2:$A$2000,A7,kb_minuta_recomendacion!$C$2:$C$2000,"RECOMENDACION")) | AA7: =IF(A7="","",COUNTIF(kb_minuta_recomendacion!$A$2:$A$2000,A7)-Z7)
A8: MH-007 | B8: Malala | C8: Malala | D8: Calle Alcanfores 151, Miraflores 15074 | E8: Miraflores | F8: 45230 | G8: 21:00 | H8: POR_INAUGURAR | I8: Local sin internet: el proveedor no había habilitado el servicio | J8: RESTOBAR | K8: 2 | M8: OTRO | N8: NO_TIENE | S8: SIN_DATO | T8: Yomira Mora | U8: Marina | V8: SI | W8: Minuta_Visita_Tecnica_Malala_31-10-23.pdf | X8: Se habilitó internet de respaldo con TP-Link 4G + chip Entel. Proveedor principal no habilitado. Tipo de negocio inferido (makis). Misma dirección que Don Oscar en la minuta. | Y8: =IF(A8="","",COUNTIF(kb_minuta_respuesta!$A$2:$A$2000,A8)) | Z8: =IF(A8="","",COUNTIFS(kb_minuta_recomendacion!$A$2:$A$2000,A8,kb_minuta_recomendacion!$C$2:$C$2000,"RECOMENDACION")) | AA8: =IF(A8="","",COUNTIF(kb_minuta_recomendacion!$A$2:$A$2000,A8)-Z8)
A9: MH-008 | B9: Hotel La Confianza | C9: Hotel La Confianza | D9: Catapalla, Lunahuaná 15727 | E9: Lunahuaná | F9: 45232 | G9: 11:30 | H9: EN_OPERACION | I9: Revisión del sistema de impresión del Raspberry | J9: HOSPEDAJE | M9: OTRO | O9: 20 | P9: 2.73 | S9: SIN_DATO | T9: Yomira Mora, Daphne | U9: Caleb | W9: Minuta_Visita_Tecnica_Hotel_La_Confianza_02-11-23.pdf | X9: Tipo de conexión vacío: es satelital (Hughesnet) y P14 no tiene esa opción. Plan de 20 Mbps con 10 GB; al agotar datos reduce la velocidad (2.73 Mbps medidos). | Y9: =IF(A9="","",COUNTIF(kb_minuta_respuesta!$A$2:$A$2000,A9)) | Z9: =IF(A9="","",COUNTIFS(kb_minuta_recomendacion!$A$2:$A$2000,A9,kb_minuta_recomendacion!$C$2:$C$2000,"RECOMENDACION")) | AA9: =IF(A9="","",COUNTIF(kb_minuta_recomendacion!$A$2:$A$2000,A9)-Z9)
A10: MH-009 | B10: Rikoton | C10: RKT Banchero | D10: Av. Santa Rosa 468, Urb. Canto Grande, San Juan de Lurigancho | E10: San Juan de Lurigancho | F10: 45819 | G10: 12:00 | I10: Validar que los equipos estén operativos antes de la implementación | J10: POLLERIA | M10: MOVISTAR | N10: FIBRA | P10: 493.11 | R10: 192.168.0.0/24 | S10: SIN_DATO | T10: Sera G., Yomira Mora | U10: Fernando | W10: RKT_BANCHERO_-_Minuta_Visita.pdf | X10: Dos segmentos de red. Tipo de negocio inferido (pollería/brasas). | Y10: =IF(A10="","",COUNTIF(kb_minuta_respuesta!$A$2:$A$2000,A10)) | Z10: =IF(A10="","",COUNTIFS(kb_minuta_recomendacion!$A$2:$A$2000,A10,kb_minuta_recomendacion!$C$2:$C$2000,"RECOMENDACION")) | AA10: =IF(A10="","",COUNTIF(kb_minuta_recomendacion!$A$2:$A$2000,A10)-Z10)
A11: MH-010 | B11: Rikoton | C11: RKT Bayóvar | D11: Cal. Segunda Zona de Bayóvar Mz. 2 Lt. 1, San Juan de Lurigancho | E11: San Juan de Lurigancho | F11: 45819 | G11: 12:00 | I11: Validar que los equipos estén operativos antes de la implementación | J11: POLLERIA | M11: MOVISTAR | P11: 93.17 | R11: 192.168.1.0/24 | S11: SIN_DATO | T11: Sera G., Yomira Mora | U11: Fernando | W11: RKT_BAYOVAR_-_Minuta_Visita.pdf | X11: Dos segmentos de red. | Y11: =IF(A11="","",COUNTIF(kb_minuta_respuesta!$A$2:$A$2000,A11)) | Z11: =IF(A11="","",COUNTIFS(kb_minuta_recomendacion!$A$2:$A$2000,A11,kb_minuta_recomendacion!$C$2:$C$2000,"RECOMENDACION")) | AA11: =IF(A11="","",COUNTIF(kb_minuta_recomendacion!$A$2:$A$2000,A11)-Z11)
A12: MH-011 | B12: Rikoton | C12: RKT Calle 8 | D12: Av. Los Pinos Mz. S Lt. 3, Campoy II Etapa, San Juan de Lurigancho | E12: San Juan de Lurigancho | F12: 45819 | G12: 12:00 | I12: Validar que los equipos estén operativos antes de la implementación | J12: POLLERIA | K12: 2 | M12: OTRO | P12: 480.02 | Q12: 488.33 | R12: 192.168.1.0/24 | S12: SIN_DATO | T12: Sera G., Yomira Mora | U12: Fernando | W12: RKT_Calle_8-_Minuta_Visita.pdf | X12: Proveedor del speedtest: Yachay Telecomunicaciones. | Y12: =IF(A12="","",COUNTIF(kb_minuta_respuesta!$A$2:$A$2000,A12)) | Z12: =IF(A12="","",COUNTIFS(kb_minuta_recomendacion!$A$2:$A$2000,A12,kb_minuta_recomendacion!$C$2:$C$2000,"RECOMENDACION")) | AA12: =IF(A12="","",COUNTIF(kb_minuta_recomendacion!$A$2:$A$2000,A12)-Z12)
A13: MH-012 | B13: Rikoton | C13: RKT Hacienda | D13: Av. Próceres de la Independencia 1730, Urb. Las Flores de Primavera, San Juan de Lurigancho | E13: San Juan de Lurigancho | F13: 45819 | G13: 12:00 | I13: Validar que los equipos estén operativos antes de la implementación | J13: POLLERIA | M13: MOVISTAR | P13: 88.94 | Q13: 92.64 | S13: APTO | T13: Sera G., Yomira Mora | U13: Fernando | W13: RKT_HACIENDA_-_Minuta_Visita_1.pdf | X13: ID de AnyDesk: ver hoja kb_minuta_credencial. Estado: 'se validaron los equipos y la funcionalidad óptima para la implementación'. | Y13: =IF(A13="","",COUNTIF(kb_minuta_respuesta!$A$2:$A$2000,A13)) | Z13: =IF(A13="","",COUNTIFS(kb_minuta_recomendacion!$A$2:$A$2000,A13,kb_minuta_recomendacion!$C$2:$C$2000,"RECOMENDACION")) | AA13: =IF(A13="","",COUNTIF(kb_minuta_recomendacion!$A$2:$A$2000,A13)-Z13)
A14: MH-013 | B14: Rikoton | C14: RKT Mariscal | D14: Jr. Somos Libres Mz. D Lt. 3, A.H. Somos Libres, San Juan de Lurigancho | E14: San Juan de Lurigancho | F14: 45819 | G14: 12:00 | I14: Validar que los equipos estén operativos antes de la implementación | J14: POLLERIA | K14: 3 | M14: OTRO | N14: FIBRA | P14: 93.91 | Q14: 94.27 | R14: 192.168.1.0/24 | S14: SIN_DATO | T14: Sera G., Yomira Mora | U14: Fernando | W14: RKT_MARISCAL_-_Minuta_Visita_1.pdf | X14: Proveedor del speedtest: Yachay Telecomunicaciones. | Y14: =IF(A14="","",COUNTIF(kb_minuta_respuesta!$A$2:$A$2000,A14)) | Z14: =IF(A14="","",COUNTIFS(kb_minuta_recomendacion!$A$2:$A$2000,A14,kb_minuta_recomendacion!$C$2:$C$2000,"RECOMENDACION")) | AA14: =IF(A14="","",COUNTIF(kb_minuta_recomendacion!$A$2:$A$2000,A14)-Z14)
A15: MH-014 | B15: Rikoton | C15: RKT Villa Flores | D15: Av. Santa Rosa de Lima Mz. T3 Lt. 33, San Juan de Lurigancho | E15: San Juan de Lurigancho | F15: 45819 | G15: 12:00 | I15: Validar que los equipos estén operativos antes de la implementación | J15: POLLERIA | M15: OTRO | P15: 400.19 | R15: 192.168.1.0/24 | S15: SIN_DATO | T15: Sera G., Yomira Mora | U15: Fernando | W15: RKT_Villa_Flores-_Minuta_Visita.pdf | X15: Proveedor WOW. Dos segmentos de red. Router sin puertos libres. | Y15: =IF(A15="","",COUNTIF(kb_minuta_respuesta!$A$2:$A$2000,A15)) | Z15: =IF(A15="","",COUNTIFS(kb_minuta_recomendacion!$A$2:$A$2000,A15,kb_minuta_recomendacion!$C$2:$C$2000,"RECOMENDACION")) | AA15: =IF(A15="","",COUNTIF(kb_minuta_recomendacion!$A$2:$A$2000,A15)-Z15)
A16: MH-015 | B16: Rikoton | C16: RKT Zárate | D16: Av. Chimú 1599, Urb. Zárate, San Juan de Lurigancho | E16: San Juan de Lurigancho | F16: 45819 | G16: 12:00 | I16: Validar que los equipos estén operativos antes de la implementación | J16: POLLERIA | K16: 2 | M16: OTRO | P16: 492.71 | Q16: 404.81 | R16: 192.168.18.0/24 | S16: SIN_DATO | T16: Sera G., Yomira Mora | U16: Fernando | W16: RKT_ZARATE_-_Minuta_Visita.pdf | X16: Proveedor del speedtest: Yachay Telecomunicaciones. Gateway 192.168.18.1. | Y16: =IF(A16="","",COUNTIF(kb_minuta_respuesta!$A$2:$A$2000,A16)) | Z16: =IF(A16="","",COUNTIFS(kb_minuta_recomendacion!$A$2:$A$2000,A16,kb_minuta_recomendacion!$C$2:$C$2000,"RECOMENDACION")) | AA16: =IF(A16="","",COUNTIF(kb_minuta_recomendacion!$A$2:$A$2000,A16)-Z16)
A17: MH-016 | B17: Gelato Alore | C17: Gelato Alore Miguel Dasso | D17: C.C. Sausalito, C. Miguel Dasso 126, San Isidro 15073 | E17: San Isidro | F17: 45839 | G17: 11:00 | I17: Conocer el local, el estado de la red y los equipos de operación antes de implementar | J17: HELADERIA | M17: MOVISTAR | P17: 155.54 | Q17: 2.52 | R17: 192.168.1.0/24 | S17: SIN_DATO | T17: Kevin | U17: Roxana Sujara | W17: Minuta_Gelato_Alore_M_Dasso.pdf | X17: Heladería. La tablet es la caja principal. Subida muy baja (2.52 Mbps). QR de WiFi: ver hoja kb_minuta_credencial. | Y17: =IF(A17="","",COUNTIF(kb_minuta_respuesta!$A$2:$A$2000,A17)) | Z17: =IF(A17="","",COUNTIFS(kb_minuta_recomendacion!$A$2:$A$2000,A17,kb_minuta_recomendacion!$C$2:$C$2000,"RECOMENDACION")) | AA17: =IF(A17="","",COUNTIF(kb_minuta_recomendacion!$A$2:$A$2000,A17)-Z17)
A18: MH-017 | B18: Gelato Alore | C18: Gelato Alore Ejército | D18: Av. del Ejército 395, Miraflores 15074 | E18: Miraflores | F18: 45839 | G18: 13:15 | I18: Conocer el local, el estado de la red y los equipos de operación antes de implementar | J18: HELADERIA | M18: MOVISTAR | P18: 89.44 | Q18: 89.61 | R18: 192.168.5.0/24 | S18: SIN_DATO | T18: Kevin | U18: Mirella León | W18: Minuta_Gelato_Alore_Ejercito.pdf | X18: Heladería. QR de WiFi: ver hoja kb_minuta_credencial. | Y18: =IF(A18="","",COUNTIF(kb_minuta_respuesta!$A$2:$A$2000,A18)) | Z18: =IF(A18="","",COUNTIFS(kb_minuta_recomendacion!$A$2:$A$2000,A18,kb_minuta_recomendacion!$C$2:$C$2000,"RECOMENDACION")) | AA18: =IF(A18="","",COUNTIF(kb_minuta_recomendacion!$A$2:$A$2000,A18)-Z18)
A19: MH-018 | B19: Gelato Alore | C19: Gelato Alore 2 de Mayo | D19: Av. Dos de Mayo 1186, San Isidro 15073 | E19: San Isidro | F19: 45839 | G19: 15:40 | I19: Conocer el local, el estado de la red y los equipos de operación antes de implementar | J19: HELADERIA | M19: CLARO | P19: 233.24 | Q19: 55.05 | R19: 192.168.0.0/24 | S19: SIN_DATO | T19: Kevin | U19: Blanca Coronel | W19: Minuta_Gelato_Alore_2_de_Mayo.pdf | X19: Heladería. Prueba adicional por WiFi móvil: 89.44 / 89.61 Mbps. QR de WiFi: ver hoja kb_minuta_credencial. | Y19: =IF(A19="","",COUNTIF(kb_minuta_respuesta!$A$2:$A$2000,A19)) | Z19: =IF(A19="","",COUNTIFS(kb_minuta_recomendacion!$A$2:$A$2000,A19,kb_minuta_recomendacion!$C$2:$C$2000,"RECOMENDACION")) | AA19: =IF(A19="","",COUNTIF(kb_minuta_recomendacion!$A$2:$A$2000,A19)-Z19)
A20: MH-019 | B20: ALF Sandwiches | C20: ALF Sandwiches | D20: Nicolás de Piérola 431, Barranco | E20: Barranco | F20: 45586 | G20: 19:00 | J20: FAST_FOOD | L20: 1 | P20: 322.45 | S20: SIN_DATO | T20: Yomira Mora, Brandon Grados | U20: Einar Paulsen | W20: Minuta de Visita Técnica - ALF SANDWICHES.pdf | X20: Ya tiene 1 Sunmi V2 Pro con IDPos. Ventas rápidas en caja: no se consideran las mesas. Router a 12 m de la caja. | Y20: =IF(A20="","",COUNTIF(kb_minuta_respuesta!$A$2:$A$2000,A20)) | Z20: =IF(A20="","",COUNTIFS(kb_minuta_recomendacion!$A$2:$A$2000,A20,kb_minuta_recomendacion!$C$2:$C$2000,"RECOMENDACION")) | AA20: =IF(A20="","",COUNTIF(kb_minuta_recomendacion!$A$2:$A$2000,A20)-Z20)
A21: MH-020 | B21: La Carpita del Sabor | C21: La Carpita del Sabor | D21: Av. San Luis 2656, San Borja 15037 | E21: San Borja | F21: 45665 | G21: 22:00 | J21: RESTAURANTE | K21: 2 | L21: 1 | S21: SIN_DATO | T21: Kevin | U21: Yessenia | W21: Minuta de Visita técnica - La Carpita del Sabor.pdf | X21: Restaurante con barras. Router y switch en caja. Impresoras: caja, cocina, bebidas/postres/vinos (piso 1) y barra piso 2–terraza. Reestructurar el cableado no impide el inicio. El PDF llegó dos veces. | Y21: =IF(A21="","",COUNTIF(kb_minuta_respuesta!$A$2:$A$2000,A21)) | Z21: =IF(A21="","",COUNTIFS(kb_minuta_recomendacion!$A$2:$A$2000,A21,kb_minuta_recomendacion!$C$2:$C$2000,"RECOMENDACION")) | AA21: =IF(A21="","",COUNTIF(kb_minuta_recomendacion!$A$2:$A$2000,A21)-Z21)
A22: MH-021 | B22: Los Juárez | C22: Los Juárez Asia | D22: Boulevard de Asia | E22: Asia | F22: 46021 | G22: 12:30 | H22: POR_INAUGURAR | J22: RESTOBAR | K22: 2 | N22: NO_TIENE | S22: SIN_DATO | T22: Kevin | U22: Jesús Pinto | W22: Minuta de visita técnica - Los Juarez Asia.pdf | X22: Aún sin puntos de red ni servicio de internet, y sin impresoras. Adquirirá Sunmi con Izipay, impresoras y 2 pantallas para caja. | Y22: =IF(A22="","",COUNTIF(kb_minuta_respuesta!$A$2:$A$2000,A22)) | Z22: =IF(A22="","",COUNTIFS(kb_minuta_recomendacion!$A$2:$A$2000,A22,kb_minuta_recomendacion!$C$2:$C$2000,"RECOMENDACION")) | AA22: =IF(A22="","",COUNTIF(kb_minuta_recomendacion!$A$2:$A$2000,A22)-Z22)
A23: MH-022 | B23: Mala Vida | C23: Mala Vida | D23: Calle Tarata 150, Miraflores | E23: Miraflores | F23: 45786 | G23: 11:00 | J23: DISCOTECA_BAR | M23: WIN | S23: SIN_DATO | T23: Kevin, Sera | U23: Eduardo Salas | W23: Minuta de Visita técnica - Mala Vida.docx | X23: Entrega de equipos antes del inicio. Barra 1: 2 Sunmi T2 mini + impresora 3nStar RPT008; Barra 2: 1 Sunmi T2 mini + impresora. La laptop no se queda: viabilizar Raspberry o la PC del DJ. Claves WiFi y usuario de la laptop: ver hoja kb_minuta_credencial. | Y23: =IF(A23="","",COUNTIF(kb_minuta_respuesta!$A$2:$A$2000,A23)) | Z23: =IF(A23="","",COUNTIFS(kb_minuta_recomendacion!$A$2:$A$2000,A23,kb_minuta_recomendacion!$C$2:$C$2000,"RECOMENDACION")) | AA23: =IF(A23="","",COUNTIF(kb_minuta_recomendacion!$A$2:$A$2000,A23)-Z23)
A24: MH-023 | B24: Huambra | C24: Huambra | D24: Miraflores | E24: Miraflores | F24: 45607 | G24: 15:00 | J24: RESTAURANTE | L24: 1 | R24: 192.168.18.x | S24: SIN_DATO | T24: Kevin | U24: Juan Pablo | W24: Minuta de Visita Técnica Huambra.docx | X24: Instalación: Raspberry en caja; impresoras caja, barra, cocina y empaquetados en el mismo segmento; pantallas Sunmi D2 mini en patio y salón principal. | Y24: =IF(A24="","",COUNTIF(kb_minuta_respuesta!$A$2:$A$2000,A24)) | Z24: =IF(A24="","",COUNTIFS(kb_minuta_recomendacion!$A$2:$A$2000,A24,kb_minuta_recomendacion!$C$2:$C$2000,"RECOMENDACION")) | AA24: =IF(A24="","",COUNTIF(kb_minuta_recomendacion!$A$2:$A$2000,A24)-Z24)
A25: MH-024 | B25: Saltao | C25: Saltao Larcomar | D25: Sótano 3 Larcomar (patio de comidas) | E25: Miraflores | F25: 45332 | G25: 11:00 | J25: FAST_FOOD | L25: 1 | M25: ENTEL | N25: CHIP | R25: 192.168.0.x | S25: SIN_DATO | T25: Kevin Flores | U25: Vanessa Chinen, Sharon Rabanal | W25: Minuta Instalación Técnica Saltao Larcomar.docx | X25: Patio de comidas: TP-Link con chip Entel. Sin puntos de red; la cobertura WiFi no llega al 100 %: TP-Link en el punto más alto con canaleta y extensión. Clave del TP-Link, red WiFi y puerto del Raspberry: ver hoja kb_minuta_credencial. Ubicación (Larcomar o El Refugio) por confirmar con el equipo. | Y25: =IF(A25="","",COUNTIF(kb_minuta_respuesta!$A$2:$A$2000,A25)) | Z25: =IF(A25="","",COUNTIFS(kb_minuta_recomendacion!$A$2:$A$2000,A25,kb_minuta_recomendacion!$C$2:$C$2000,"RECOMENDACION")) | AA25: =IF(A25="","",COUNTIF(kb_minuta_recomendacion!$A$2:$A$2000,A25)-Z25)
A26: MH-025 | B26: Maki Sam | C26: Maki Sam Real Plaza | D26: Real Plaza Trujillo | E26: Trujillo | F26: 45580 | G26: 10:00 | J26: REST_ORIENTAL | L26: 1 | N26: FIBRA | R26: 192.168.1.x | S26: SIN_DATO | T26: Kimberly Huamani | U26: Vanessa | W26: Minuta Técnica Maki Sam Real plaza.docx | X26: Tercer local, en patio de comidas. 4 impresoras Bienex (caja, barra sushi, bar, cocina) pasadas al mismo segmento con cable USB; laptop propia del local. ID de AnyDesk: ver hoja kb_minuta_credencial. | Y26: =IF(A26="","",COUNTIF(kb_minuta_respuesta!$A$2:$A$2000,A26)) | Z26: =IF(A26="","",COUNTIFS(kb_minuta_recomendacion!$A$2:$A$2000,A26,kb_minuta_recomendacion!$C$2:$C$2000,"RECOMENDACION")) | AA26: =IF(A26="","",COUNTIF(kb_minuta_recomendacion!$A$2:$A$2000,A26)-Z26)
A27: MH-026 | B27: Maki Sam | C27: Maki Sam Primavera | D27: Maki Sam sede centro | F27: 45580 | H27: EN_OPERACION | I27: La impresora de caja se conecta y desconecta: la entrada del cable de red está floja | J27: REST_ORIENTAL | L27: 1 | S27: SIN_DATO | T27: Kimberly Huamani | U27: Kelly Sayan | W27: Minuta Técnica makisamprimavera.docx | X27: Minuta corta: solo antecedentes. | Y27: =IF(A27="","",COUNTIF(kb_minuta_respuesta!$A$2:$A$2000,A27)) | Z27: =IF(A27="","",COUNTIFS(kb_minuta_recomendacion!$A$2:$A$2000,A27,kb_minuta_recomendacion!$C$2:$C$2000,"RECOMENDACION")) | AA27: =IF(A27="","",COUNTIF(kb_minuta_recomendacion!$A$2:$A$2000,A27)-Z27)
A28: MH-027 | B28: Gourmety | C28: Gourmety | D28: Av. Rivera Navarrete 575, San Isidro | E28: San Isidro | F28: 45727 | G28: 12:30 | H28: EN_OBRA | J28: CAFETERIA | K28: 2 | L28: 1 | S28: SIN_DATO | T28: Fabián Guadiamos, Sera Ghafari | U28: Joanna | W28: Minuta Visita Técnica - Gourmety 11.03.22 (1).docx | X28: Local en obra: puntos de red y de corriente se instalan del 16 al 22/03. El nombre del archivo dice 11.03.22, pero la fecha es 2025. | Y28: =IF(A28="","",COUNTIF(kb_minuta_respuesta!$A$2:$A$2000,A28)) | Z28: =IF(A28="","",COUNTIFS(kb_minuta_recomendacion!$A$2:$A$2000,A28,kb_minuta_recomendacion!$C$2:$C$2000,"RECOMENDACION")) | AA28: =IF(A28="","",COUNTIF(kb_minuta_recomendacion!$A$2:$A$2000,A28)-Z28)
A29: MH-028 | B29: Bros | C29: Bros – Refugio Gastronómico | D29: Refugio Gastronómico | E29: Santiago de Surco | F29: 45372 | G29: 13:00 | J29: FAST_FOOD | L29: 1 | P29: 94.42 | S29: SIN_DATO | T29: Nelson Luque | U29: Vanessa, Elio | W29: Minuta Visita Técnica bros.docx | X29: Patio gastronómico. Laptop conectada directo al router. Las minutas de Juicy Lucy – Larco (y V2) tienen este mismo texto: no se cargaron. | Y29: =IF(A29="","",COUNTIF(kb_minuta_respuesta!$A$2:$A$2000,A29)) | Z29: =IF(A29="","",COUNTIFS(kb_minuta_recomendacion!$A$2:$A$2000,A29,kb_minuta_recomendacion!$C$2:$C$2000,"RECOMENDACION")) | AA29: =IF(A29="","",COUNTIF(kb_minuta_recomendacion!$A$2:$A$2000,A29)-Z29)
A30: MH-029 | B30: El Chito | C30: El Chito | F30: 45210 | G30: 16:00 | J30: REST_PESCADOS | L30: 1 | M30: MOVISTAR | N30: FIBRA | O30: 1000 | S30: SIN_DATO | T30: Kevin Flores | U30: Leonardo, Rosbeyli | W30: Minuta Visita Técnica El Chito.docx | X30: El cableado y los puntos de red se estaban instalando ese día. Impresoras: cocina y caja-barra. | Y30: =IF(A30="","",COUNTIF(kb_minuta_respuesta!$A$2:$A$2000,A30)) | Z30: =IF(A30="","",COUNTIFS(kb_minuta_recomendacion!$A$2:$A$2000,A30,kb_minuta_recomendacion!$C$2:$C$2000,"RECOMENDACION")) | AA30: =IF(A30="","",COUNTIF(kb_minuta_recomendacion!$A$2:$A$2000,A30)-Z30)
A31: MH-030 | B31: Shimaya Ramen | C31: Shimaya Comas | D31: Av. Los Ángeles 602, local FC-3041, 3er nivel | E31: Comas | F31: 45360 | G31: 11:00 | J31: REST_ORIENTAL | L31: 1 | M31: WIN | N31: FIBRA | R31: 192.168.100.x | S31: SIN_DATO | T31: Kevin | U31: Yanina | W31: Visita Técnica Shimaya - Comas.docx | X31: Impresoras caja, ramen, salteados, frituras y makis por cable; 2 cables de cámaras en el mismo switch y cables de cámara sueltos. Clave WiFi: ver hoja kb_minuta_credencial. | Y31: =IF(A31="","",COUNTIF(kb_minuta_respuesta!$A$2:$A$2000,A31)) | Z31: =IF(A31="","",COUNTIFS(kb_minuta_recomendacion!$A$2:$A$2000,A31,kb_minuta_recomendacion!$C$2:$C$2000,"RECOMENDACION")) | AA31: =IF(A31="","",COUNTIF(kb_minuta_recomendacion!$A$2:$A$2000,A31)-Z31)
A32: MH-031 | B32: Shimaya Ramen | C32: Shimaya La Molina | D32: Av. Flora Tristán 471, La Molina 15024 | E32: La Molina | F32: 45366 | G32: 11:00 | J32: REST_ORIENTAL | L32: 1 | M32: CLARO | N32: COAXIAL | O32: 100 | S32: SIN_DATO | T32: Kevin | W32: Minuta visita Técnica Shimaya Ramen - La Molina.docx | X32: Claro HFC. Switch principal 10/100 con cámaras, PC de caja e impresora. 3 access points (barra makis, salón zona B, entrada). WiFi libre para clientes. Caja USB con la PC. Tablets de mozos. Clave WiFi: ver hoja kb_minuta_credencial. | Y32: =IF(A32="","",COUNTIF(kb_minuta_respuesta!$A$2:$A$2000,A32)) | Z32: =IF(A32="","",COUNTIFS(kb_minuta_recomendacion!$A$2:$A$2000,A32,kb_minuta_recomendacion!$C$2:$C$2000,"RECOMENDACION")) | AA32: =IF(A32="","",COUNTIF(kb_minuta_recomendacion!$A$2:$A$2000,A32)-Z32)
A33: MH-032 | B33: Shimaya Ramen | C33: Shimaya Kennedy (Miraflores) | D33: Av. Diagonal 344, Miraflores | E33: Miraflores | F33: 45364 | G33: 16:00 | J33: REST_ORIENTAL | L33: 1 | M33: MOVISTAR | O33: 100 | S33: SIN_DATO | T33: Kevin Flores | U33: Gabriela | W33: Minuta Visita Técnica Shimaya Ramen-Miraflores.docx | X33: Switch 10/100 TP-Link con cámaras, PC de caja e impresoras. Caja USB. Frituras: punto de red por cambiar; Makis: RJ45 por cambiar. Tablets por WiFi. | Y33: =IF(A33="","",COUNTIF(kb_minuta_respuesta!$A$2:$A$2000,A33)) | Z33: =IF(A33="","",COUNTIFS(kb_minuta_recomendacion!$A$2:$A$2000,A33,kb_minuta_recomendacion!$C$2:$C$2000,"RECOMENDACION")) | AA33: =IF(A33="","",COUNTIF(kb_minuta_recomendacion!$A$2:$A$2000,A33)-Z33)
A34: MH-033 | B34: Modonese | C34: Modonese Arica | D34: Jr. Arica 880 | F34: 45605 | H34: EN_OPERACION | I34: El local reportaba lentitud de red | J34: REST_PESCADOS | L34: 1 | N34: FIBRA | O34: 400 | S34: SIN_DATO | T34: Kevin | U34: Diego (caja) | V34: SI | W34: Minuta Visita Técnica Modonese Arica.docx | X34: Red estable en la visita. Tablet de caja por WiFi (−37 dBm, estable). Cable de cámaras junto a corriente y bajo un equipo con motor: ruido hasta el router. Se cambió el cable Cat5e por Cat6a hacia el Raspberry. | Y34: =IF(A34="","",COUNTIF(kb_minuta_respuesta!$A$2:$A$2000,A34)) | Z34: =IF(A34="","",COUNTIFS(kb_minuta_recomendacion!$A$2:$A$2000,A34,kb_minuta_recomendacion!$C$2:$C$2000,"RECOMENDACION")) | AA34: =IF(A34="","",COUNTIF(kb_minuta_recomendacion!$A$2:$A$2000,A34)-Z34)
A35: MH-034 | B35: Omakase | C35: Omakase | D35: Santiago de Compostela, La Molina 15026 | E35: La Molina | F35: 45243 | G35: 15:00 | J35: REST_ORIENTAL | L35: 1 | S35: SIN_DATO | T35: Sandra | U35: Keyri, Álvaro | W35: Minuta Visita Técnica OMAKASE.docx | X35: Sin acceso al cuarto de telecomunicaciones: solo test por WiFi. Trabajan desde un celular por WiFi; posible laptop temporal. La barra principal no tiene punto de red. El cliente no desea el Raspberry. | Y35: =IF(A35="","",COUNTIF(kb_minuta_respuesta!$A$2:$A$2000,A35)) | Z35: =IF(A35="","",COUNTIFS(kb_minuta_recomendacion!$A$2:$A$2000,A35,kb_minuta_recomendacion!$C$2:$C$2000,"RECOMENDACION")) | AA35: =IF(A35="","",COUNTIF(kb_minuta_recomendacion!$A$2:$A$2000,A35)-Z35)
A36: MH-035 | B36: Shimaya Ramen | C36: Shimaya Chorrillos | D36: Av. Defensores del Morro 448, Chorrillos | E36: Chorrillos | F36: 45363 | G36: 11:00 | J36: REST_ORIENTAL | L36: 1 | M36: MOVISTAR | N36: COAXIAL | O36: 250 | S36: SIN_DATO | T36: Kevin | U36: Shinjuu | W36: Minuta de Visita tecnica Shimaya chorrillos .docx | X36: Movistar HFC. Switch TP-Link 10/100. Puntos de red: PC de caja e impresoras caja, makis, frituras, ramen, salteados y pre-cuentas. Tablets. Clave WiFi: ver hoja kb_minuta_credencial. | Y36: =IF(A36="","",COUNTIF(kb_minuta_respuesta!$A$2:$A$2000,A36)) | Z36: =IF(A36="","",COUNTIFS(kb_minuta_recomendacion!$A$2:$A$2000,A36,kb_minuta_recomendacion!$C$2:$C$2000,"RECOMENDACION")) | AA36: =IF(A36="","",COUNTIF(kb_minuta_recomendacion!$A$2:$A$2000,A36)-Z36)
A37: MH-036 | B37: Shimaya Ramen | C37: Shimaya Los Olivos | D37: Av. Carlos Izaguirre 789 | E37: Los Olivos | F37: 45360 | G37: 16:00 | J37: REST_ORIENTAL | L37: 1 | M37: WIN | N37: FIBRA | O37: 400 | R37: 192.168.18.x | S37: SIN_DATO | T37: Kevin | U37: Yrama | W37: Minuta visita Técnica Shimaya Los Olivos.docx | X37: La impresora de caja (de red) pierde conexión por cable mal ponchado (norma A, cruzado). RJ45 de makis por cambiar. Switch de 8 puertos 10/100. | Y37: =IF(A37="","",COUNTIF(kb_minuta_respuesta!$A$2:$A$2000,A37)) | Z37: =IF(A37="","",COUNTIFS(kb_minuta_recomendacion!$A$2:$A$2000,A37,kb_minuta_recomendacion!$C$2:$C$2000,"RECOMENDACION")) | AA37: =IF(A37="","",COUNTIF(kb_minuta_recomendacion!$A$2:$A$2000,A37)-Z37)
A38: MH-037 | B38: Shimaya Ramen | C38: Shimaya SJL | D38: Av. Lurigancho 997-999, tienda B-3006, Urb. Zárate Industrial | E38: San Juan de Lurigancho | F38: 45367 | G38: 11:00 | J38: REST_ORIENTAL | L38: 1 | M38: WIN | O38: 400 | S38: SIN_DATO | T38: Kevin | U38: Alvani | W38: Minuta visita Técnica Shimaya Ramen - SJL.docx | X38: Switch con PC de caja, cámaras e impresoras. Caja USB con la PC. 5 tablets de mozos. | Y38: =IF(A38="","",COUNTIF(kb_minuta_respuesta!$A$2:$A$2000,A38)) | Z38: =IF(A38="","",COUNTIFS(kb_minuta_recomendacion!$A$2:$A$2000,A38,kb_minuta_recomendacion!$C$2:$C$2000,"RECOMENDACION")) | AA38: =IF(A38="","",COUNTIF(kb_minuta_recomendacion!$A$2:$A$2000,A38)-Z38)
A39: MH-038 | B39: Shimaya Ramen | C39: Shimaya San Borja | D39: Av. Aviación 3341, San Borja | E39: San Borja | F39: 45365 | G39: 11:00 | J39: REST_ORIENTAL | L39: 1 | M39: MOVISTAR | N39: FIBRA | P39: 350 | S39: SIN_DATO | T39: Kevin | U39: Daya | W39: Minuta Visita Técnica Shimaya Ramen-San Borja.docx | X39: Velocidad medida en la laptop de ID. Switch 10/100 TP-Link con cámaras, PC de caja e impresoras. Caja USB. RJ45 de frituras por cambiar. 5 tablets Lenovo. | Y39: =IF(A39="","",COUNTIF(kb_minuta_respuesta!$A$2:$A$2000,A39)) | Z39: =IF(A39="","",COUNTIFS(kb_minuta_recomendacion!$A$2:$A$2000,A39,kb_minuta_recomendacion!$C$2:$C$2000,"RECOMENDACION")) | AA39: =IF(A39="","",COUNTIF(kb_minuta_recomendacion!$A$2:$A$2000,A39)-Z39)
A40: MH-039 | B40: Caleta | C40: Caleta de la Punta – Callao | D40: Malecón Pardo 180, La Punta 07021 | E40: La Punta | F40: 45783 | G40: 09:00 | J40: REST_PESCADOS | L40: 2 | M40: WIN | O40: 100 | S40: SIN_DATO | T40: Kevin | U40: Briggitte, Andrea | W40: Minuta de Visita técnica - Caleta Callao.docx | X40: Dos lugares de preparación (Caleta 01 y 02), cada uno con su PC e impresora 3nStar RPT006B. 2 tablets Samsung. Claves WiFi: ver hoja kb_minuta_credencial. | Y40: =IF(A40="","",COUNTIF(kb_minuta_respuesta!$A$2:$A$2000,A40)) | Z40: =IF(A40="","",COUNTIFS(kb_minuta_recomendacion!$A$2:$A$2000,A40,kb_minuta_recomendacion!$C$2:$C$2000,"RECOMENDACION")) | AA40: =IF(A40="","",COUNTIF(kb_minuta_recomendacion!$A$2:$A$2000,A40)-Z40)
A41: MH-040 | B41: Don Chalán | C41: Don Chalán Unicachi – PRO | D41: Unicachi PRO | F41: 45358 | G41: 14:00 | J41: REST_PESCADOS | L41: 1 | M41: WIN | N41: FIBRA | S41: SIN_DATO | T41: Nelson Luque | U41: Don Chalán | W41: Formato_de_Minuta_Visita_Técnica_DON_CHALAN.docx | X41: Barra junto a la caja (impresora Bar-Caja). La impresora de cocina está deshabilitada por falta de cableado. Repetidor de red. Clave WiFi: ver hoja kb_minuta_credencial. | Y41: =IF(A41="","",COUNTIF(kb_minuta_respuesta!$A$2:$A$2000,A41)) | Z41: =IF(A41="","",COUNTIFS(kb_minuta_recomendacion!$A$2:$A$2000,A41,kb_minuta_recomendacion!$C$2:$C$2000,"RECOMENDACION")) | AA41: =IF(A41="","",COUNTIF(kb_minuta_recomendacion!$A$2:$A$2000,A41)-Z41)
A42: MH-041 | B42: Soma | C42: Soma (El Refugio) | D42: Av. Manuel Olguín 100, Santiago de Surco 15023 | E42: Santiago de Surco | F42: 45912 | G42: 14:40 | J42: DISCOTECA_BAR | N42: NO_TIENE | S42: SIN_DATO | T42: Leonardo Espejo | W42: Minuta de visita técnica - Soma (El refugio).docx | X42: Sin internet, router, switch ni cableado. Patio principal de ~18 m, con tomas a ~7 m y ~3,5 m. Si está en patio de comidas (El Refugio) está por confirmar. | Y42: =IF(A42="","",COUNTIF(kb_minuta_respuesta!$A$2:$A$2000,A42)) | Z42: =IF(A42="","",COUNTIFS(kb_minuta_recomendacion!$A$2:$A$2000,A42,kb_minuta_recomendacion!$C$2:$C$2000,"RECOMENDACION")) | AA42: =IF(A42="","",COUNTIF(kb_minuta_recomendacion!$A$2:$A$2000,A42)-Z42)
A43: MH-042 | B43: Belgofre | C43: Belgofre Javier Prado | F43: 45748 | H43: EN_OPERACION | I43: Envío y conexión del Raspberry al local | J43: FAST_FOOD | L43: 1 | S43: SIN_DATO | T43: Marco | U43: Belgofre | W43: Minuta Visita Técnica Belgofre 01-04.docx | X43: El 4.º puerto del router no daba conexión: la impresora pasó al 3.er puerto. El gancho del RJ45 de la impresora estaba roto. | Y43: =IF(A43="","",COUNTIF(kb_minuta_respuesta!$A$2:$A$2000,A43)) | Z43: =IF(A43="","",COUNTIFS(kb_minuta_recomendacion!$A$2:$A$2000,A43,kb_minuta_recomendacion!$C$2:$C$2000,"RECOMENDACION")) | AA43: =IF(A43="","",COUNTIF(kb_minuta_recomendacion!$A$2:$A$2000,A43)-Z43)
A44: MH-043 | B44: Flora y Fauna | C44: Flora y Fauna San Miguel | D44: San Miguel | E44: San Miguel | F44: 46198 | G44: 15:00 | H44: SISTEMA_ANTERIOR | J44: RETAIL | L44: 2 | P44: 52.51 | Q44: 57.55 | R44: 192.168.10.x | S44: SIN_DATO | U44: Pedro Ly | W44: Flora y Fauna Miraflores Sede San Miguel - Minuta de visita técnica.pdf | X44: Retail de alimentos saludables. Cajas por Ethernet (Caja 02: 56.11/57.01 Mbps). La impresora de Caja 02 está en 192.168.1.87 (otro segmento, DHCP desactivado); la de Caja 01 tiene DHCP activado. Periféricos: balanza/escáner Magellan, escáner de mano, gaveta, impresora de etiquetas TSC, Niubiz. La balanza de Caja 02 falla. No se identificó impedimento de inicio. | Y44: =IF(A44="","",COUNTIF(kb_minuta_respuesta!$A$2:$A$2000,A44)) | Z44: =IF(A44="","",COUNTIFS(kb_minuta_recomendacion!$A$2:$A$2000,A44,kb_minuta_recomendacion!$C$2:$C$2000,"RECOMENDACION")) | AA44: =IF(A44="","",COUNTIF(kb_minuta_recomendacion!$A$2:$A$2000,A44)-Z44)
A45: MH-044 | B45: Verbena | C45: Verbena | D45: Av. Conquistadores 396 | E45: San Isidro | F45: 45801 | G45: 16:00 | J45: RESTAURANTE | L45: 1 | M45: CLARO | S45: SIN_DATO | T45: Yomira Mora | U45: Marian Jiménez | W45: Minuta Visita Técnica Verbena.pdf | X45: Zonas: terraza (6 mesas), privado (2), alfombra (3), individuales (2), mesa barra y mesa amor. Impresoras de red de bar y cocina juntas; tablet para pedidos. Pago con Culqi. Clave WiFi: ver hoja kb_minuta_credencial. | Y45: =IF(A45="","",COUNTIF(kb_minuta_respuesta!$A$2:$A$2000,A45)) | Z45: =IF(A45="","",COUNTIFS(kb_minuta_recomendacion!$A$2:$A$2000,A45,kb_minuta_recomendacion!$C$2:$C$2000,"RECOMENDACION")) | AA45: =IF(A45="","",COUNTIF(kb_minuta_recomendacion!$A$2:$A$2000,A45)-Z45)
Y46: =IF(A46="","",COUNTIF(kb_minuta_respuesta!$A$2:$A$2000,A46)) | Z46: =IF(A46="","",COUNTIFS(kb_minuta_recomendacion!$A$2:$A$2000,A46,kb_minuta_recomendacion!$C$2:$C$2000,"RECOMENDACION")) | AA46: =IF(A46="","",COUNTIF(kb_minuta_recomendacion!$A$2:$A$2000,A46)-Z46)
Y47: =IF(A47="","",COUNTIF(kb_minuta_respuesta!$A$2:$A$2000,A47)) | Z47: =IF(A47="","",COUNTIFS(kb_minuta_recomendacion!$A$2:$A$2000,A47,kb_minuta_recomendacion!$C$2:$C$2000,"RECOMENDACION")) | AA47: =IF(A47="","",COUNTIF(kb_minuta_recomendacion!$A$2:$A$2000,A47)-Z47)
Y48: =IF(A48="","",COUNTIF(kb_minuta_respuesta!$A$2:$A$2000,A48)) | Z48: =IF(A48="","",COUNTIFS(kb_minuta_recomendacion!$A$2:$A$2000,A48,kb_minuta_recomendacion!$C$2:$C$2000,"RECOMENDACION")) | AA48: =IF(A48="","",COUNTIF(kb_minuta_recomendacion!$A$2:$A$2000,A48)-Z48)
Y49: =IF(A49="","",COUNTIF(kb_minuta_respuesta!$A$2:$A$2000,A49)) | Z49: =IF(A49="","",COUNTIFS(kb_minuta_recomendacion!$A$2:$A$2000,A49,kb_minuta_recomendacion!$C$2:$C$2000,"RECOMENDACION")) | AA49: =IF(A49="","",COUNTIF(kb_minuta_recomendacion!$A$2:$A$2000,A49)-Z49)
Y50: =IF(A50="","",COUNTIF(kb_minuta_respuesta!$A$2:$A$2000,A50)) | Z50: =IF(A50="","",COUNTIFS(kb_minuta_recomendacion!$A$2:$A$2000,A50,kb_minuta_recomendacion!$C$2:$C$2000,"RECOMENDACION")) | AA50: =IF(A50="","",COUNTIF(kb_minuta_recomendacion!$A$2:$A$2000,A50)-Z50)
Y51: =IF(A51="","",COUNTIF(kb_minuta_respuesta!$A$2:$A$2000,A51)) | Z51: =IF(A51="","",COUNTIFS(kb_minuta_recomendacion!$A$2:$A$2000,A51,kb_minuta_recomendacion!$C$2:$C$2000,"RECOMENDACION")) | AA51: =IF(A51="","",COUNTIF(kb_minuta_recomendacion!$A$2:$A$2000,A51)-Z51)
Y52: =IF(A52="","",COUNTIF(kb_minuta_respuesta!$A$2:$A$2000,A52)) | Z52: =IF(A52="","",COUNTIFS(kb_minuta_recomendacion!$A$2:$A$2000,A52,kb_minuta_recomendacion!$C$2:$C$2000,"RECOMENDACION")) | AA52: =IF(A52="","",COUNTIF(kb_minuta_recomendacion!$A$2:$A$2000,A52)-Z52)
Y53: =IF(A53="","",COUNTIF(kb_minuta_respuesta!$A$2:$A$2000,A53)) | Z53: =IF(A53="","",COUNTIFS(kb_minuta_recomendacion!$A$2:$A$2000,A53,kb_minuta_recomendacion!$C$2:$C$2000,"RECOMENDACION")) | AA53: =IF(A53="","",COUNTIF(kb_minuta_recomendacion!$A$2:$A$2000,A53)-Z53)
Y54: =IF(A54="","",COUNTIF(kb_minuta_respuesta!$A$2:$A$2000,A54)) | Z54: =IF(A54="","",COUNTIFS(kb_minuta_recomendacion!$A$2:$A$2000,A54,kb_minuta_recomendacion!$C$2:$C$2000,"RECOMENDACION")) | AA54: =IF(A54="","",COUNTIF(kb_minuta_recomendacion!$A$2:$A$2000,A54)-Z54)
Y55: =IF(A55="","",COUNTIF(kb_minuta_respuesta!$A$2:$A$2000,A55)) | Z55: =IF(A55="","",COUNTIFS(kb_minuta_recomendacion!$A$2:$A$2000,A55,kb_minuta_recomendacion!$C$2:$C$2000,"RECOMENDACION")) | AA55: =IF(A55="","",COUNTIF(kb_minuta_recomendacion!$A$2:$A$2000,A55)-Z55)
Y56: =IF(A56="","",COUNTIF(kb_minuta_respuesta!$A$2:$A$2000,A56)) | Z56: =IF(A56="","",COUNTIFS(kb_minuta_recomendacion!$A$2:$A$2000,A56,kb_minuta_recomendacion!$C$2:$C$2000,"RECOMENDACION")) | AA56: =IF(A56="","",COUNTIF(kb_minuta_recomendacion!$A$2:$A$2000,A56)-Z56)
Y57: =IF(A57="","",COUNTIF(kb_minuta_respuesta!$A$2:$A$2000,A57)) | Z57: =IF(A57="","",COUNTIFS(kb_minuta_recomendacion!$A$2:$A$2000,A57,kb_minuta_recomendacion!$C$2:$C$2000,"RECOMENDACION")) | AA57: =IF(A57="","",COUNTIF(kb_minuta_recomendacion!$A$2:$A$2000,A57)-Z57)
... Y75: =IF(A75="","",COUNTIF(kb_minuta_respuesta!$A$2:$A$2000,A75)) | Z75: =IF(A75="","",COUNTIFS(kb_minuta_recomendacion!$A$2:$A$2000,A75,kb_minuta_recomendacion!$C$2:$C$2000,"RECOMENDACION")) | AA75: =IF(A75="","",COUNTIF(kb_minuta_recomendacion!$A$2:$A$2000,A75)-Z75)

Sheet kb_minuta_respuesta
A1: minuta_id | B1: pregunta_id | C1: alcance | D1: valor | E1: confianza | F1: fuente_en_minuta | G1: texto_pregunta
A2: MH-001 | B2: P01 | D2: Sicilia | E2: EXPLICITO | F2: Título de la minuta | G2: =IF(B2="","",IFERROR(INDEX(ref_preguntas!$C$2:$C$200,MATCH(B2,ref_preguntas!$A$2:$A$200,0)),"ID no existe"))
A3: MH-001 | B3: P03 | D3: Patio Gastronómico Refugio | E3: EXPLICITO | F3: Lugar | G3: =IF(B3="","",IFERROR(INDEX(ref_preguntas!$C$2:$C$200,MATCH(B3,ref_preguntas!$A$2:$A$200,0)),"ID no existe"))
A4: MH-001 | B4: P04 | D4: Kathy | E4: EXPLICITO | F4: Team cliente | G4: =IF(B4="","",IFERROR(INDEX(ref_preguntas!$C$2:$C$200,MATCH(B4,ref_preguntas!$A$2:$A$200,0)),"ID no existe"))
A5: MH-001 | B5: P06 | D5: 2023-10-03 | E5: EXPLICITO | F5: Fecha y hora | G5: =IF(B5="","",IFERROR(INDEX(ref_preguntas!$C$2:$C$200,MATCH(B5,ref_preguntas!$A$2:$A$200,0)),"ID no existe"))
A6: MH-001 | B6: P11 | D6: COCINA, TERRAZA | E6: INFERIDO | F6: Recomendaciones mencionan cocina y terraza | G6: =IF(B6="","",IFERROR(INDEX(ref_preguntas!$C$2:$C$200,MATCH(B6,ref_preguntas!$A$2:$A$200,0)),"ID no existe"))
A7: MH-001 | B7: P38 | D7: NO | E7: INFERIDO | F7: La impresora de cocina está lejos del punto de red | G7: =IF(B7="","",IFERROR(INDEX(ref_preguntas!$C$2:$C$200,MATCH(B7,ref_preguntas!$A$2:$A$200,0)),"ID no existe"))
A8: MH-001 | B8: P50 | D8: SI | E8: EXPLICITO | F8: Siguientes acciones | G8: =IF(B8="","",IFERROR(INDEX(ref_preguntas!$C$2:$C$200,MATCH(B8,ref_preguntas!$A$2:$A$200,0)),"ID no existe"))
A9: MH-001 | B9: P50a | D9: Conexión de impresoras | E9: EXPLICITO | F9: Siguientes acciones | G9: =IF(B9="","",IFERROR(INDEX(ref_preguntas!$C$2:$C$200,MATCH(B9,ref_preguntas!$A$2:$A$200,0)),"ID no existe"))
A10: MH-001 | B10: P51 | D10: ID: Kevin Flores, Yomira Mora · Cliente: Kathy | E10: EXPLICITO | F10: Asistentes | G10: =IF(B10="","",IFERROR(INDEX(ref_preguntas!$C$2:$C$200,MATCH(B10,ref_preguntas!$A$2:$A$200,0)),"ID no existe"))
A11: MH-001 | B11: P12a | D11: SI | E11: INFERIDO | F11: Impresoras en áreas, incluida cocina | G11: =IF(B11="","",IFERROR(INDEX(ref_preguntas!$C$2:$C$200,MATCH(B11,ref_preguntas!$A$2:$A$200,0)),"ID no existe"))
A12: MH-001 | B12: P09 | D12: RESTAURANTE | E12: EXPLICITO | F12: Rubro confirmado por el equipo (2026-10-10) | G12: =IF(B12="","",IFERROR(INDEX(ref_preguntas!$C$2:$C$200,MATCH(B12,ref_preguntas!$A$2:$A$200,0)),"ID no existe"))
A13: MH-002 | B13: P01 | D13: Don Oscar | E13: EXPLICITO | F13: Título de la minuta | G13: =IF(B13="","",IFERROR(INDEX(ref_preguntas!$C$2:$C$200,MATCH(B13,ref_preguntas!$A$2:$A$200,0)),"ID no existe"))
... A27: MH-003 | B27: P11 | D27: BAR, CAJA | E27: INFERIDO | F27: Recomendación: switch en barra para impresora de barra y caja | G27: =IF(B27="","",IFERROR(INDEX(ref_preguntas!$C$2:$C$200,MATCH(B27,ref_preguntas!$A$2:$A$200,0)),"ID no existe"))
A28: MH-003 | B28: P22 | C28: L_CAJAS:1 | D28: SI | E28: INFERIDO | F28: PC con programas de impresión | G28: =IF(B28="","",IFERROR(INDEX(ref_preguntas!$C$2:$C$200,MATCH(B28,ref_preguntas!$A$2:$A$200,0)),"ID no existe"))
A29: MH-003 | B29: P23 | C29: L_CAJAS:1 | D29: WIFI | E29: EXPLICITO | F29: Desarrollo | G29: =IF(B29="","",IFERROR(INDEX(ref_preguntas!$C$2:$C$200,MATCH(B29,ref_preguntas!$A$2:$A$200,0)),"ID no existe"))
A30: MH-003 | B30: P40 | D30: DESORDENADO | E30: EXPLICITO | F30: Desarrollo | G30: =IF(B30="","",IFERROR(INDEX(ref_preguntas!$C$2:$C$200,MATCH(B30,ref_preguntas!$A$2:$A$200,0)),"ID no existe"))
A31: MH-003 | B31: P45 | D31: SI | E31: EXPLICITO | F31: Desarrollo: repetidores | G31: =IF(B31="","",IFERROR(INDEX(ref_preguntas!$C$2:$C$200,MATCH(B31,ref_preguntas!$A$2:$A$200,0)),"ID no existe"))
A32: MH-003 | B32: P51 | D32: ID: Yomira Mora · Cliente: Giancarlo Sanguinetti | E32: EXPLICITO | F32: Asistentes | G32: =IF(B32="","",IFERROR(INDEX(ref_preguntas!$C$2:$C$200,MATCH(B32,ref_preguntas!$A$2:$A$200,0)),"ID no existe"))
A33: MH-003 | B33: P12a | D33: SI | E33: INFERIDO | F33: Impresora de barra | G33: =IF(B33="","",IFERROR(INDEX(ref_preguntas!$C$2:$C$200,MATCH(B33,ref_preguntas!$A$2:$A$200,0)),"ID no existe"))
A34: MH-003 | B34: P09 | D34: REST_PESCADOS | E34: EXPLICITO | F34: Rubro confirmado por el equipo (2026-10-10) | G34: =IF(B34="","",IFERROR(INDEX(ref_preguntas!$C$2:$C$200,MATCH(B34,ref_preguntas!$A$2:$A$200,0)),"ID no existe"))
A35: MH-004 | B35: P01 | D35: Rock & Burgers | E35: EXPLICITO | F35: Título de la minuta | G35: =IF(B35="","",IFERROR(INDEX(ref_preguntas!$C$2:$C$200,MATCH(B35,ref_preguntas!$A$2:$A$200,0)),"ID no existe"))
A36: MH-004 | B36: P03 | D36: C. Luis Colán 242, Huaral 15201 | E36: EXPLICITO | F36: Dirección | G36: =IF(B36="","",IFERROR(INDEX(ref_preguntas!$C$2:$C$200,MATCH(B36,ref_preguntas!$A$2:$A$200,0)),"ID no existe"))
A37: MH-004 | B37: P04 | D37: Gianfranco (equipo operativo) | E37: EXPLICITO | F37: Team cliente | G37: =IF(B37="","",IFERROR(INDEX(ref_preguntas!$C$2:$C$200,MATCH(B37,ref_preguntas!$A$2:$A$200,0)),"ID no existe"))
A38: MH-004 | B38: P06 | D38: 2026-05-31 | E38: EXPLICITO | F38: Fecha y hora | G38: =IF(B38="","",IFERROR(INDEX(ref_preguntas!$C$2:$C$200,MATCH(B38,ref_preguntas!$A$2:$A$200,0)),"ID no existe"))
A39: MH-004 | B39: P10 | D39: 3 | E39: EXPLICITO | F39: Pisos | G39: =IF(B39="","",IFERROR(INDEX(ref_preguntas!$C$2:$C$200,MATCH(B39,ref_preguntas!$A$2:$A$200,0)),"ID no existe"))
A40: MH-004 | B40: P11 | D40: CAJA, COCINA, SALON_1, SALON_2 | E40: INFERIDO | F40: Salones en piso 2 y 3, caja y cocina | G40: =IF(B40="","",IFERROR(INDEX(ref_preguntas!$C$2:$C$200,MATCH(B40,ref_preguntas!$A$2:$A$200,0)),"ID no existe"))
A41: MH-004 | B41: P13 | D41: CLARO | E41: EXPLICITO | F41: Proveedor | G41: =IF(B41="","",IFERROR(INDEX(ref_preguntas!$C$2:$C$200,MATCH(B41,ref_preguntas!$A$2:$A$200,0)),"ID no existe"))
... A43: MH-004 | B43: P18 | D43: CAJA | E43: EXPLICITO | F43: Caja y router principal | G43: =IF(B43="","",IFERROR(INDEX(ref_preguntas!$C$2:$C$200,MATCH(B43,ref_preguntas!$A$2:$A$200,0)),"ID no existe"))
A44: MH-004 | B44: P22 | C44: L_CAJAS:1 | D44: SI | E44: EXPLICITO | F44: Equipos tecnológicos (PC de caja) | G44: =IF(B44="","",IFERROR(INDEX(ref_preguntas!$C$2:$C$200,MATCH(B44,ref_preguntas!$A$2:$A$200,0)),"ID no existe"))
A45: MH-004 | B45: P23 | C45: L_CAJAS:1 | D45: WIFI | E45: EXPLICITO | F45: Equipos tecnológicos | G45: =IF(B45="","",IFERROR(INDEX(ref_preguntas!$C$2:$C$200,MATCH(B45,ref_preguntas!$A$2:$A$200,0)),"ID no existe"))
A46: MH-004 | B46: P26 | D46: 2 | E46: EXPLICITO | F46: Impresoras | G46: =IF(B46="","",IFERROR(INDEX(ref_preguntas!$C$2:$C$200,MATCH(B46,ref_preguntas!$A$2:$A$200,0)),"ID no existe"))
A47: MH-004 | B47: P27 | C47: L_IMPRESORAS:1 | D47: CAJA | E47: EXPLICITO | F47: Impresora de caja (bebidas se preparan en caja) | G47: =IF(B47="","",IFERROR(INDEX(ref_preguntas!$C$2:$C$200,MATCH(B47,ref_preguntas!$A$2:$A$200,0)),"ID no existe"))
A48: MH-004 | B48: P30 | C48: L_IMPRESORAS:1 | D48: USB | E48: EXPLICITO | F48: Especificaciones de impresoras | G48: =IF(B48="","",IFERROR(INDEX(ref_preguntas!$C$2:$C$200,MATCH(B48,ref_preguntas!$A$2:$A$200,0)),"ID no existe"))
A49: MH-004 | B49: P27 | C49: L_IMPRESORAS:2 | D49: COCINA | E49: EXPLICITO | F49: Especificaciones de impresoras | G49: =IF(B49="","",IFERROR(INDEX(ref_preguntas!$C$2:$C$200,MATCH(B49,ref_preguntas!$A$2:$A$200,0)),"ID no existe"))
A50: MH-004 | B50: P29 | C50: L_IMPRESORAS:2 | D50: OTRO | E50: EXPLICITO | F50: Modelo CBX 89E | G50: =IF(B50="","",IFERROR(INDEX(ref_preguntas!$C$2:$C$200,MATCH(B50,ref_preguntas!$A$2:$A$200,0)),"ID no existe"))
A51: MH-004 | B51: P30 | C51: L_IMPRESORAS:2 | D51: CABLE_RED | E51: EXPLICITO | F51: Especificaciones de impresoras | G51: =IF(B51="","",IFERROR(INDEX(ref_preguntas!$C$2:$C$200,MATCH(B51,ref_preguntas!$A$2:$A$200,0)),"ID no existe"))
A52: MH-004 | B52: P45 | D52: SI | E52: EXPLICITO | F52: 2 repetidores | G52: =IF(B52="","",IFERROR(INDEX(ref_preguntas!$C$2:$C$200,MATCH(B52,ref_preguntas!$A$2:$A$200,0)),"ID no existe"))
A53: MH-004 | B53: P51 | D53: ID: Yomira Mora · Cliente: Gianfranco (equipo operativo) | E53: EXPLICITO | F53: Asistentes | G53: =IF(B53="","",IFERROR(INDEX(ref_preguntas!$C$2:$C$200,MATCH(B53,ref_preguntas!$A$2:$A$200,0)),"ID no existe"))
A54: MH-004 | B54: P12a | D54: SI | E54: EXPLICITO | F54: Pruebas de comandas | G54: =IF(B54="","",IFERROR(INDEX(ref_preguntas!$C$2:$C$200,MATCH(B54,ref_preguntas!$A$2:$A$200,0)),"ID no existe"))
A55: MH-004 | B55: P09 | D55: FAST_FOOD | E55: EXPLICITO | F55: Rubro confirmado por el equipo (2026-10-10) | G55: =IF(B55="","",IFERROR(INDEX(ref_preguntas!$C$2:$C$200,MATCH(B55,ref_preguntas!$A$2:$A$200,0)),"ID no existe"))
A56: MH-005 | B56: P01 | D56: Dorcher Bier | E56: EXPLICITO | F56: Título | G56: =IF(B56="","",IFERROR(INDEX(ref_preguntas!$C$2:$C$200,MATCH(B56,ref_preguntas!$A$2:$A$200,0)),"ID no existe"))
A57: MH-005 | B57: P03 | D57: Dorcher San Miguel | E57: EXPLICITO | F57: Lugar | G57: =IF(B57="","",IFERROR(INDEX(ref_preguntas!$C$2:$C$200,MATCH(B57,ref_preguntas!$A$2:$A$200,0)),"ID no existe"))
A58: MH-005 | B58: P04 | D58: Karla Sandoval | E58: EXPLICITO | F58: Team cliente | G58: =IF(B58="","",IFERROR(INDEX(ref_preguntas!$C$2:$C$200,MATCH(B58,ref_preguntas!$A$2:$A$200,0)),"ID no existe"))
A59: MH-005 | B59: P06 | D59: 2023-04-14 | E59: EXPLICITO | F59: Fecha y hora | G59: =IF(B59="","",IFERROR(INDEX(ref_preguntas!$C$2:$C$200,MATCH(B59,ref_preguntas!$A$2:$A$200,0)),"ID no existe"))
A60: MH-005 | B60: P10 | D60: 2 | E60: INFERIDO | F60: Barra 1 y barra 2 (segundo piso) | G60: =IF(B60="","",IFERROR(INDEX(ref_preguntas!$C$2:$C$200,MATCH(B60,ref_preguntas!$A$2:$A$200,0)),"ID no existe"))
A61: MH-005 | B61: P11 | D61: CAJA, BAR, COCINA | E61: EXPLICITO | F61: Desarrollo | G61: =IF(B61="","",IFERROR(INDEX(ref_preguntas!$C$2:$C$200,MATCH(B61,ref_preguntas!$A$2:$A$200,0)),"ID no existe"))
A62: MH-005 | B62: P12 | D62: 3 | E62: EXPLICITO | F62: PC caja 1, 2 y 3 | G62: =IF(B62="","",IFERROR(INDEX(ref_preguntas!$C$2:$C$200,MATCH(B62,ref_preguntas!$A$2:$A$200,0)),"ID no existe"))
A63: MH-005 | B63: P13 | D63: MOVISTAR | E63: EXPLICITO | F63: Equipos pasados a la red Movistar | G63: =IF(B63="","",IFERROR(INDEX(ref_preguntas!$C$2:$C$200,MATCH(B63,ref_preguntas!$A$2:$A$200,0)),"ID no existe"))
... A97: MH-008 | B97: P15 | D97: 20 | E97: EXPLICITO | F97: Plan 20 Mega | G97: =IF(B97="","",IFERROR(INDEX(ref_preguntas!$C$2:$C$200,MATCH(B97,ref_preguntas!$A$2:$A$200,0)),"ID no existe"))
A98: MH-008 | B98: P22 | C98: L_CAJAS:1 | D98: SI | E98: EXPLICITO | F98: PC de caja | G98: =IF(B98="","",IFERROR(INDEX(ref_preguntas!$C$2:$C$200,MATCH(B98,ref_preguntas!$A$2:$A$200,0)),"ID no existe"))
A99: MH-008 | B99: P23 | C99: L_CAJAS:1 | D99: WIFI | E99: EXPLICITO | F99: PC conectada vía WiFi | G99: =IF(B99="","",IFERROR(INDEX(ref_preguntas!$C$2:$C$200,MATCH(B99,ref_preguntas!$A$2:$A$200,0)),"ID no existe"))
A100: MH-008 | B100: P26 | D100: 3 | E100: EXPLICITO | F100: Recepción, Bodegón, Lagar | G100: =IF(B100="","",IFERROR(INDEX(ref_preguntas!$C$2:$C$200,MATCH(B100,ref_preguntas!$A$2:$A$200,0)),"ID no existe"))
A101: MH-008 | B101: P51 | D101: ID: Yomira Mora, Daphne · Cliente: Caleb | E101: EXPLICITO | F101: Asistentes | G101: =IF(B101="","",IFERROR(INDEX(ref_preguntas!$C$2:$C$200,MATCH(B101,ref_preguntas!$A$2:$A$200,0)),"ID no existe"))
A102: MH-008 | B102: P12a | D102: SI | E102: INFERIDO | F102: Lugares de impresión Bodegón y Lagar | G102: =IF(B102="","",IFERROR(INDEX(ref_preguntas!$C$2:$C$200,MATCH(B102,ref_preguntas!$A$2:$A$200,0)),"ID no existe"))
A103: MH-008 | B103: P09 | D103: HOSPEDAJE | E103: EXPLICITO | F103: Rubro confirmado por el equipo (2026-10-10) | G103: =IF(B103="","",IFERROR(INDEX(ref_preguntas!$C$2:$C$200,MATCH(B103,ref_preguntas!$A$2:$A$200,0)),"ID no existe"))
A104: MH-009 | B104: P01 | D104: Rikoton | E104: INFERIDO | F104: Rikoton (RKT); el nombre comercial aparece en RKT Hacienda | G104: =IF(B104="","",IFERROR(INDEX(ref_preguntas!$C$2:$C$200,MATCH(B104,ref_preguntas!$A$2:$A$200,0)),"ID no existe"))
A105: MH-009 | B105: P02 | D105: RKT Banchero | E105: EXPLICITO | F105: Título | G105: =IF(B105="","",IFERROR(INDEX(ref_preguntas!$C$2:$C$200,MATCH(B105,ref_preguntas!$A$2:$A$200,0)),"ID no existe"))
A106: MH-009 | B106: P03 | D106: Av. Santa Rosa 468, Urb. Canto Grande, San Juan de Lurigancho | E106: EXPLICITO | F106: Dirección | G106: =IF(B106="","",IFERROR(INDEX(ref_preguntas!$C$2:$C$200,MATCH(B106,ref_preguntas!$A$2:$A$200,0)),"ID no existe"))
A107: MH-009 | B107: P04 | D107: Fernando | E107: EXPLICITO | F107: Team cliente | G107: =IF(B107="","",IFERROR(INDEX(ref_preguntas!$C$2:$C$200,MATCH(B107,ref_preguntas!$A$2:$A$200,0)),"ID no existe"))
A108: MH-009 | B108: P06 | D108: 2025-06-11 | E108: EXPLICITO | F108: Fecha y hora | G108: =IF(B108="","",IFERROR(INDEX(ref_preguntas!$C$2:$C$200,MATCH(B108,ref_preguntas!$A$2:$A$200,0)),"ID no existe"))
A109: MH-009 | B109: P11 | D109: SALON_1, SALON_2, CAJA, COCINA, BRASAS | E109: EXPLICITO | F109: Imágenes de zonas | G109: =IF(B109="","",IFERROR(INDEX(ref_preguntas!$C$2:$C$200,MATCH(B109,ref_preguntas!$A$2:$A$200,0)),"ID no existe"))
A110: MH-009 | B110: P13 | D110: MOVISTAR | E110: EXPLICITO | F110: Speedtest | G110: =IF(B110="","",IFERROR(INDEX(ref_preguntas!$C$2:$C$200,MATCH(B110,ref_preguntas!$A$2:$A$200,0)),"ID no existe"))
A111: MH-009 | B111: P18 | D111: CAJA | E111: EXPLICITO | F111: Router principal en caja | G111: =IF(B111="","",IFERROR(INDEX(ref_preguntas!$C$2:$C$200,MATCH(B111,ref_preguntas!$A$2:$A$200,0)),"ID no existe"))
... A114: MH-009 | B114: P14 | D114: FIBRA | E114: EXPLICITO | F114: Router conectado a fibra óptica | G114: =IF(B114="","",IFERROR(INDEX(ref_preguntas!$C$2:$C$200,MATCH(B114,ref_preguntas!$A$2:$A$200,0)),"ID no existe"))
A115: MH-009 | B115: P27 | C115: L_IMPRESORAS:1 | D115: CAJA | E115: EXPLICITO | F115: Impresoras | G115: =IF(B115="","",IFERROR(INDEX(ref_preguntas!$C$2:$C$200,MATCH(B115,ref_preguntas!$A$2:$A$200,0)),"ID no existe"))
A116: MH-009 | B116: P30 | C116: L_IMPRESORAS:1 | D116: USB | E116: EXPLICITO | F116: Caja (USB) | G116: =IF(B116="","",IFERROR(INDEX(ref_preguntas!$C$2:$C$200,MATCH(B116,ref_preguntas!$A$2:$A$200,0)),"ID no existe"))
A117: MH-009 | B117: P12a | D117: SI | E117: EXPLICITO | F117: Comandas y pre-cuentas desde tablets | G117: =IF(B117="","",IFERROR(INDEX(ref_preguntas!$C$2:$C$200,MATCH(B117,ref_preguntas!$A$2:$A$200,0)),"ID no existe"))
A118: MH-009 | B118: P09 | D118: POLLERIA | E118: EXPLICITO | F118: Rubro confirmado por el equipo (2026-10-10) | G118: =IF(B118="","",IFERROR(INDEX(ref_preguntas!$C$2:$C$200,MATCH(B118,ref_preguntas!$A$2:$A$200,0)),"ID no existe"))
A119: MH-010 | B119: P01 | D119: Rikoton | E119: INFERIDO | F119: Rikoton (RKT); el nombre comercial aparece en RKT Hacienda | G119: =IF(B119="","",IFERROR(INDEX(ref_preguntas!$C$2:$C$200,MATCH(B119,ref_preguntas!$A$2:$A$200,0)),"ID no existe"))
A120: MH-010 | B120: P02 | D120: RKT Bayóvar | E120: EXPLICITO | F120: Título | G120: =IF(B120="","",IFERROR(INDEX(ref_preguntas!$C$2:$C$200,MATCH(B120,ref_preguntas!$A$2:$A$200,0)),"ID no existe"))
A121: MH-010 | B121: P03 | D121: Cal. Segunda Zona de Bayóvar Mz. 2 Lt. 1, San Juan de Lurigancho | E121: EXPLICITO | F121: Dirección | G121: =IF(B121="","",IFERROR(INDEX(ref_preguntas!$C$2:$C$200,MATCH(B121,ref_preguntas!$A$2:$A$200,0)),"ID no existe"))
A122: MH-010 | B122: P04 | D122: Fernando | E122: EXPLICITO | F122: Team cliente | G122: =IF(B122="","",IFERROR(INDEX(ref_preguntas!$C$2:$C$200,MATCH(B122,ref_preguntas!$A$2:$A$200,0)),"ID no existe"))
A123: MH-010 | B123: P06 | D123: 2025-06-11 | E123: EXPLICITO | F123: Fecha y hora | G123: =IF(B123="","",IFERROR(INDEX(ref_preguntas!$C$2:$C$200,MATCH(B123,ref_preguntas!$A$2:$A$200,0)),"ID no existe"))
A124: MH-010 | B124: P11 | D124: SALON_1, CAJA, BRASAS, COCINA | E124: EXPLICITO | F124: Imágenes de zonas | G124: =IF(B124="","",IFERROR(INDEX(ref_preguntas!$C$2:$C$200,MATCH(B124,ref_preguntas!$A$2:$A$200,0)),"ID no existe"))
A125: MH-010 | B125: P13 | D125: MOVISTAR | E125: EXPLICITO | F125: Speedtest | G125: =IF(B125="","",IFERROR(INDEX(ref_preguntas!$C$2:$C$200,MATCH(B125,ref_preguntas!$A$2:$A$200,0)),"ID no existe"))
A126: MH-010 | B126: P26 | D126: 3 | E126: EXPLICITO | F126: Impresoras | G126: =IF(B126="","",IFERROR(INDEX(ref_preguntas!$C$2:$C$200,MATCH(B126,ref_preguntas!$A$2:$A$200,0)),"ID no existe"))
A127: MH-010 | B127: P51 | D127: ID: Sera G., Yomira Mora · Cliente: Fernando | E127: EXPLICITO | F127: Asistentes | G127: =IF(B127="","",IFERROR(INDEX(ref_preguntas!$C$2:$C$200,MATCH(B127,ref_preguntas!$A$2:$A$200,0)),"ID no existe"))
A128: MH-010 | B128: P12a | D128: SI | E128: INFERIDO | F128: Impresoras de cocina y brasas | G128: =IF(B128="","",IFERROR(INDEX(ref_preguntas!$C$2:$C$200,MATCH(B128,ref_preguntas!$A$2:$A$200,0)),"ID no existe"))
... A141: MH-011 | B141: P45 | D141: SI | E141: EXPLICITO | F141: Repetidor escalera piso 2 | G141: =IF(B141="","",IFERROR(INDEX(ref_preguntas!$C$2:$C$200,MATCH(B141,ref_preguntas!$A$2:$A$200,0)),"ID no existe"))
A142: MH-011 | B142: P30 | C142: L_IMPRESORAS:1 | D142: CABLE_RED | E142: EXPLICITO | F142: Impresoras vía Ethernet | G142: =IF(B142="","",IFERROR(INDEX(ref_preguntas!$C$2:$C$200,MATCH(B142,ref_preguntas!$A$2:$A$200,0)),"ID no existe"))
A143: MH-011 | B143: P12a | D143: SI | E143: INFERIDO | F143: Impresoras de cocina y brasas | G143: =IF(B143="","",IFERROR(INDEX(ref_preguntas!$C$2:$C$200,MATCH(B143,ref_preguntas!$A$2:$A$200,0)),"ID no existe"))
A144: MH-011 | B144: P09 | D144: POLLERIA | E144: EXPLICITO | F144: Rubro confirmado por el equipo (2026-10-10) | G144: =IF(B144="","",IFERROR(INDEX(ref_preguntas!$C$2:$C$200,MATCH(B144,ref_preguntas!$A$2:$A$200,0)),"ID no existe"))
A145: MH-012 | B145: P01 | D145: Rikoton | E145: INFERIDO | F145: Rikoton (RKT); el nombre comercial aparece en RKT Hacienda | G145: =IF(B145="","",IFERROR(INDEX(ref_preguntas!$C$2:$C$200,MATCH(B145,ref_preguntas!$A$2:$A$200,0)),"ID no existe"))
A146: MH-012 | B146: P02 | D146: RKT Hacienda | E146: EXPLICITO | F146: Título | G146: =IF(B146="","",IFERROR(INDEX(ref_preguntas!$C$2:$C$200,MATCH(B146,ref_preguntas!$A$2:$A$200,0)),"ID no existe"))
A147: MH-012 | B147: P03 | D147: Av. Próceres de la Independencia 1730, San Juan de Lurigancho | E147: EXPLICITO | F147: Dirección | G147: =IF(B147="","",IFERROR(INDEX(ref_preguntas!$C$2:$C$200,MATCH(B147,ref_preguntas!$A$2:$A$200,0)),"ID no existe"))
A148: MH-012 | B148: P04 | D148: Fernando | E148: EXPLICITO | F148: Team cliente | G148: =IF(B148="","",IFERROR(INDEX(ref_preguntas!$C$2:$C$200,MATCH(B148,ref_preguntas!$A$2:$A$200,0)),"ID no existe"))
A149: MH-012 | B149: P06 | D149: 2025-06-11 | E149: EXPLICITO | F149: Fecha y hora | G149: =IF(B149="","",IFERROR(INDEX(ref_preguntas!$C$2:$C$200,MATCH(B149,ref_preguntas!$A$2:$A$200,0)),"ID no existe"))
A150: MH-012 | B150: P11 | D150: SALON_1, SALON_2, CAJA, BAR, COCINA | E150: EXPLICITO | F150: Imágenes de zonas | G150: =IF(B150="","",IFERROR(INDEX(ref_preguntas!$C$2:$C$200,MATCH(B150,ref_preguntas!$A$2:$A$200,0)),"ID no existe"))
A151: MH-012 | B151: P13 | D151: MOVISTAR | E151: EXPLICITO | F151: Speedtest | G151: =IF(B151="","",IFERROR(INDEX(ref_preguntas!$C$2:$C$200,MATCH(B151,ref_preguntas!$A$2:$A$200,0)),"ID no existe"))
A152: MH-012 | B152: P18 | D152: CAJA | E152: EXPLICITO | F152: Router principal en caja | G152: =IF(B152="","",IFERROR(INDEX(ref_preguntas!$C$2:$C$200,MATCH(B152,ref_preguntas!$A$2:$A$200,0)),"ID no existe"))
A153: MH-012 | B153: P26 | D153: 2 | E153: EXPLICITO | F153: Impresoras | G153: =IF(B153="","",IFERROR(INDEX(ref_preguntas!$C$2:$C$200,MATCH(B153,ref_preguntas!$A$2:$A$200,0)),"ID no existe"))
A154: MH-012 | B154: P51 | D154: ID: Sera G., Yomira Mora · Cliente: Fernando | E154: EXPLICITO | F154: Asistentes | G154: =IF(B154="","",IFERROR(INDEX(ref_preguntas!$C$2:$C$200,MATCH(B154,ref_preguntas!$A$2:$A$200,0)),"ID no existe"))
... A181: MH-014 | B181: P51 | D181: ID: Sera G., Yomira Mora · Cliente: Fernando | E181: EXPLICITO | F181: Asistentes | G181: =IF(B181="","",IFERROR(INDEX(ref_preguntas!$C$2:$C$200,MATCH(B181,ref_preguntas!$A$2:$A$200,0)),"ID no existe"))
A182: MH-014 | B182: P27 | C182: L_IMPRESORAS:1 | D182: CAJA | E182: EXPLICITO | F182: Impresoras | G182: =IF(B182="","",IFERROR(INDEX(ref_preguntas!$C$2:$C$200,MATCH(B182,ref_preguntas!$A$2:$A$200,0)),"ID no existe"))
A183: MH-014 | B183: P30 | C183: L_IMPRESORAS:1 | D183: USB | E183: EXPLICITO | F183: Caja (USB) | G183: =IF(B183="","",IFERROR(INDEX(ref_preguntas!$C$2:$C$200,MATCH(B183,ref_preguntas!$A$2:$A$200,0)),"ID no existe"))
A184: MH-014 | B184: P12a | D184: SI | E184: EXPLICITO | F184: Uso de comandas | G184: =IF(B184="","",IFERROR(INDEX(ref_preguntas!$C$2:$C$200,MATCH(B184,ref_preguntas!$A$2:$A$200,0)),"ID no existe"))
A185: MH-014 | B185: P18a | D185: 0 | E185: EXPLICITO | F185: Router principal sin puertos libres | G185: =IF(B185="","",IFERROR(INDEX(ref_preguntas!$C$2:$C$200,MATCH(B185,ref_preguntas!$A$2:$A$200,0)),"ID no existe"))
A186: MH-014 | B186: P09 | D186: POLLERIA | E186: EXPLICITO | F186: Rubro confirmado por el equipo (2026-10-10) | G186: =IF(B186="","",IFERROR(INDEX(ref_preguntas!$C$2:$C$200,MATCH(B186,ref_preguntas!$A$2:$A$200,0)),"ID no existe"))
A187: MH-015 | B187: P01 | D187: Rikoton | E187: INFERIDO | F187: Rikoton (RKT); el nombre comercial aparece en RKT Hacienda | G187: =IF(B187="","",IFERROR(INDEX(ref_preguntas!$C$2:$C$200,MATCH(B187,ref_preguntas!$A$2:$A$200,0)),"ID no existe"))
...

Sheet kb_minuta_hallazgo
A1: minuta_id | B1: orden | C1: seccion | D1: texto | E1: pregunta_id | F1: regla_id
A2: MH-001 | B2: 1 | C2: ANTECEDENTE | D2: Entrega de impresoras.
A3: MH-001 | B3: 2 | C3: ANTECEDENTE | D3: Configuración de impresoras.
A4: MH-001 | B4: 3 | C4: ANTECEDENTE | D4: Creación de tienda en IDPos.
A5: MH-001 | B5: 4 | C5: ANTECEDENTE | D5: Creación de zonas de trabajo.
A6: MH-001 | B6: 5 | C6: ANTECEDENTE | D6: Acompañamiento en el llenado de información.
A7: MH-001 | B7: 6 | C7: DESARROLLO | D7: Para configurar las impresoras se hizo un mapeo de red.
A8: MH-001 | B8: 7 | C8: DESARROLLO | D8: Se armaron cables de red para cada impresora, excepto la de cocina porque está lejos del punto de red. | E8: U1 | F8: R06
A9: MH-001 | B9: 8 | C9: DESARROLLO | D9: Se creó la tienda en IDPos y se configuraron impresoras, zonas de trabajo y numeración de comprobantes.
A10: MH-002 | B10: 1 | C10: ANTECEDENTE | D10: Revisión del sistema de impresión del Raspberry y capacitación sobre creación de cupones.
A11: MH-002 | B11: 2 | C11: DESARROLLO | D11: Capacitación a la parte administrativa y caja sobre creación y uso de cupones. | F11: A04
A12: MH-002 | B12: 3 | C12: DESARROLLO | D12: Mapeo de red: los equipos estaban configurados directamente hacia el módem. | F12: R18
A13: MH-002 | B13: 4 | C13: DESARROLLO | D13: Mantenimiento a equipos de la red (TP-Link, módem, Raspberry). | F13: R27
A14: MH-002 | B14: 5 | C14: DESARROLLO | D14: Se armaron cables de red a medida, se cambiaron todos por Cat6 (más resistentes al calor) y se rotularon. | E14: P39 | F14: R09
A15: MH-002 | B15: 6 | C15: DESARROLLO | D15: Limpieza de tomas de energía. | F15: R27
A16: MH-002 | B16: 7 | C16: DESARROLLO | D16: Configuración del TP-Link para red de redundancia de internet. | E16: P16 | F16: R56
A17: MH-002 | B17: 8 | C17: DESARROLLO | D17: Configuración de impresora y sistema IDPos.
A18: MH-003 | B18: 1 | C18: ANTECEDENTE | D18: Los programas de impresión no funcionan hasta que se reinicia el internet.
A19: MH-003 | B19: 2 | C19: DESARROLLO | D19: Se realizó el mapeo de la red.
A20: MH-003 | B20: 3 | C20: OBSERVACION | D20: La computadora con los programas de impresión estaba conectada vía WiFi. | E20: P23 | F20: R11
A21: MH-003 | B21: 4 | C21: OBSERVACION | D21: La red de los repetidores compartía internet con las impresoras; no había conexión directa del módem a las impresoras. | F21: R12
A22: MH-003 | B22: 5 | C22: OBSERVACION | D22: Gabinete desorganizado con cable eléctrico libre; mantener cables eléctricos aislados. | E22: P40 | F22: R08
A23: MH-004 | B23: 1 | C23: ANTECEDENTE | D23: Cuentan con 2 impresoras (1 USB y 1 de red). | E23: P26
A24: MH-004 | B24: 2 | C24: OBSERVACION | D24: PC de caja conectada por adaptador WiFi; tiene puerto de red disponible y se probó la conexión directa por red. | E24: P23 | F24: R11
A25: MH-004 | B25: 3 | C25: OBSERVACION | D25: La comanda de bebidas se prepara en caja. | E25: P27
A26: MH-004 | B26: 4 | C26: OBSERVACION | D26: Tablets para meseros y para una segunda caja (rush).
A27: MH-004 | B27: 5 | C27: OBSERVACION | D27: Impresora de caja por USB; impresora de cocina por red (CBX 89E, IP 192.168.100.20). | E27: P30 | F27: R16
A28: MH-004 | B28: 6 | C28: OBSERVACION | D28: Dos repetidores Huawei (192.168.100.22 y 192.168.100.50). | E28: P45
A29: MH-005 | B29: 1 | C29: ANTECEDENTE | D29: El día previo se reportó que no había internet y que las impresoras no imprimían comandas ni comprobantes. | E29: P17
A30: MH-005 | B30: 2 | C30: DESARROLLO | D30: Solo la PC de caja 1 tenía internet (red Movistar). | E30: P23
A31: MH-005 | B31: 3 | C31: OBSERVACION | D31: Posible desconexión del cable de corriente del router de Claro; por eso no había internet. | E31: P34 | F31: R03
A32: MH-005 | B32: 4 | C32: OBSERVACION | D32: Un cable de red conectado al módem provocaba caídas de red en todos los dispositivos; se pasaron todos los equipos a la red Movistar. | F32: R29
A33: MH-005 | B33: 5 | C33: DESARROLLO | D33: Se reconfiguraron todas las impresoras en la red Movistar. | F33: A10
A34: MH-005 | B34: 6 | C34: OBSERVACION | D34: La red llegaba inestable a la barra 1 que reparte a las PC de caja; el switch de la barra fallaba y se reemplazó. | F34: R31
A35: MH-005 | B35: 7 | C35: DESARROLLO | D35: Se conectaron las tablets por WiFi a la red DORCHER CLIENTES (15/04/2023). | F35: R32
A36: MH-006 | B36: 1 | C36: ANTECEDENTE | D36: Se movió el cable de internet del segundo piso del router Movistar al de Claro; las impresoras dejaron de imprimir. | F36: R29
A37: MH-006 | B37: 2 | C37: DESARROLLO | D37: Se recableó el segundo piso (PC caja 3, impresoras de caja 3, barra 2 y cocina) para que todo quede en la red Claro. | F37: R29
A38: MH-006 | B38: 3 | C38: DESARROLLO | D38: Se reconfiguraron todos los equipos en la red Claro, se probó la impresión y la velocidad en cada PC de caja (~92–93 Mbps). | F38: A10
A39: MH-006 | B39: 4 | C39: DESARROLLO | D39: Se rotularon todos los cables de red de equipos e impresoras conectados al router. | F39: R30
A40: MH-006 | B40: 5 | C40: OBSERVACION | D40: Las 6 tablets tienen conectividad variable: algunas solo se conectan a DORCHER SISTEMAS y otras a DORCHER CLIENTES. | F40: R32
A41: MH-007 | B41: 1 | C41: ANTECEDENTE | D41: Local sin internet; se pidió un chip Entel 4G para el monitor Summi y poder comandar e imprimir comprobantes. | E41: P17 | F41: R56
A42: MH-007 | B42: 2 | C42: DESARROLLO | D42: Las áreas de preparación no tenían sistema de impresión; solo se comandaba desde el monitor Summi.
A43: MH-007 | B43: 3 | C43: DESARROLLO | D43: Se adquirió un TP-Link con chip 4G (10 GB) como respaldo automático ante caídas para PCs e impresoras. | E43: P16 | F43: R56
A44: MH-007 | B44: 4 | C44: OBSERVACION | D44: El TP-Link solo tiene 3 puertos: la barra 1 de makis quedó fuera de la red de respaldo. | E44: P38 | F44: R48
A45: MH-008 | B45: 1 | C45: ANTECEDENTE | D45: Revisión del sistema de impresión del Raspberry.
A46: MH-008 | B46: 2 | C46: DESARROLLO | D46: Lugares de impresión: Recepción, Bodegón y Lagar. Se hizo el mapeo de red y se cambió el cable de la impresora de Bodegón. | E46: P25
A47: MH-008 | B47: 3 | C47: OBSERVACION | D47: El Raspberry estaba en la barra de Bodegón, sobre la mesa de trabajo del personal. | F47: R34
A48: MH-008 | B48: 4 | C48: OBSERVACION | D48: No se pudo conectar el Raspberry: faltaba el personal de mantenimiento y el switch. | F48: R26
A49: MH-008 | B49: 5 | C49: OBSERVACION | D49: Proveedor Hughesnet (satelital): al agotar los 10 GB baja la velocidad; se midieron 2.73 Mbps. | E49: P13 | F49: R33
A50: MH-008 | B50: 6 | C50: OBSERVACION | D50: Con internet satelital la latencia es alta; la PC de caja estaba conectada por WiFi. | E50: P23 | F50: R11
A51: MH-008 | B51: 7 | C51: OBSERVACION | D51: Mensajes 'Network Error' con datos móviles (lejos de la antena) y 'Server Error' en Bodegón; se actualizó el sistema de impresión. | F51: R36
A52: MH-008 | B52: 8 | C52: OBSERVACION | D52: La PC de recepción tenía zona horaria de México y las aperturas se registraban en días anteriores; se corrigió. | F52: R35
A53: MH-009 | B53: 1 | C53: OBSERVACION | D53: La impresora de caja es USB; para pre-cuentas desde tablets y comandas en caja se necesita una impresora de red. | E53: P30 | F53: R16
A54: MH-009 | B54: 2 | C54: OBSERVACION | D54: No hay punto de red para la impresora de caja. | E54: U1 | F54: R06
A55: MH-010 | B55: 1 | C55: OBSERVACION | D55: Los cables de red de las impresoras están holgados; puede causar intermitencia. | F55: R37
A56: MH-011 | B56: 1 | C56: OBSERVACION | D56: Las tres impresoras (caja, brasas, cocina) están conectadas por Ethernet. | E56: P30
A57: MH-011 | B57: 2 | C57: OBSERVACION | D57: Dos pisos con una sola tablet; repetidor en la escalera del piso 2. | E57: P10 | F57: R39
A58: MH-012 | B58: 1 | C58: OBSERVACION | D58: Se validaron los equipos y su funcionamiento para la implementación.
A59: MH-012 | B59: 2 | C59: OBSERVACION | D59: La impresora de caja tiene el botón de feed inoperativo (no relevante).
A60: MH-013 | B60: 1 | C60: OBSERVACION | D60: En la barra del piso 2 preparan bebidas sin recibir comandas. | E60: P25 | F60: R38
A61: MH-013 | B61: 2 | C61: OBSERVACION | D61: Solo hay una impresora de red para pre-cuenta en la caja del piso 1. | E61: P26
A62: MH-014 | B62: 1 | C62: OBSERVACION | D62: La impresora de caja solo tiene puerto USB; se necesita una con Ethernet para comandas y pre-cuentas desde tablets. | E62: P30 | F62: R16
A63: MH-014 | B63: 2 | C63: OBSERVACION | D63: El router principal no tiene puertos libres para cablear la impresora de caja. | F63: R48
A64: MH-014 | B64: 3 | C64: OBSERVACION | D64: La impresora de cocina-brasas tiene el botón de feed averiado; no se pudo sacar el selftest.
A65: MH-015 | B65: 1 | C65: OBSERVACION | D65: La impresora de caja tiene puerto Ethernet pero no está conectada a la red (IP desconfigurada). | E65: P30 | F65: R06
A66: MH-015 | B66: 2 | C66: OBSERVACION | D66: Barra del piso 2 sin atención; hay PC estación de mozo y repetidor.
A67: MH-016 | B67: 1 | C67: OBSERVACION | D67: La tablet se usa para toda la operación de venta: es la caja principal (no hay PC). | E67: P22 | F67: R47
A68: MH-016 | B68: 2 | C68: OBSERVACION | D68: Impresora 3nStar (192.168.1.230) para boletas y facturas, uso no recurrente. | E68: P29
A69: MH-016 | B69: 3 | C69: OBSERVACION | D69: Subida de internet muy baja: 2.52 Mbps. | F69: R17
A70: MH-017 | B70: 1 | C70: OBSERVACION | D70: Access point Movistar (192.168.5.1) reparte red a la impresora de salón y WiFi para tablet y clientes.
A71: MH-017 | B71: 2 | C71: OBSERVACION | D71: Impresora 3nStar con cambio de IP pendiente. | E71: P30 | F71: R24
A72: MH-017 | B72: 3 | C72: OBSERVACION | D72: No hay puertos libres en el access point del salón para conectar el Raspberry. | F72: R48
A73: MH-018 | B73: 1 | C73: OBSERVACION | D73: Router Claro (192.168.0.1), impresora 3nStar en barra y tablet.
A74: MH-019 | B74: 1 | C74: DESARROLLO | D74: Velocidad de internet de 322.45 Mbps.
A75: MH-019 | B75: 2 | C75: DESARROLLO | D75: Ventas rápidas en caja: no se consideran las mesas. | E75: P11
A76: MH-019 | B76: 3 | C76: OBSERVACION | D76: El router está a 12 m de la caja: hacen falta canaletas para el cableado. | F76: R06
A77: MH-020 | B77: 1 | C77: OBSERVACION | D77: Cableado de red por reestructurar; no es impedimento de inicio. | F77: R64
A78: MH-021 | B78: 1 | C78: OBSERVACION | D78: Sin puntos de red y aún sin servicio de internet. | E78: P14 | F78: R06
A79: MH-021 | B79: 2 | C79: DESARROLLO | D79: Aún sin impresoras para barra y cocina. | E79: P26
A80: MH-022 | B80: 1 | C80: OBSERVACION | D80: La laptop no estará permanentemente en el local. | E80: P22 | F80: R60
A81: MH-023 | B81: 1 | C81: DESARROLLO | D81: Raspberry instalado en caja; impresoras caja, barra, cocina y empaquetados en el mismo segmento.
A82: MH-024 | B82: 1 | C82: OBSERVACION | D82: El local no cuenta con puntos de red. | E82: P38 | F82: R06
A83: MH-024 | B83: 2 | C83: OBSERVACION | D83: La cobertura WiFi no llega al 100 % del local. | E83: P46 | F83: R19
A84: MH-024 | B84: 3 | C84: DESARROLLO | D84: Patio de comidas: se instaló TP-Link con chip Entel. | E84: P13 | F84: R56
A85: MH-025 | B85: 1 | C85: DESARROLLO | D85: Las impresoras se pasaron al mismo segmento de red con ayuda del cable USB. | F85: R55
A86: MH-026 | B86: 1 | C86: ANTECEDENTE | D86: La impresora de caja se conecta y desconecta: la entrada del cable de red está floja. | F86: R37
A87: MH-027 | B87: 1 | C87: OBSERVACION | D87: Pendiente el punto de red para la pantalla de caja. | E87: P38 | F87: R06
A88: MH-027 | B88: 2 | C88: OBSERVACION | D88: Pendiente el punto de red para la impresora de cocina. | E88: P38 | F88: R06
A89: MH-028 | B89: 1 | C89: DESARROLLO | D89: Velocidad de internet de 94.42 Mbps; laptop conectada directo al router.
A90: MH-029 | B90: 1 | C90: OBSERVACION | D90: El técnico de redes estaba implementando el cableado; quedó pendiente.
A91: MH-030 | B91: 1 | C91: OBSERVACION | D91: Dos cables de cámaras en el mismo switch que las impresoras. | E91: P47 | F91: R53
A92: MH-030 | B92: 2 | C92: OBSERVACION | D92: Cables de cámaras sueltos. | F92: R64
A93: MH-031 | B93: 1 | C93: OBSERVACION | D93: Switch principal de 10/100 Mbps. | F93: R58
A94: MH-031 | B94: 2 | C94: OBSERVACION | D94: El WiFi es libre para los clientes. | F94: R32
A95: MH-031 | B95: 3 | C95: OBSERVACION | D95: Impresora de caja USB conectada a la PC. | E95: P30 | F95: R16
A96: MH-032 | B96: 1 | C96: OBSERVACION | D96: Switch principal de 10/100 Mbps con cámaras, PC de caja e impresoras. | F96: R58
A97: MH-032 | B97: 2 | C97: OBSERVACION | D97: Punto de red de la impresora de frituras por cambiar. | F97: R06
A98: MH-032 | B98: 3 | C98: OBSERVACION | D98: Conector RJ45 de la impresora de makis por cambiar. | F98: R37
A99: MH-033 | B99: 1 | C99: OBSERVACION | D99: El cable de cámaras está junto a un cable de corriente: ruido que llega al router. | F99: R62
A100: MH-033 | B100: 2 | C100: OBSERVACION | D100: El cable pasa bajo un equipo con motor que genera ruido en la señal. | F100: R62
...

Sheet kb_minuta_recomendacion
A1: minuta_id | B1: orden | C1: tipo | D1: regla_id | E1: texto_original | F1: texto_regla
A2: MH-001 | B2: 1 | C2: RECOMENDACION | D2: R56 | E2: Ante caídas de la red principal es opcional tener un TP-Link 4G con chip para mantener la conexión de internet para las impresoras. | F2: =IF(D2="","",IFERROR(INDEX(kb_regla_recomendacion!$G$2:$G$200,MATCH(D2,kb_regla_recomendacion!$A$2:$A$200,0)),"Regla no existe"))
A3: MH-001 | B3: 2 | C3: RECOMENDACION | D3: R02 | E3: Es imprescindible contar con un kit Raspberry como parte de la virtualización de conexión a las impresoras e impresión. | F3: =IF(D3="","",IFERROR(INDEX(kb_regla_recomendacion!$G$2:$G$200,MATCH(D3,kb_regla_recomendacion!$A$2:$A$200,0)),"Regla no existe"))
A4: MH-001 | B4: 3 | C4: RECOMENDACION | D4: R03 | E4: Contar con un punto más de energía cerca del gabinete de cámaras u otro supresor de picos para la extensión de energía del Raspberry. | F4: =IF(D4="","",IFERROR(INDEX(kb_regla_recomendacion!$G$2:$G$200,MATCH(D4,kb_regla_recomendacion!$A$2:$A$200,0)),"Regla no existe"))
A5: MH-001 | B5: 4 | C5: RECOMENDACION | D5: R05 | E5: Un switch de 4 a 5 puertos para ampliar el punto de red en terraza. | F5: =IF(D5="","",IFERROR(INDEX(kb_regla_recomendacion!$G$2:$G$200,MATCH(D5,kb_regla_recomendacion!$A$2:$A$200,0)),"Regla no existe"))
A6: MH-001 | B6: 5 | C6: RECOMENDACION | D6: R06 | E6: Para la impresora de cocina contar con un punto de red más cerca. | F6: =IF(D6="","",IFERROR(INDEX(kb_regla_recomendacion!$G$2:$G$200,MATCH(D6,kb_regla_recomendacion!$A$2:$A$200,0)),"Regla no existe"))
A7: MH-001 | B7: 6 | C7: ACCION_ID | D7: R26 | E7: Realizar una segunda visita técnica para la conexión de impresoras. | F7: =IF(D7="","",IFERROR(INDEX(kb_regla_recomendacion!$G$2:$G$200,MATCH(D7,kb_regla_recomendacion!$A$2:$A$200,0)),"Regla no existe"))
A8: MH-001 | B8: 7 | C8: ACCION_CLIENTE | D8: A02 | E8: Confirmar recepción de la minuta de visita técnica. | F8: =IF(D8="","",IFERROR(INDEX(kb_regla_recomendacion!$G$2:$G$200,MATCH(D8,kb_regla_recomendacion!$A$2:$A$200,0)),"Regla no existe"))
A9: MH-001 | B9: 8 | C9: ACCION_CLIENTE | D9: R06 | E9: Tener el punto de red de la cocina cerca de su instalación para la siguiente visita. | F9: =IF(D9="","",IFERROR(INDEX(kb_regla_recomendacion!$G$2:$G$200,MATCH(D9,kb_regla_recomendacion!$A$2:$A$200,0)),"Regla no existe"))
A10: MH-001 | B10: 9 | C10: ACCION_CLIENTE | D10: A07 | E10: Llenado de la información del Excel brindado. | F10: =IF(D10="","",IFERROR(INDEX(kb_regla_recomendacion!$G$2:$G$200,MATCH(D10,kb_regla_recomendacion!$A$2:$A$200,0)),"Regla no existe"))
A11: MH-002 | B11: 1 | C11: RECOMENDACION | D11: R03 | E11: La toma de energía para los equipos en red debe ser independiente para evitar desconexiones al conectar la licuadora. | F11: =IF(D11="","",IFERROR(INDEX(kb_regla_recomendacion!$G$2:$G$200,MATCH(D11,kb_regla_recomendacion!$A$2:$A$200,0)),"Regla no existe"))
A12: MH-002 | B12: 2 | C12: RECOMENDACION | D12: R07 | E12: Adquirir un gabinete Nacional de pared de 4 RU (24 alto x 36 ancho x 35 prof.), colocarlo a 1.65 m del piso y contar con otro supresor de picos solo para los equipos del gabinete. | F12: =IF(D12="","",IFERROR(INDEX(kb_regla_recomendacion!$G$2:$G$200,MATCH(D12,kb_regla_recomendacion!$A$2:$A$200,0)),"Regla no existe"))
A13: MH-002 | B13: 3 | C13: RECOMENDACION | D13: R56 | E13: Contar con un chip solo para uso del TP-Link. | F13: =IF(D13="","",IFERROR(INDEX(kb_regla_recomendacion!$G$2:$G$200,MATCH(D13,kb_regla_recomendacion!$A$2:$A$200,0)),"Regla no existe"))
... A197: MH-044 | B197: 4 | C197: ACCION_CLIENTE | D197: A02 | E197: Confirmar recepción de la minuta. | F197: =IF(D197="","",IFERROR(INDEX(kb_regla_recomendacion!$G$2:$G$200,MATCH(D197,kb_regla_recomendacion!$A$2:$A$200,0)),"Regla no existe"))
F198: =IF(D198="","",IFERROR(INDEX(kb_regla_recomendacion!$G$2:$G$200,MATCH(D198,kb_regla_recomendacion!$A$2:$A$200,0)),"Regla no existe"))
F199: =IF(D199="","",IFERROR(INDEX(kb_regla_recomendacion!$G$2:$G$200,MATCH(D199,kb_regla_recomendacion!$A$2:$A$200,0)),"Regla no existe"))
F200: =IF(D200="","",IFERROR(INDEX(kb_regla_recomendacion!$G$2:$G$200,MATCH(D200,kb_regla_recomendacion!$A$2:$A$200,0)),"Regla no existe"))
F201: =IF(D201="","",IFERROR(INDEX(kb_regla_recomendacion!$G$2:$G$200,MATCH(D201,kb_regla_recomendacion!$A$2:$A$200,0)),"Regla no existe"))
F202: =IF(D202="","",IFERROR(INDEX(kb_regla_recomendacion!$G$2:$G$200,MATCH(D202,kb_regla_recomendacion!$A$2:$A$200,0)),"Regla no existe"))
F203: =IF(D203="","",IFERROR(INDEX(kb_regla_recomendacion!$G$2:$G$200,MATCH(D203,kb_regla_recomendacion!$A$2:$A$200,0)),"Regla no existe"))
F204: =IF(D204="","",IFERROR(INDEX(kb_regla_recomendacion!$G$2:$G$200,MATCH(D204,kb_regla_recomendacion!$A$2:$A$200,0)),"Regla no existe"))
F205: =IF(D205="","",IFERROR(INDEX(kb_regla_recomendacion!$G$2:$G$200,MATCH(D205,kb_regla_recomendacion!$A$2:$A$200,0)),"Regla no existe"))
F206: =IF(D206="","",IFERROR(INDEX(kb_regla_recomendacion!$G$2:$G$200,MATCH(D206,kb_regla_recomendacion!$A$2:$A$200,0)),"Regla no existe"))
F207: =IF(D207="","",IFERROR(INDEX(kb_regla_recomendacion!$G$2:$G$200,MATCH(D207,kb_regla_recomendacion!$A$2:$A$200,0)),"Regla no existe"))
F208: =IF(D208="","",IFERROR(INDEX(kb_regla_recomendacion!$G$2:$G$200,MATCH(D208,kb_regla_recomendacion!$A$2:$A$200,0)),"Regla no existe"))
F209: =IF(D209="","",IFERROR(INDEX(kb_regla_recomendacion!$G$2:$G$200,MATCH(D209,kb_regla_recomendacion!$A$2:$A$200,0)),"Regla no existe"))
... F347: =IF(D347="","",IFERROR(INDEX(kb_regla_recomendacion!$G$2:$G$200,MATCH(D347,kb_regla_recomendacion!$A$2:$A$200,0)),"Regla no existe"))

Sheet kb_minuta_equipo
A1: minuta_id | B1: tipo_equipo | C1: marca | D1: modelo | E1: ip | F1: conexion | G1: area | H1: cantidad | I1: nota
A2: MH-001 | B2: printer | F2: CABLE_RED | I2: Impresoras entregadas y configuradas; la de cocina quedó pendiente por falta de punto de red
A3: MH-001 | B3: camera | I3: Hay un gabinete de cámaras
A4: MH-002 | B4: modem | H4: 1 | I4: Los equipos estaban configurados directo al módem
A5: MH-002 | B5: router | C5: TP-Link | H5: 1 | I5: Configurado como red de redundancia de internet (4G)
A6: MH-002 | B6: raspberry | C6: Raspberry | H6: 1 | I6: Sistema de impresión
A7: MH-002 | B7: printer | I7: Configurada con IDPos
A8: MH-003 | B8: computer | F8: WIFI | G8: CAJA | H8: 1 | I8: PC con los programas de impresión
A9: MH-003 | B9: repetidor | F9: WIFI | I9: Compartían red con las impresoras
A10: MH-003 | B10: printer | G10: BAR | H10: 1 | I10: Impresora de barra
A11: MH-004 | B11: router | C11: Huawei | D11: OptiXstar HG8145X6-10 | E11: 192.168.100.1 | G11: CAJA | H11: 1 | I11: Router principal (Claro)
A12: MH-004 | B12: computer | E12: 192.168.100.13 | F12: WIFI | G12: CAJA | H12: 1 | I12: Tiene puerto de red libre
A13: MH-004 | B13: printer | F13: USB | G13: CAJA | H13: 1 | I13: Conectada a la PC de caja
A14: MH-004 | B14: printer | C14: CBX | D14: CBX-POS89E | E14: 192.168.100.20 | F14: CABLE_RED | G14: COCINA | H14: 1 | I14: IP fija
A15: MH-004 | B15: repetidor | C15: Huawei | E15: 192.168.100.22 | F15: WIFI | H15: 1
A16: MH-004 | B16: repetidor | C16: Huawei | E16: 192.168.100.50 | F16: WIFI | H16: 1
A17: MH-004 | B17: tablet | F17: WIFI | G17: SALON_1 | I17: Tablets para meseros y segunda caja (rush)
A18: MH-005 | B18: router | H18: 2 | I18: Dos routers: Claro y Movistar
A19: MH-005 | B19: computer | F19: CABLE_RED | G19: CAJA | H19: 3 | I19: PC caja 1, 2 y 3
A20: MH-005 | B20: switch | F20: CABLE_RED | G20: BAR | H20: 1 | I20: Switch de la barra 1 con falla; reemplazado por uno de ID
A21: MH-005 | B21: tablet | F21: WIFI | I21: Tablets de meseras en red DORCHER CLIENTES
A22: MH-006 | B22: computer | F22: CABLE_RED | G22: CAJA | H22: 3 | I22: ~92–93 Mbps en cada PC
A23: MH-006 | B23: printer | F23: CABLE_RED | G23: CAJA | H23: 3 | I23: Impresoras de caja 1, 2 y 3
A24: MH-006 | B24: printer | F24: CABLE_RED | G24: BAR | H24: 2 | I24: Barra 1 (piso 1) y barra 2 (piso 2)
A25: MH-006 | B25: printer | F25: CABLE_RED | G25: COCINA | H25: 1
A26: MH-006 | B26: tablet | F26: WIFI | H26: 6 | I26: Redes DORCHER SISTEMAS y DORCHER CLIENTES
A27: MH-007 | B27: pos | C27: Sunmi | F27: WIFI | H27: 1 | I27: Monitor Summi con chip Entel 4G
A28: MH-007 | B28: router | C28: TP-Link | H28: 1 | I28: Router 4G con chip (10 GB), 3 puertos, respaldo automático
A29: MH-008 | B29: raspberry | C29: Raspberry | F29: CABLE_RED | G29: OTRO | H29: 1 | I29: En la barra de Bodegón
A30: MH-008 | B30: printer | F30: CABLE_RED | G30: OTRO | H30: 3 | I30: Recepción, Bodegón y Lagar
A31: MH-008 | B31: computer | F31: WIFI | G31: CAJA | H31: 1 | I31: PC de caja por WiFi
A32: MH-008 | B32: computer | G32: OTRO | H32: 1 | I32: PC de recepción (zona horaria corregida)
A33: MH-008 | B33: modem | C33: Hughesnet | H33: 1 | I33: Internet satelital
A34: MH-009 | B34: router | G34: CAJA | H34: 1 | I34: Router principal con fibra óptica
A35: MH-009 | B35: printer | F35: USB | G35: CAJA | H35: 1 | I35: Impresora de caja USB
A36: MH-009 | B36: printer | E36: 192.168.0.241 | F36: CABLE_RED | G36: CAJA | H36: 1 | I36: El PDF la rotula 'Impresora de Caja (RED)'; verificar si es la de cocina-brasas
A37: MH-009 | B37: tablet | F37: WIFI
A38: MH-010 | B38: printer | E38: 192.168.1.111 | F38: CABLE_RED | G38: CAJA | H38: 1 | I38: Conector holgado
A39: MH-010 | B39: printer | E39: 192.168.1.110 | F39: CABLE_RED | G39: BRASAS | H39: 1 | I39: Conector holgado
A40: MH-010 | B40: printer | E40: 192.168.1.100 | F40: CABLE_RED | G40: COCINA | H40: 1 | I40: Conector holgado
A41: MH-011 | B41: router | G41: CAJA | H41: 1 | I41: Router principal
A42: MH-011 | B42: repetidor | F42: WIFI | H42: 1 | I42: Escalera del piso 2
A43: MH-011 | B43: printer | E43: 192.168.1.55 | F43: CABLE_RED | G43: CAJA | H43: 1
A44: MH-011 | B44: printer | E44: 192.168.1.195 | F44: CABLE_RED | G44: BRASAS | H44: 1
A45: MH-011 | B45: printer | E45: 192.168.1.196 | F45: CABLE_RED | G45: COCINA | H45: 1
A46: MH-011 | B46: tablet | F46: WIFI | H46: 1
A47: MH-012 | B47: router | G47: CAJA | H47: 1 | I47: Router principal
A48: MH-012 | B48: computer | G48: CAJA | H48: 1 | I48: PC de caja
A49: MH-012 | B49: printer | E49: 192.168.1.112 | F49: CABLE_RED | G49: CAJA | H49: 1 | I49: Botón feed inoperativo
A50: MH-012 | B50: printer | F50: CABLE_RED | G50: COCINA | H50: 1 | I50: IP ilegible en la minuta
A51: MH-012 | B51: tablet | F51: WIFI | H51: 2 | I51: Equipos de meseros
A52: MH-013 | B52: router | G52: CAJA | H52: 1 | I52: Router principal con fibra óptica, piso 1
A53: MH-013 | B53: repetidor | F53: WIFI | G53: BAR | I53: Barra del piso 2
A54: MH-013 | B54: computer | G54: CAJA | H54: 1 | I54: PC de caja
A55: MH-013 | B55: printer | E55: 192.168.1.241 | F55: CABLE_RED | G55: CAJA | H55: 1
A56: MH-013 | B56: printer | E56: 192.168.1.250 | F56: CABLE_RED | G56: COCINA | H56: 1 | I56: Cocina-brasas
A57: MH-014 | B57: router | H57: 1 | I57: Sin puertos libres
A58: MH-014 | B58: computer | G58: CAJA | H58: 1 | I58: PC de caja
A59: MH-014 | B59: printer | F59: USB | G59: CAJA | H59: 1 | I59: Solo puerto USB
A60: MH-014 | B60: printer | E60: 192.168.1.100 | F60: CABLE_RED | G60: COCINA | H60: 1 | I60: Cocina-brasas; feed averiado, sin selftest
A61: MH-015 | B61: router | E61: 192.168.18.1 | H61: 1 | I61: Router principal
A62: MH-015 | B62: repetidor | F62: WIFI | H62: 1
A63: MH-015 | B63: computer | E63: 192.168.18.20 | H63: 1 | I63: PC estación de mozo
A64: MH-015 | B64: printer | F64: CABLE_RED | G64: CAJA | H64: 1 | I64: Tiene puerto Ethernet pero no está conectada; IP desconfigurada
A65: MH-015 | B65: printer | E65: 192.168.18.110 | F65: CABLE_RED | G65: BRASAS | H65: 1
A66: MH-015 | B66: printer | E66: 192.168.18.100 | F66: CABLE_RED | G66: COCINA | H66: 1
A67: MH-016 | B67: router | C67: Movistar | E67: 192.168.1.1 | H67: 1
A68: MH-016 | B68: printer | C68: 3nStar | E68: 192.168.1.230 | F68: CABLE_RED | G68: BAR | H68: 1 | I68: Boletas y facturas
A69: MH-016 | B69: tablet | F69: WIFI | G69: CAJA | H69: 1 | I69: Caja principal
A70: MH-017 | B70: access_point | C70: Movistar | E70: 192.168.5.1 | G70: SALON_1 | H70: 1 | I70: Sin puertos libres; red para impresora de salón y WiFi
A71: MH-017 | B71: printer | C71: 3nStar | F71: CABLE_RED | G71: SALON_1 | H71: 1 | I71: Cambio de IP pendiente
A72: MH-017 | B72: tablet | F72: WIFI | H72: 1
A73: MH-018 | B73: router | C73: Claro | E73: 192.168.0.1 | H73: 1
A74: MH-018 | B74: printer | C74: 3nStar | G74: BAR | H74: 1
A75: MH-018 | B75: tablet | F75: WIFI | H75: 1
A76: MH-019 | B76: pos | C76: Sunmi | D76: V2 Pro | G76: CAJA | H76: 1 | I76: Registrado en IDPos
A77: MH-020 | B77: router | G77: CAJA | H77: 1 | I77: Router y switch principal en caja
A78: MH-020 | B78: printer | H78: 4 | I78: Caja, cocina, bebidas/postres/vinos (piso 1), barra piso 2–terraza
A79: MH-022 | B79: pos | C79: Sunmi | D79: T2 mini | G79: BARRA_1 | H79: 2 | I79: Pantallas
A80: MH-022 | B80: pos | C80: Sunmi | D80: T2 mini | G80: BARRA_2 | H80: 1 | I80: Pantalla
A81: MH-022 | B81: printer | C81: 3nStar | D81: RPT008 | G81: BARRA_1 | H81: 1 | I81: Comandas
A82: MH-022 | B82: printer | C82: 3nStar | D82: RPT008 | G82: BARRA_2 | H82: 1 | I82: Comandas
A83: MH-022 | B83: computer | C83: Lenovo | D83: Laptop Win10 | H83: 1 | I83: No se queda en el local
A84: MH-023 | B84: raspberry | G84: CAJA | H84: 1
A85: MH-023 | B85: printer | E85: 192.168.18.17 | F85: CABLE_RED | G85: CAJA | H85: 1
A86: MH-023 | B86: printer | E86: 192.168.18.35 | F86: CABLE_RED | G86: BAR | H86: 1
A87: MH-023 | B87: printer | E87: 192.168.18.34 | F87: CABLE_RED | G87: COCINA | H87: 1
A88: MH-023 | B88: printer | E88: 192.168.18.36 | F88: CABLE_RED | G88: EMPAQUETADO | H88: 1
A89: MH-023 | B89: pos | C89: Sunmi | D89: D2 mini | I89: Pantallas en patio y salón principal
A90: MH-024 | B90: printer | C90: POSD | D90: TP 300PRO | E90: 192.168.0.31 | G90: CAJA | H90: 1 | I90: Caja/Barra
A91: MH-024 | B91: printer | C91: POSD | D91: TP 300PRO | E91: 192.168.0.32 | G91: COCINA | H91: 1
A92: MH-024 | B92: router | C92: TP-Link | H92: 1 | I92: Con chip Entel
A93: MH-024 | B93: raspberry | H93: 1
A94: MH-025 | B94: printer | C94: Bienex | H94: 4 | I94: Caja, barra sushi, bar y cocina
A95: MH-025 | B95: computer | D95: Laptop | G95: CAJA | H95: 1 | I95: Laptop del local
A96: MH-029 | B96: printer | G96: COCINA | H96: 1
A97: MH-029 | B97: printer | G97: CAJA | H97: 1 | I97: Caja-Barra
A98: MH-030 | B98: printer | F98: CABLE_RED | H98: 5 | I98: Caja, ramen, salteados, frituras, makis
A99: MH-030 | B99: camera | F99: CABLE_RED | H99: 2 | I99: En el mismo switch
A100: MH-031 | B100: switch | D100: 10/100 | H100: 1 | I100: Switch principal
...

Sheet kb_minuta_evidencia
A1: minuta_id | B1: codigo_evidencia | C1: descripcion | D1: archivo_o_pagina | E1: nota
A2: MH-001 | B2: MAPA | C2: Network Topology | D2: sicilia.pdf
A3: MH-002 | B3: MAPA | C3: Topology Network (a implementar gabinete y energía) | D3: donoscar.pdf
A4: MH-003 | B4: E1 | C4: Velocidad de internet | D4: barrio.pdf
A5: MH-003 | B5: E6 | C5: Fotos de la red | D5: barrio.pdf
A6: MH-003 | B6: MAPA | C6: Topology Network de equipos a implementar | D6: barrio.pdf
A7: MH-004 | B7: E1 | C7: Especificaciones de velocidad: descarga 91.50 Mbps, subida 92.49 Mbps | D7: rock.pdf
A8: MH-004 | B8: E3 | C8: Especificaciones del router principal: gateway 192.168.100.1 | D8: rock.pdf | E8: Ocultar credenciales de la etiqueta
A9: MH-004 | B9: E5 | C9: Especificaciones de impresoras: Caja (USB) y Cocina (CBX 89E, IP 192.168.100.20) | D9: rock.pdf
A10: MH-004 | B10: E8 | C10: Mapeo de red: 192.168.100.1 router, .13 PC caja, .20 impresora cocina, .22 y .50 repetidores | D10: rock.pdf
A11: MH-004 | B11: E9 | C11: Imágenes de zonas: salones del piso 2 y piso 3 | D11: rock.pdf
A12: MH-004 | B12: VIDEO | C12: CAJA Y ROUTER PRINCIPAL.mp4 | E12: Video externo
A13: MH-004 | B13: VIDEO | C13: REPETIDORES.mp4 | E13: Video externo
A14: MH-004 | B14: VIDEO | C14: SELFTEST.mp4 | E14: Video externo
A15: MH-005 | B15: E1 | C15: Speedtest antes y después del cambio de switch (94.01 / 94.43 Mbps)
A16: MH-005 | B16: E2 | C16: Router antes y después de conectarlo
A17: MH-006 | B17: E1 | C17: Speedtest de PC caja 1, 2 y 3 (~92–93 Mbps)
A18: MH-006 | B18: E5 | C18: Pruebas de impresión: barra 2, caja 3, cocina, caja 1, caja 2 y barra 1
A19: MH-006 | B19: E6 | C19: Cables rotulados en el router
A20: MH-006 | B20: OTRA | C20: Redes WiFi de las tablets
A21: MH-007 | B21: MAPA | C21: Topology Network
A22: MH-008 | B22: E8 | C22: Mapeo de red: Lagar, Recepción, Bodegón
A23: MH-008 | B23: MAPA | C23: Topology Network
A24: MH-009 | B24: E9 | C24: Zonas: salón 01, salón 02, caja, cocina-brasas
A25: MH-009 | B25: VIDEO | C25: Video del local
A26: MH-009 | B26: E1 | C26: Speedtest 493.11 Mbps
... A58: MH-015 | B58: E2 | C58: Router principal y repetidor
A59: MH-016 | B59: E1 | C59: Speedtest 155.54 / 2.52 Mbps | E59: QR de WiFi: ver hoja kb_minuta_credencial
A60: MH-016 | B60: E5 | C60: Impresora 3nStar y su etiqueta
A61: MH-016 | B61: E9 | C61: Barra y vista general
A62: MH-016 | B62: OTRA | C62: Datos de la tablet
A63: MH-017 | B63: E1 | C63: Speedtest 89.44 / 89.61 Mbps | E63: QR de WiFi: ver hoja kb_minuta_credencial
A64: MH-017 | B64: E5 | C64: Selftest y etiqueta de la impresora 3nStar
A65: MH-017 | B65: E9 | C65: Barra principal, salón, terraza, frente del local
A66: MH-017 | B66: OTRA | C66: Datos de la tablet
A67: MH-018 | B67: E1 | C67: Speedtest 233.24 / 55.05 Mbps y prueba por WiFi móvil | E67: QR de WiFi: ver hoja kb_minuta_credencial
A68: MH-018 | B68: E5 | C68: Impresora 3nStar y su etiqueta
A69: MH-018 | B69: E9 | C69: Barra
A70: MH-018 | B70: OTRA | C70: Datos de la tablet
A71: MH-012 | B71: OTRA | C71: Captura de AnyDesk | E71: ID de AnyDesk: ver hoja kb_minuta_credencial
A72: MH-019 | B72: E1 | C72: Speedtest 322.45 Mbps
A73: MH-019 | B73: E2 | C73: Router principal
A74: MH-019 | B74: E9 | C74: Zonas y ubicación de la impresora
A75: MH-020 | B75: VIDEO | C75: Ubicación de router y switch principal; piso 1; terraza piso 2
A76: MH-020 | B76: E5 | C76: Impresoras caja, cocina, bebidas, barra piso 2
A77: MH-021 | B77: VIDEO | C77: Ubicación de equipos, zonas y lugares de preparación (2 videos)
A78: MH-022 | B78: E5 | C78: Impresoras de barra 1 y 2 | E78: ver hoja kb_minuta_credencial
A79: MH-023 | B79: E5 | C79: Impresoras caja, barra, cocina y empaquetados
A80: MH-024 | B80: E5 | C80: Impresoras caja/barra y cocina | E80: ver hoja kb_minuta_credencial
A81: MH-024 | B81: E9 | C81: Cobertura de red y punto de corriente
A82: MH-025 | B82: OTRA | C82: Captura de AnyDesk | E82: ver hoja kb_minuta_credencial
A83: MH-027 | B83: E9 | C83: Caja principal, zona de mesas piso 1 y 2, puntos de corriente
A84: MH-028 | B84: E1 | C84: Speedtest 94.42 Mbps
A85: MH-028 | B85: E2 | C85: Router principal
A86: MH-029 | B86: E1 | C86: Speedtest 1000 Mbps
A87: MH-030 | B87: E1 | C87: Velocidad de la PC de caja y de cada impresora | E87: ver hoja kb_minuta_credencial
A88: MH-030 | B88: E6 | C88: Conexiones del switch
A89: MH-031 | B89: E1 | C89: Velocidad Claro HFC | E89: ver hoja kb_minuta_credencial
A90: MH-031 | B90: E8 | C90: Dispositivos conectados
A91: MH-032 | B91: E1 | C91: Velocidad Movistar
A92: MH-033 | B92: E1 | C92: Speedtest de la red y de la tablet
A93: MH-033 | B93: E6 | C93: Cable de cámaras y punto de red directo
A94: MH-034 | B94: E1 | C94: Test de la red WiFi
A95: MH-035 | B95: E1 | C95: Velocidad Movistar HFC | E95: ver hoja kb_minuta_credencial
A96: MH-035 | B96: E8 | C96: Dispositivos conectados a la red
A97: MH-036 | B97: E6 | C97: Cable de caja mal ponchado; data center
A98: MH-037 | B98: E1 | C98: Velocidad de red desde el switch
A99: MH-037 | B99: E8 | C99: Dispositivos asociados a la red
A100: MH-038 | B100: E1 | C100: Velocidad en la laptop de ID
A101: MH-039 | B101: E5 | C101: Impresoras Caleta 01 y 02 | E101: ver hoja kb_minuta_credencial
A102: MH-040 | B102: E1 | C102: Velocidad por WiFi y por cable | E102: ver hoja kb_minuta_credencial
A103: MH-041 | B103: VIDEO | C103: Video del área y vista aérea de las tomas de energía
A104: MH-042 | B104: E5 | C104: Prueba de impresión
A105: MH-043 | B105: E1 | C105: Speedtest Caja 01 y Caja 02
A106: MH-043 | B106: E4 | C106: ipconfig Caja 01
A107: MH-043 | B107: E8 | C107: Escaneo 192.168.10.1-254
A108: MH-043 | B108: E5 | C108: Selftest de impresoras Caja 01 y Caja 02
A109: MH-043 | B109: E9 | C109: Fachada, interior y zona de cajas
A110: MH-044 | B110: E2 | C110: Router principal | E110: ver hoja kb_minuta_credencial
A111: MH-044 | B111: E9 | C111: Cafetería, terraza, privado y mesas

Sheet kb_regla_recomendacion
A1: regla_id | B1: categoria | C1: nombre | D1: disparador | E1: condicion_json | F1: hallazgo_as_is | G1: recomendacion_to_be | H1: responsable | I1: prioridad | J1: equipo_id | K1: fuente | L1: activa | M1: veces_en_minutas | N1: minutas_distintas | O1: veces_como_hallazgo
A2: R01 | B2: Internet | C2: Internet de respaldo 4G | D2: P16 = No (sin línea de respaldo) o P17 = Sí (hubo caídas) | E2: {"or":[{"eq":["$P16","NO"]},{"eq":["$P17","SI"]}]} | F2: El negocio depende de un solo enlace de internet. | G2: Instalar un router 4G con chip de datos exclusivo como respaldo para POS e impresoras ante caídas del enlace principal. | H2: Cliente | I2: Media | J2: EQ-ROUTER-4G | K2: Minutas Sicilia y Don Oscar; motor actual (redundancia) | L2: NO (unificada en R56) | M2: =IF(A2="","",COUNTIF(kb_minuta_recomendacion!$D$2:$D$2000,A2)) | N2: =IF(A2="","",SUMPRODUCT((kb_minuta_recomendacion!$D$2:$D$2000=A2)/COUNTIFS(kb_minuta_recomendacion!$D$2:$D$2000,kb_minuta_recomendacion!$D$2:$D$2000&"",kb_minuta_recomendacion!$A$2:$A$2000,kb_minuta_recomendacion!$A$2:$A$2000&""))) | O2: =IF(A2="","",COUNTIF(kb_minuta_hallazgo!$F$2:$F$2000,A2))
A3: R02 | B3: Impresión | C3: Raspberry para el controlador de impresiones | D3: Hay áreas de preparación (deducido de P11/P25), P22 = No, No sé u Otro y la impresora de caja no es USB (deducido de P27 + P30) | E3: {"and":[{"eq":["$derived.necesitaComandas",true]},{"in":["$P22",["NO","NO_SE","OTRO"]]},{"ne":["$derived.conexionImpresoraCaja","USB"]}]} | F3: El negocio necesita comandas, no hay PC ni laptop y las impresoras son de red. | G3: Recomendar un kit Raspberry para instalar el controlador (sistema de impresiones). Solo trabaja con impresoras de red: no sirve si la impresora de caja es USB. El kit se cotiza con el equipo de Desarrollo de Negocios. | H3: Cliente | I3: Alta | J3: EQ-RASPBERRY | K3: Regla de negocio IDPos (2026-10-06); flujo (P22); minutas Sicilia, Barrio Pesquero y Gelato Alore | L3: SI | M3: =IF(A3="","",COUNTIF(kb_minuta_recomendacion!$D$2:$D$2000,A3)) | N3: =IF(A3="","",SUMPRODUCT((kb_minuta_recomendacion!$D$2:$D$2000=A3)/COUNTIFS(kb_minuta_recomendacion!$D$2:$D$2000,kb_minuta_recomendacion!$D$2:$D$2000&"",kb_minuta_recomendacion!$A$2:$A$2000,kb_minuta_recomendacion!$A$2:$A$2000&""))) | O3: =IF(A3="","",COUNTIF(kb_minuta_hallazgo!$F$2:$F$2000,A3))
A4: R03 | B4: Energía | C4: Toma independiente para equipos de red | D4: P34 = Sí (comparten toma) o P36 = Sí (extensiones) | E4: {"or":[{"eq":["$P34","SI"]},{"eq":["$P36","SI"]}]} | F4: Los equipos de red comparten toma con otros equipos (riesgo de desconexión, p. ej. al conectar una licuadora). | G4: Habilitar una toma independiente para los equipos de red y un supresor de picos exclusivo para ellos. | H4: Cliente | I4: Alta | J4: EQ-SUPRESOR | K4: Minutas Sicilia y Don Oscar | L4: SI | M4: =IF(A4="","",COUNTIF(kb_minuta_recomendacion!$D$2:$D$2000,A4)) | N4: =IF(A4="","",SUMPRODUCT((kb_minuta_recomendacion!$D$2:$D$2000=A4)/COUNTIFS(kb_minuta_recomendacion!$D$2:$D$2000,kb_minuta_recomendacion!$D$2:$D$2000&"",kb_minuta_recomendacion!$A$2:$A$2000,kb_minuta_recomendacion!$A$2:$A$2000&""))) | O4: =IF(A4="","",COUNTIF(kb_minuta_hallazgo!$F$2:$F$2000,A4))
A5: R04 | B5: Energía | C5: UPS para router e impresoras | D5: P35 = No | E5: {"eq":["$P35","NO"]} | F5: No hay energía de respaldo. | G5: Recomendar UPS para router e impresoras. | H5: Cliente | I5: Media | J5: EQ-UPS | K5: Flujo (P35); minuta Rock & Burgers | L5: SI | M5: =IF(A5="","",COUNTIF(kb_minuta_recomendacion!$D$2:$D$2000,A5)) | N5: =IF(A5="","",SUMPRODUCT((kb_minuta_recomendacion!$D$2:$D$2000=A5)/COUNTIFS(kb_minuta_recomendacion!$D$2:$D$2000,kb_minuta_recomendacion!$D$2:$D$2000&"",kb_minuta_recomendacion!$A$2:$A$2000,kb_minuta_recomendacion!$A$2:$A$2000&""))) | O5: =IF(A5="","",COUNTIF(kb_minuta_hallazgo!$F$2:$F$2000,A5))
A6: R05 | B6: Cableado | C6: Switch para ampliar un punto de red | D6: P38 = No (áreas sin punto de red) o varios equipos de un área dependen de un solo punto | E6: {"eq":["$P38","NO"]} | F6: Un área necesita más puntos de red de los que tiene. | G6: Instalar un switch de 4 a 8 puertos en el área para repartir la conexión (impresora, repetidor, caja). | H6: Cliente | I6: Media | J6: EQ-SWITCH-NM | K6: Minutas Sicilia (terraza) y Barrio Pesquero (barra) | L6: SI | M6: =IF(A6="","",COUNTIF(kb_minuta_recomendacion!$D$2:$D$2000,A6)) | N6: =IF(A6="","",SUMPRODUCT((kb_minuta_recomendacion!$D$2:$D$2000=A6)/COUNTIFS(kb_minuta_recomendacion!$D$2:$D$2000,kb_minuta_recomendacion!$D$2:$D$2000&"",kb_minuta_recomendacion!$A$2:$A$2000,kb_minuta_recomendacion!$A$2:$A$2000&""))) | O6: =IF(A6="","",COUNTIF(kb_minuta_hallazgo!$F$2:$F$2000,A6))
A7: R06 | B7: Cableado | C7: Punto de red cerca de la impresora | D7: U1 = No para una impresora (no hay punto de red cerca) | E7: {"and":[{"eq":["$U1","NO"]},{"contains":["$ctx.equipo","Impresora"]}]} | F7: La impresora está lejos del punto de red. | G7: Instalar un punto de red cerca de la impresora antes de la siguiente visita. | H7: Cliente | I7: Alta | K7: Flujo (subflujo U); minuta Sicilia (cocina) | L7: SI | M7: =IF(A7="","",COUNTIF(kb_minuta_recomendacion!$D$2:$D$2000,A7)) | N7: =IF(A7="","",SUMPRODUCT((kb_minuta_recomendacion!$D$2:$D$2000=A7)/COUNTIFS(kb_minuta_recomendacion!$D$2:$D$2000,kb_minuta_recomendacion!$D$2:$D$2000&"",kb_minuta_recomendacion!$A$2:$A$2000,kb_minuta_recomendacion!$A$2:$A$2000&""))) | O7: =IF(A7="","",COUNTIF(kb_minuta_hallazgo!$F$2:$F$2000,A7))
A8: R07 | B8: Infraestructura | C8: Gabinete de pared | D8: P40 = No hay o Desordenado | E8: {"in":["$P40",["NO_HAY","DESORDENADO"]]} | F8: Los equipos de red no están en un gabinete ordenado. | G8: Adquirir un gabinete de pared de 4 RU, instalarlo a 1.65 m del piso y usar un supresor que solo alimente los equipos del gabinete. | H8: Cliente | I8: Media | J8: EQ-GABINETE-4RU | K8: Minuta Don Oscar | L8: SI | M8: =IF(A8="","",COUNTIF(kb_minuta_recomendacion!$D$2:$D$2000,A8)) | N8: =IF(A8="","",SUMPRODUCT((kb_minuta_recomendacion!$D$2:$D$2000=A8)/COUNTIFS(kb_minuta_recomendacion!$D$2:$D$2000,kb_minuta_recomendacion!$D$2:$D$2000&"",kb_minuta_recomendacion!$A$2:$A$2000,kb_minuta_recomendacion!$A$2:$A$2000&""))) | O8: =IF(A8="","",COUNTIF(kb_minuta_hallazgo!$F$2:$F$2000,A8))
A9: R08 | B9: Infraestructura | C9: Separar cables eléctricos en el gabinete | D9: P40 = Desordenado o con cables | E9: {"eq":["$P40","DESORDENADO"]} | F9: Gabinete desorganizado con cable eléctrico libre. | G9: Ordenar el gabinete y mantener los cables eléctricos aislados de los de red. | H9: Cliente | I9: Media | K9: Minuta Barrio Pesquero | L9: SI | M9: =IF(A9="","",COUNTIF(kb_minuta_recomendacion!$D$2:$D$2000,A9)) | N9: =IF(A9="","",SUMPRODUCT((kb_minuta_recomendacion!$D$2:$D$2000=A9)/COUNTIFS(kb_minuta_recomendacion!$D$2:$D$2000,kb_minuta_recomendacion!$D$2:$D$2000&"",kb_minuta_recomendacion!$A$2:$A$2000,kb_minuta_recomendacion!$A$2:$A$2000&""))) | O9: =IF(A9="","",COUNTIF(kb_minuta_hallazgo!$F$2:$F$2000,A9))
A10: R09 | B10: Cableado | C10: Cable Cat6 rotulado | D10: P39 = Interior Cat5e o No sé, o P41 = Sí (calor/grasa) | E10: {"or":[{"in":["$P39",["CAT5E_INT","NO_SE"]]},{"eq":["$P41","SI"]}]} | F10: Cableado antiguo o expuesto a calor. | G10: Cambiar los cables por Cat6 armados a medida y rotulados. | H10: ID | I10: Media | J10: EQ-CABLE-CAT6 | K10: Minuta Don Oscar | L10: SI | M10: =IF(A10="","",COUNTIF(kb_minuta_recomendacion!$D$2:$D$2000,A10)) | N10: =IF(A10="","",SUMPRODUCT((kb_minuta_recomendacion!$D$2:$D$2000=A10)/COUNTIFS(kb_minuta_recomendacion!$D$2:$D$2000,kb_minuta_recomendacion!$D$2:$D$2000&"",kb_minuta_recomendacion!$A$2:$A$2000,kb_minuta_recomendacion!$A$2:$A$2000&""))) | O10: =IF(A10="","",COUNTIF(kb_minuta_hallazgo!$F$2:$F$2000,A10))
A11: R10 | B11: Infraestructura | C11: Proteger equipos de grasa y calor | D11: P41 = Sí | E11: {"eq":["$P41","SI"]} | F11: Equipos expuestos a calor o grasa. | G11: Hacer cambios para evitar la acumulación de grasa en los equipos (reubicar o proteger). | H11: Cliente | I11: Media | K11: Minuta Don Oscar | L11: SI | M11: =IF(A11="","",COUNTIF(kb_minuta_recomendacion!$D$2:$D$2000,A11)) | N11: =IF(A11="","",SUMPRODUCT((kb_minuta_recomendacion!$D$2:$D$2000=A11)/COUNTIFS(kb_minuta_recomendacion!$D$2:$D$2000,kb_minuta_recomendacion!$D$2:$D$2000&"",kb_minuta_recomendacion!$A$2:$A$2000,kb_minuta_recomendacion!$A$2:$A$2000&""))) | O11: =IF(A11="","",COUNTIF(kb_minuta_hallazgo!$F$2:$F$2000,A11))
A12: R11 | B12: Cajas | C12: PC de caja por cable | D12: P23 = WiFi o el ipconfig (E4) muestra adaptador WiFi | E12: {"eq":["$P23","WIFI"]} | F12: La PC de caja está conectada por WiFi. | G12: Conectar la PC de caja al router o switch por cable Ethernet y reservar su IP en el DHCP. | H12: ID | I12: Alta | K12: Minutas Barrio Pesquero y Rock & Burgers; regla de validación V03 | L12: SI | M12: =IF(A12="","",COUNTIF(kb_minuta_recomendacion!$D$2:$D$2000,A12)) | N12: =IF(A12="","",SUMPRODUCT((kb_minuta_recomendacion!$D$2:$D$2000=A12)/COUNTIFS(kb_minuta_recomendacion!$D$2:$D$2000,kb_minuta_recomendacion!$D$2:$D$2000&"",kb_minuta_recomendacion!$A$2:$A$2000,kb_minuta_recomendacion!$A$2:$A$2000&""))) | O12: =IF(A12="","",COUNTIF(kb_minuta_hallazgo!$F$2:$F$2000,A12))
A13: R12 | B13: Impresión | C13: Impresoras conectadas directo a la red principal | D13: El mapa o el escáner (E8) muestran impresoras detrás de un repetidor | E13: {"manual":"impresora conectada vía repetidor"} | F13: Las impresoras comparten la red de los repetidores, sin conexión directa al módem. | G13: Conectar las impresoras por cable al router o a un switch de la red principal, no a través de repetidores. | H13: ID | I13: Alta | J13: EQ-SWITCH-NM | K13: Minuta Barrio Pesquero | L13: SI | M13: =IF(A13="","",COUNTIF(kb_minuta_recomendacion!$D$2:$D$2000,A13)) | N13: =IF(A13="","",SUMPRODUCT((kb_minuta_recomendacion!$D$2:$D$2000=A13)/COUNTIFS(kb_minuta_recomendacion!$D$2:$D$2000,kb_minuta_recomendacion!$D$2:$D$2000&"",kb_minuta_recomendacion!$A$2:$A$2000,kb_minuta_recomendacion!$A$2:$A$2000&""))) | O13: =IF(A13="","",COUNTIF(kb_minuta_hallazgo!$F$2:$F$2000,A13))
A14: R13 | B14: Red | C14: Equipos sin documentar a red de invitados | D14: Regla V06 en OBSERVADO | E14: {"validacion":"V06","estado":"OBSERVADO"} | F14: Hay equipos en la red que no están documentados. | G14: Identificar los equipos sin documentar; si no son del negocio, moverlos a una red WiFi de invitados separada de la operativa. | H14: ID | I14: Media | K14: Minuta generada Rock & Burgers | L14: SI | M14: =IF(A14="","",COUNTIF(kb_minuta_recomendacion!$D$2:$D$2000,A14)) | N14: =IF(A14="","",SUMPRODUCT((kb_minuta_recomendacion!$D$2:$D$2000=A14)/COUNTIFS(kb_minuta_recomendacion!$D$2:$D$2000,kb_minuta_recomendacion!$D$2:$D$2000&"",kb_minuta_recomendacion!$A$2:$A$2000,kb_minuta_recomendacion!$A$2:$A$2000&""))) | O14: =IF(A14="","",COUNTIF(kb_minuta_hallazgo!$F$2:$F$2000,A14))
A15: R14 | B15: Internet | C15: Latencia alta en hora punta | D15: Regla V02 en OBSERVADO (latencia ≥ MAX_LATENCY_MS) | E15: {"validacion":"V02","estado":"OBSERVADO"} | F15: Latencia alta con la red en uso. | G15: Medir la latencia en hora punta; si se confirma, priorizar el tráfico del POS (QoS) o poner un router propio detrás del terminal del proveedor. | H15: ID | I15: Media | J15: EQ-ROUTER-EMP | K15: Minuta generada Rock & Burgers | L15: SI | M15: =IF(A15="","",COUNTIF(kb_minuta_recomendacion!$D$2:$D$2000,A15)) | N15: =IF(A15="","",SUMPRODUCT((kb_minuta_recomendacion!$D$2:$D$2000=A15)/COUNTIFS(kb_minuta_recomendacion!$D$2:$D$2000,kb_minuta_recomendacion!$D$2:$D$2000&"",kb_minuta_recomendacion!$A$2:$A$2000,kb_minuta_recomendacion!$A$2:$A$2000&""))) | O15: =IF(A15="","",COUNTIF(kb_minuta_hallazgo!$F$2:$F$2000,A15))
A16: R15 | B16: Seguridad | C16: Cambiar contraseña de gestión del router | D16: Hay foto de la etiqueta del router (E3) | E16: {"evidencia":"E3"} | F16: La contraseña de gestión podría ser la de fábrica impresa en la etiqueta. | G16: Cambiar la contraseña de gestión del router si es la de fábrica. | H16: ID | I16: Media | K16: Minuta generada Rock & Burgers | L16: SI | M16: =IF(A16="","",COUNTIF(kb_minuta_recomendacion!$D$2:$D$2000,A16)) | N16: =IF(A16="","",SUMPRODUCT((kb_minuta_recomendacion!$D$2:$D$2000=A16)/COUNTIFS(kb_minuta_recomendacion!$D$2:$D$2000,kb_minuta_recomendacion!$D$2:$D$2000&"",kb_minuta_recomendacion!$A$2:$A$2000,kb_minuta_recomendacion!$A$2:$A$2000&""))) | O16: =IF(A16="","",COUNTIF(kb_minuta_hallazgo!$F$2:$F$2000,A16))
A17: R16 | B17: Impresión | C17: Impresora USB conectada al equipo con controlador | D17: P30 = USB y necesita comandas (deducido) | E17: {"and":[{"eq":["$P30","USB"]},{"eq":["$derived.necesitaComandas",true]}]} | F17: La impresora es USB: solo funciona conectada a una laptop o PC, e imprime mientras ese equipo esté encendido. | G17: Conectar la impresora USB a la laptop o PC que tiene el controlador de impresiones; así imprime comandas, pre-cuentas y comprobantes. Una impresora USB no funciona con Raspberry. Pasarla a red solo si debe imprimir sin depender de la PC. | H17: ID | I17: Media | K17: Regla de negocio IDPos (2026-10-06); minutas Rock & Burgers, RKT Banchero y Villa Flores; validación V08 | L17: SI | M17: =IF(A17="","",COUNTIF(kb_minuta_recomendacion!$D$2:$D$2000,A17)) | N17: =IF(A17="","",SUMPRODUCT((kb_minuta_recomendacion!$D$2:$D$2000=A17)/COUNTIFS(kb_minuta_recomendacion!$D$2:$D$2000,kb_minuta_recomendacion!$D$2:$D$2000&"",kb_minuta_recomendacion!$A$2:$A$2000,kb_minuta_recomendacion!$A$2:$A$2000&""))) | O17: =IF(A17="","",COUNTIF(kb_minuta_hallazgo!$F$2:$F$2000,A17))
A18: R17 | B18: Internet | C18: Plan de internet bajo | D18: P15 < 100 Mbps o velocidad medida < MIN_SPEED_MBPS | E18: {"lt":["$P15",100]} | F18: La velocidad contratada es baja para POS y WiFi. | G18: Evaluar un plan de mayor ancho de banda. | H18: Cliente | I18: Media | K18: Motor actual (proposal.py) | L18: SI | M18: =IF(A18="","",COUNTIF(kb_minuta_recomendacion!$D$2:$D$2000,A18)) | N18: =IF(A18="","",SUMPRODUCT((kb_minuta_recomendacion!$D$2:$D$2000=A18)/COUNTIFS(kb_minuta_recomendacion!$D$2:$D$2000,kb_minuta_recomendacion!$D$2:$D$2000&"",kb_minuta_recomendacion!$A$2:$A$2000,kb_minuta_recomendacion!$A$2:$A$2000&""))) | O18: =IF(A18="","",COUNTIF(kb_minuta_hallazgo!$F$2:$F$2000,A18))
A19: R18 | B19: Red | C19: Switch administrable | D19: No hay switch: las conexiones dependen del router | E19: {"manual":"sin switch"} | F19: Las conexiones cableadas dependen directamente del router o módem. | G19: Centralizar las conexiones cableadas en un switch administrable. | H19: Cliente | I19: Media | J19: EQ-SWITCH-ADM | K19: Motor actual (proposal.py); minuta Don Oscar (equipos directo al módem) | L19: SI | M19: =IF(A19="","",COUNTIF(kb_minuta_recomendacion!$D$2:$D$2000,A19)) | N19: =IF(A19="","",SUMPRODUCT((kb_minuta_recomendacion!$D$2:$D$2000=A19)/COUNTIFS(kb_minuta_recomendacion!$D$2:$D$2000,kb_minuta_recomendacion!$D$2:$D$2000&"",kb_minuta_recomendacion!$A$2:$A$2000,kb_minuta_recomendacion!$A$2:$A$2000&""))) | O19: =IF(A19="","",COUNTIF(kb_minuta_hallazgo!$F$2:$F$2000,A19))
A20: R19 | B20: WiFi | C20: Cobertura WiFi en todo el local (repetidor o access point) | D20: P46 tiene áreas (zonas sin señal WiFi) | E20: {"notEmpty":"$P46"} | F20: Hay zonas sin señal WiFi. Los meseros comandan desde celular, tablet, PC, laptop o Sunmi por WiFi y en esas zonas no pueden acceder al sistema. | G20: Colocar un repetidor o un access point para cubrir las zonas sin señal. Todo el local (salones, terraza, barra) debe tener WiFi para que los meseros comanden. | H20: Cliente | I20: Alta | J20: EQ-AP-WIFI6 | K20: Regla de negocio IDPos (2026-10-06); motor actual (proposal.py) | L20: SI | M20: =IF(A20="","",COUNTIF(kb_minuta_recomendacion!$D$2:$D$2000,A20)) | N20: =IF(A20="","",SUMPRODUCT((kb_minuta_recomendacion!$D$2:$D$2000=A20)/COUNTIFS(kb_minuta_recomendacion!$D$2:$D$2000,kb_minuta_recomendacion!$D$2:$D$2000&"",kb_minuta_recomendacion!$A$2:$A$2000,kb_minuta_recomendacion!$A$2:$A$2000&""))) | O20: =IF(A20="","",COUNTIF(kb_minuta_hallazgo!$F$2:$F$2000,A20))
A21: R20 | B21: Red | C21: Switch PoE para cámaras | D21: P47 = Sí | E21: {"eq":["$P47","SI"]} | F21: Hay cámaras en la red. | G21: Usar un switch PoE para alimentar cámaras y access points por el mismo cable. | H21: Cliente | I21: Baja | J21: EQ-SWITCH-POE | K21: Motor actual (proposal.py) | L21: SI | M21: =IF(A21="","",COUNTIF(kb_minuta_recomendacion!$D$2:$D$2000,A21)) | N21: =IF(A21="","",SUMPRODUCT((kb_minuta_recomendacion!$D$2:$D$2000=A21)/COUNTIFS(kb_minuta_recomendacion!$D$2:$D$2000,kb_minuta_recomendacion!$D$2:$D$2000&"",kb_minuta_recomendacion!$A$2:$A$2000,kb_minuta_recomendacion!$A$2:$A$2000&""))) | O21: =IF(A21="","",COUNTIF(kb_minuta_hallazgo!$F$2:$F$2000,A21))
A22: R21 | B22: Red | C22: VLAN para cajas y POS | D22: P12 > 0 | E22: {"gt":["$P12",0]} | F22: El tráfico de cajas comparte la red con los demás equipos. | G22: Separar el tráfico de POS/cajas en una VLAN exclusiva. | H22: ID | I22: Baja | J22: EQ-SWITCH-ADM | K22: Motor actual (proposal.py) | L22: SI | M22: =IF(A22="","",COUNTIF(kb_minuta_recomendacion!$D$2:$D$2000,A22)) | N22: =IF(A22="","",SUMPRODUCT((kb_minuta_recomendacion!$D$2:$D$2000=A22)/COUNTIFS(kb_minuta_recomendacion!$D$2:$D$2000,kb_minuta_recomendacion!$D$2:$D$2000&"",kb_minuta_recomendacion!$A$2:$A$2000,kb_minuta_recomendacion!$A$2:$A$2000&""))) | O22: =IF(A22="","",COUNTIF(kb_minuta_hallazgo!$F$2:$F$2000,A22))
A23: R22 | B23: Energía | C23: Tomacorrientes junto a puntos de red | D23: P33 = No | E23: {"eq":["$P33","NO"]} | F23: No hay tomas cerca de los equipos de red. | G23: Habilitar tomacorrientes adyacentes a cada punto de red (TIA/EIA-568). | H23: Cliente | I23: Alta | K23: Motor actual (proposal.py); flujo (P33) | L23: SI | M23: =IF(A23="","",COUNTIF(kb_minuta_recomendacion!$D$2:$D$2000,A23)) | N23: =IF(A23="","",SUMPRODUCT((kb_minuta_recomendacion!$D$2:$D$2000=A23)/COUNTIFS(kb_minuta_recomendacion!$D$2:$D$2000,kb_minuta_recomendacion!$D$2:$D$2000&"",kb_minuta_recomendacion!$A$2:$A$2000,kb_minuta_recomendacion!$A$2:$A$2000&""))) | O23: =IF(A23="","",COUNTIF(kb_minuta_hallazgo!$F$2:$F$2000,A23))
A24: R23 | B24: Internet | C24: Confirmar proveedor | D24: Regla V07 en REVISAR | E24: {"validacion":"V07","estado":"REVISAR"} | F24: El proveedor indicado no coincide con el de las evidencias. | G24: Confirmar con el cliente qué proveedor se usa realmente. | H24: ID | I24: Baja | K24: Regla de validación V07 | L24: SI | M24: =IF(A24="","",COUNTIF(kb_minuta_recomendacion!$D$2:$D$2000,A24)) | N24: =IF(A24="","",SUMPRODUCT((kb_minuta_recomendacion!$D$2:$D$2000=A24)/COUNTIFS(kb_minuta_recomendacion!$D$2:$D$2000,kb_minuta_recomendacion!$D$2:$D$2000&"",kb_minuta_recomendacion!$A$2:$A$2000,kb_minuta_recomendacion!$A$2:$A$2000&""))) | O24: =IF(A24="","",COUNTIF(kb_minuta_hallazgo!$F$2:$F$2000,A24))
A25: R24 | B25: Impresión | C25: IP fija para impresoras de red | D25: Regla V04 en OBSERVADO | E25: {"validacion":"V04","estado":"OBSERVADO"} | F25: Una impresora de red no tiene IP fija dentro del segmento. | G25: Fijar la IP de la impresora dentro del segmento del router (desactivar DHCP). | H25: ID | I25: Alta | K25: Regla de validación V04 | L25: SI | M25: =IF(A25="","",COUNTIF(kb_minuta_recomendacion!$D$2:$D$2000,A25)) | N25: =IF(A25="","",SUMPRODUCT((kb_minuta_recomendacion!$D$2:$D$2000=A25)/COUNTIFS(kb_minuta_recomendacion!$D$2:$D$2000,kb_minuta_recomendacion!$D$2:$D$2000&"",kb_minuta_recomendacion!$A$2:$A$2000,kb_minuta_recomendacion!$A$2:$A$2000&""))) | O25: =IF(A25="","",COUNTIF(kb_minuta_hallazgo!$F$2:$F$2000,A25))
A26: R25 | B26: Energía | C26: Retirar extensiones | D26: P36 = Sí | E26: {"eq":["$P36","SI"]} | F26: Hay equipos de red o impresoras conectados a extensiones. | G26: Pasar los equipos de la extensión a una toma directa o a un UPS. | H26: Cliente | I26: Alta | J26: EQ-UPS | K26: Flujo (P36a) | L26: SI | M26: =IF(A26="","",COUNTIF(kb_minuta_recomendacion!$D$2:$D$2000,A26)) | N26: =IF(A26="","",SUMPRODUCT((kb_minuta_recomendacion!$D$2:$D$2000=A26)/COUNTIFS(kb_minuta_recomendacion!$D$2:$D$2000,kb_minuta_recomendacion!$D$2:$D$2000&"",kb_minuta_recomendacion!$A$2:$A$2000,kb_minuta_recomendacion!$A$2:$A$2000&""))) | O26: =IF(A26="","",COUNTIF(kb_minuta_hallazgo!$F$2:$F$2000,A26))
A27: R26 | B27: Visita | C27: Segunda visita técnica | D27: P50 = Sí | E27: {"eq":["$P50","SI"]} | F27: Quedan trabajos pendientes en el local. | G27: Agendar una segunda visita técnica (motivo en P50a). | H27: ID | I27: Alta | K27: Flujo (P50); minuta Sicilia | L27: SI | M27: =IF(A27="","",COUNTIF(kb_minuta_recomendacion!$D$2:$D$2000,A27)) | N27: =IF(A27="","",SUMPRODUCT((kb_minuta_recomendacion!$D$2:$D$2000=A27)/COUNTIFS(kb_minuta_recomendacion!$D$2:$D$2000,kb_minuta_recomendacion!$D$2:$D$2000&"",kb_minuta_recomendacion!$A$2:$A$2000,kb_minuta_recomendacion!$A$2:$A$2000&""))) | O27: =IF(A27="","",COUNTIF(kb_minuta_hallazgo!$F$2:$F$2000,A27))
A28: R27 | B28: Mantenimiento | C28: Mantenimiento de equipos y tomas | D28: Equipos con suciedad o grasa observados en la visita | E28: {"manual":"mantenimiento"} | F28: Equipos de red y tomas con suciedad. | G28: Dar mantenimiento a los equipos de red (router, módem, Raspberry) y limpiar las tomas de energía. | H28: ID | I28: Baja | K28: Minuta Don Oscar | L28: SI | M28: =IF(A28="","",COUNTIF(kb_minuta_recomendacion!$D$2:$D$2000,A28)) | N28: =IF(A28="","",SUMPRODUCT((kb_minuta_recomendacion!$D$2:$D$2000=A28)/COUNTIFS(kb_minuta_recomendacion!$D$2:$D$2000,kb_minuta_recomendacion!$D$2:$D$2000&"",kb_minuta_recomendacion!$A$2:$A$2000,kb_minuta_recomendacion!$A$2:$A$2000&""))) | O28: =IF(A28="","",COUNTIF(kb_minuta_hallazgo!$F$2:$F$2000,A28))
A29: R28 | B29: Seguridad | C29: Firewall y segmentación | D29: El cliente requiere firewall o VLAN | E29: {"manual":"servicios firewall/vlan"} | F29: No hay segmentación ni firewall. | G29: Implementar firewall y segmentación por VLAN. | H29: ID | I29: Baja | J29: EQ-ROUTER-EMP | K29: Motor actual (proposal.py) | L29: SI | M29: =IF(A29="","",COUNTIF(kb_minuta_recomendacion!$D$2:$D$2000,A29)) | N29: =IF(A29="","",SUMPRODUCT((kb_minuta_recomendacion!$D$2:$D$2000=A29)/COUNTIFS(kb_minuta_recomendacion!$D$2:$D$2000,kb_minuta_recomendacion!$D$2:$D$2000&"",kb_minuta_recomendacion!$A$2:$A$2000,kb_minuta_recomendacion!$A$2:$A$2000&""))) | O29: =IF(A29="","",COUNTIF(kb_minuta_hallazgo!$F$2:$F$2000,A29))
A30: A01 | B30: Acción estándar | C30: Compartir la minuta técnica | D30: Siempre | E30: {"siempre":true} | G30: Compartir la minuta técnica con el cliente. | H30: ID | I30: Alta | K30: Minutas Don Oscar, Barrio Pesquero y Rock & Burgers | L30: SI | M30: =IF(A30="","",COUNTIF(kb_minuta_recomendacion!$D$2:$D$2000,A30)) | N30: =IF(A30="","",SUMPRODUCT((kb_minuta_recomendacion!$D$2:$D$2000=A30)/COUNTIFS(kb_minuta_recomendacion!$D$2:$D$2000,kb_minuta_recomendacion!$D$2:$D$2000&"",kb_minuta_recomendacion!$A$2:$A$2000,kb_minuta_recomendacion!$A$2:$A$2000&""))) | O30: =IF(A30="","",COUNTIF(kb_minuta_hallazgo!$F$2:$F$2000,A30))
A31: A02 | B31: Acción estándar | C31: Confirmar recepción de la minuta | D31: Siempre | E31: {"siempre":true} | G31: Confirmar la recepción de la minuta de visita técnica. | H31: Cliente | I31: Alta | K31: Minutas Sicilia, Don Oscar y Barrio Pesquero | L31: SI | M31: =IF(A31="","",COUNTIF(kb_minuta_recomendacion!$D$2:$D$2000,A31)) | N31: =IF(A31="","",SUMPRODUCT((kb_minuta_recomendacion!$D$2:$D$2000=A31)/COUNTIFS(kb_minuta_recomendacion!$D$2:$D$2000,kb_minuta_recomendacion!$D$2:$D$2000&"",kb_minuta_recomendacion!$A$2:$A$2000,kb_minuta_recomendacion!$A$2:$A$2000&""))) | O31: =IF(A31="","",COUNTIF(kb_minuta_hallazgo!$F$2:$F$2000,A31))
A32: A03 | B32: Acción estándar | C32: Enviar cotización de equipos | D32: Hay equipos recomendados | E32: {"manual":"equipos recomendados"} | G32: Enviar la cotización de los equipos recomendados. | H32: ID | I32: Media | K32: Minuta Barrio Pesquero | L32: SI | M32: =IF(A32="","",COUNTIF(kb_minuta_recomendacion!$D$2:$D$2000,A32)) | N32: =IF(A32="","",SUMPRODUCT((kb_minuta_recomendacion!$D$2:$D$2000=A32)/COUNTIFS(kb_minuta_recomendacion!$D$2:$D$2000,kb_minuta_recomendacion!$D$2:$D$2000&"",kb_minuta_recomendacion!$A$2:$A$2000,kb_minuta_recomendacion!$A$2:$A$2000&""))) | O32: =IF(A32="","",COUNTIF(kb_minuta_hallazgo!$F$2:$F$2000,A32))
A33: A04 | B33: Acción estándar | C33: Capacitación e inicio con el sistema | D33: Siempre (visita para implementar IDPos) | E33: {"siempre":true} | G33: Realizar la capacitación e inicio con el sistema en la fecha acordada. | H33: ID | I33: Alta | K33: Minuta Rock & Burgers | L33: SI | M33: =IF(A33="","",COUNTIF(kb_minuta_recomendacion!$D$2:$D$2000,A33)) | N33: =IF(A33="","",SUMPRODUCT((kb_minuta_recomendacion!$D$2:$D$2000=A33)/COUNTIFS(kb_minuta_recomendacion!$D$2:$D$2000,kb_minuta_recomendacion!$D$2:$D$2000&"",kb_minuta_recomendacion!$A$2:$A$2000,kb_minuta_recomendacion!$A$2:$A$2000&""))) | O33: =IF(A33="","",COUNTIF(kb_minuta_hallazgo!$F$2:$F$2000,A33))
A34: A05 | B34: Acción estándar | C34: Pruebas de comanda con impresoras | D34: Hay impresoras configuradas | E34: {"gt":["$P26",0]} | G34: Realizar pruebas de comanda con cada impresora. | H34: ID | I34: Media | K34: Minuta Rock & Burgers | L34: SI | M34: =IF(A34="","",COUNTIF(kb_minuta_recomendacion!$D$2:$D$2000,A34)) | N34: =IF(A34="","",SUMPRODUCT((kb_minuta_recomendacion!$D$2:$D$2000=A34)/COUNTIFS(kb_minuta_recomendacion!$D$2:$D$2000,kb_minuta_recomendacion!$D$2:$D$2000&"",kb_minuta_recomendacion!$A$2:$A$2000,kb_minuta_recomendacion!$A$2:$A$2000&""))) | O34: =IF(A34="","",COUNTIF(kb_minuta_hallazgo!$F$2:$F$2000,A34))
A35: A06 | B35: Acción estándar | C35: Lista de usuarios del sistema | D35: Siempre (visita para implementar IDPos) | E35: {"siempre":true} | G35: Enviar la lista de usuarios que tendrán acceso (p. ej. meseros). | H35: Cliente | I35: Media | K35: Minuta Rock & Burgers | L35: SI | M35: =IF(A35="","",COUNTIF(kb_minuta_recomendacion!$D$2:$D$2000,A35)) | N35: =IF(A35="","",SUMPRODUCT((kb_minuta_recomendacion!$D$2:$D$2000=A35)/COUNTIFS(kb_minuta_recomendacion!$D$2:$D$2000,kb_minuta_recomendacion!$D$2:$D$2000&"",kb_minuta_recomendacion!$A$2:$A$2000,kb_minuta_recomendacion!$A$2:$A$2000&""))) | O35: =IF(A35="","",COUNTIF(kb_minuta_hallazgo!$F$2:$F$2000,A35))
A36: A07 | B36: Acción estándar | C36: Enviar información del negocio | D36: Siempre (visita para implementar IDPos) | E36: {"siempre":true} | G36: Enviar la información del negocio (Excel, carta, usuarios) en el formato que comparte ID. | H36: Cliente | I36: Media | K36: Minuta Sicilia; minutas RKT (carta) | L36: SI | M36: =IF(A36="","",COUNTIF(kb_minuta_recomendacion!$D$2:$D$2000,A36)) | N36: =IF(A36="","",SUMPRODUCT((kb_minuta_recomendacion!$D$2:$D$2000=A36)/COUNTIFS(kb_minuta_recomendacion!$D$2:$D$2000,kb_minuta_recomendacion!$D$2:$D$2000&"",kb_minuta_recomendacion!$A$2:$A$2000,kb_minuta_recomendacion!$A$2:$A$2000&""))) | O36: =IF(A36="","",COUNTIF(kb_minuta_hallazgo!$F$2:$F$2000,A36))
A37: R29 | B37: Red | C37: Una sola red para POS e impresoras | D37: Hay dos proveedores o routers y los equipos quedan repartidos entre redes | E37: {"manual":"equipos en redes distintas"} | F37: PC de caja e impresoras están en redes distintas; desde una no se llega a la otra y dejan de imprimir. | G37: Conectar todas las PC de caja e impresoras a una misma red y dejar la otra solo como respaldo o para clientes. | H37: ID | I37: Alta | K37: Minutas Dorcher San Miguel (14/04/23 y 27/05/23) | L37: SI | M37: =IF(A37="","",COUNTIF(kb_minuta_recomendacion!$D$2:$D$2000,A37)) | N37: =IF(A37="","",SUMPRODUCT((kb_minuta_recomendacion!$D$2:$D$2000=A37)/COUNTIFS(kb_minuta_recomendacion!$D$2:$D$2000,kb_minuta_recomendacion!$D$2:$D$2000&"",kb_minuta_recomendacion!$A$2:$A$2000,kb_minuta_recomendacion!$A$2:$A$2000&""))) | O37: =IF(A37="","",COUNTIF(kb_minuta_hallazgo!$F$2:$F$2000,A37))
A38: R30 | B38: Cableado | C38: Rotular cables y no moverlos sin avisar | D38: Se reconfiguró o reordenó el cableado durante la visita | E38: {"manual":"cableado reconfigurado"} | F38: El personal mueve cables de red entre routers y se pierde la impresión. | G38: Rotular los cables de red de cada equipo y no hacer cambios en el cableado sin informar antes a ID. | H38: Cliente | I38: Alta | K38: Minuta Dorcher San Miguel 27/05/23; minuta Don Oscar (rotulado) | L38: SI | M38: =IF(A38="","",COUNTIF(kb_minuta_recomendacion!$D$2:$D$2000,A38)) | N38: =IF(A38="","",SUMPRODUCT((kb_minuta_recomendacion!$D$2:$D$2000=A38)/COUNTIFS(kb_minuta_recomendacion!$D$2:$D$2000,kb_minuta_recomendacion!$D$2:$D$2000&"",kb_minuta_recomendacion!$A$2:$A$2000,kb_minuta_recomendacion!$A$2:$A$2000&""))) | O38: =IF(A38="","",COUNTIF(kb_minuta_hallazgo!$F$2:$F$2000,A38))
A39: R31 | B39: Red | C39: Reemplazar switch defectuoso | D39: La velocidad llega inestable a un área y el switch del área falla | E39: {"manual":"switch con falla"} | F39: Un switch con falla corta o degrada la red de las PC de caja. | G39: Reemplazar el switch defectuoso y medir la velocidad en cada PC después del cambio. | H39: ID | I39: Alta | J39: EQ-SWITCH-NM | K39: Minuta Dorcher San Miguel 14/04/23 | L39: SI | M39: =IF(A39="","",COUNTIF(kb_minuta_recomendacion!$D$2:$D$2000,A39)) | N39: =IF(A39="","",SUMPRODUCT((kb_minuta_recomendacion!$D$2:$D$2000=A39)/COUNTIFS(kb_minuta_recomendacion!$D$2:$D$2000,kb_minuta_recomendacion!$D$2:$D$2000&"",kb_minuta_recomendacion!$A$2:$A$2000,kb_minuta_recomendacion!$A$2:$A$2000&""))) | O39: =IF(A39="","",COUNTIF(kb_minuta_hallazgo!$F$2:$F$2000,A39))
A40: R32 | B40: WiFi | C40: Red WiFi definida para tablets | D40: Hay tablets de meseros con conectividad variable | E40: {"manual":"tablets con conectividad variable"} | F40: Las tablets se conectan a redes distintas y algunas pierden conexión. | G40: Definir la red WiFi que usará cada tablet, probar su conexión una por una y separarla de la red de clientes cuando sea posible. | H40: ID | I40: Media | K40: Minutas Dorcher San Miguel (14/04/23 y 27/05/23) | L40: SI | M40: =IF(A40="","",COUNTIF(kb_minuta_recomendacion!$D$2:$D$2000,A40)) | N40: =IF(A40="","",SUMPRODUCT((kb_minuta_recomendacion!$D$2:$D$2000=A40)/COUNTIFS(kb_minuta_recomendacion!$D$2:$D$2000,kb_minuta_recomendacion!$D$2:$D$2000&"",kb_minuta_recomendacion!$A$2:$A$2000,kb_minuta_recomendacion!$A$2:$A$2000&""))) | O40: =IF(A40="","",COUNTIF(kb_minuta_hallazgo!$F$2:$F$2000,A40))
A41: R33 | B41: Internet | C41: Cambiar a un proveedor más estable | D41: P14 no es Fibra ni Cable coaxial, plan con datos limitados o P17 = Sí (caídas frecuentes) | E41: {"or":[{"and":[{"ne":["$P14","FIBRA"]},{"ne":["$P14","COAXIAL"]}]},{"eq":["$P17","SI"]}]} | F41: El internet es satelital, móvil o de un proveedor con caídas frecuentes. | G41: Evaluar internet por fibra (o Starlink donde no llega la fibra) y monitorear el consumo del plan mientras tanto. | H41: Cliente | I41: Media | K41: Minutas Hotel La Confianza y Malala | L41: SI | M41: =IF(A41="","",COUNTIF(kb_minuta_recomendacion!$D$2:$D$2000,A41)) | N41: =IF(A41="","",SUMPRODUCT((kb_minuta_recomendacion!$D$2:$D$2000=A41)/COUNTIFS(kb_minuta_recomendacion!$D$2:$D$2000,kb_minuta_recomendacion!$D$2:$D$2000&"",kb_minuta_recomendacion!$A$2:$A$2000,kb_minuta_recomendacion!$A$2:$A$2000&""))) | O41: =IF(A41="","",COUNTIF(kb_minuta_hallazgo!$F$2:$F$2000,A41))
A42: R34 | B42: Impresión | C42: Ubicar el Raspberry en un lugar protegido | D42: El Raspberry está al alcance del personal o en la mesa de trabajo | E42: {"manual":"raspberry expuesto"} | F42: El Raspberry está en una zona de trabajo donde puede desconectarse o dañarse. | G42: Mover el Raspberry a un punto protegido e inaccesible para el personal, con toma y punto de red propios. | H42: Cliente | I42: Media | J42: EQ-RASPBERRY | K42: Minuta Hotel La Confianza | L42: SI | M42: =IF(A42="","",COUNTIF(kb_minuta_recomendacion!$D$2:$D$2000,A42)) | N42: =IF(A42="","",SUMPRODUCT((kb_minuta_recomendacion!$D$2:$D$2000=A42)/COUNTIFS(kb_minuta_recomendacion!$D$2:$D$2000,kb_minuta_recomendacion!$D$2:$D$2000&"",kb_minuta_recomendacion!$A$2:$A$2000,kb_minuta_recomendacion!$A$2:$A$2000&""))) | O42: =IF(A42="","",COUNTIF(kb_minuta_hallazgo!$F$2:$F$2000,A42))
A43: R35 | B43: Sistema | C43: Zona horaria correcta en las PC | D43: Las aperturas o reportes se registran en días anteriores | E43: {"manual":"zona horaria incorrecta"} | F43: La PC tiene otra zona horaria y las aperturas de caja se registran en días anteriores. | G43: Configurar la zona horaria de Perú (UTC-5) en todas las PC que usan el sistema. | H43: ID | I43: Media | K43: Minuta Hotel La Confianza | L43: SI | M43: =IF(A43="","",COUNTIF(kb_minuta_recomendacion!$D$2:$D$2000,A43)) | N43: =IF(A43="","",SUMPRODUCT((kb_minuta_recomendacion!$D$2:$D$2000=A43)/COUNTIFS(kb_minuta_recomendacion!$D$2:$D$2000,kb_minuta_recomendacion!$D$2:$D$2000&"",kb_minuta_recomendacion!$A$2:$A$2000,kb_minuta_recomendacion!$A$2:$A$2000&""))) | O43: =IF(A43="","",COUNTIF(kb_minuta_hallazgo!$F$2:$F$2000,A43))
A44: R36 | B44: Sistema | C44: Dejar cargar el sistema antes de operar | D44: Internet lento o de alta latencia | E44: {"manual":"internet de alta latencia"} | F44: Con internet lento, operar antes de que cargue el sistema mezcla o duplica datos. | G44: Esperar a que IDPos cargue por completo antes de operar, sobre todo después de actualizaciones. | H44: Cliente | I44: Baja | K44: Minuta Hotel La Confianza | L44: SI | M44: =IF(A44="","",COUNTIF(kb_minuta_recomendacion!$D$2:$D$2000,A44)) | N44: =IF(A44="","",SUMPRODUCT((kb_minuta_recomendacion!$D$2:$D$2000=A44)/COUNTIFS(kb_minuta_recomendacion!$D$2:$D$2000,kb_minuta_recomendacion!$D$2:$D$2000&"",kb_minuta_recomendacion!$A$2:$A$2000,kb_minuta_recomendacion!$A$2:$A$2000&""))) | O44: =IF(A44="","",COUNTIF(kb_minuta_hallazgo!$F$2:$F$2000,A44))
A45: R37 | B45: Cableado | C45: Cambiar conectores de red desgastados | D45: Conectores RJ45 holgados o gastados en impresoras o equipos | E45: {"manual":"conectores holgados"} | F45: Los conectores de los cables de red están holgados y pueden causar intermitencia. | G45: Cambiar los conectores RJ45 desgastados de las impresoras y probar la conexión. | H45: Cliente | I45: Media | J45: EQ-CABLE-CAT6 | K45: Minuta RKT Bayóvar | L45: SI | M45: =IF(A45="","",COUNTIF(kb_minuta_recomendacion!$D$2:$D$2000,A45)) | N45: =IF(A45="","",SUMPRODUCT((kb_minuta_recomendacion!$D$2:$D$2000=A45)/COUNTIFS(kb_minuta_recomendacion!$D$2:$D$2000,kb_minuta_recomendacion!$D$2:$D$2000&"",kb_minuta_recomendacion!$A$2:$A$2000,kb_minuta_recomendacion!$A$2:$A$2000&""))) | O45: =IF(A45="","",COUNTIF(kb_minuta_hallazgo!$F$2:$F$2000,A45))
A46: R38 | B46: Impresión | C46: Impresora para área que prepara sin comandas | D46: Un área de P25 queda sin impresora (aviso A_SIN_IMPRESORA) | E46: {"notEmpty":"$derived.areasSinImpresora"} | F46: Un área prepara pedidos sin recibir comandas impresas. | G46: Instalar una impresora ticketera de red en el área, con su punto de red, para comandas y pre-cuentas. | H46: Cliente | I46: Alta | K46: Minuta RKT Mariscal (barra del piso 2); flujo (P32) | L46: SI | M46: =IF(A46="","",COUNTIF(kb_minuta_recomendacion!$D$2:$D$2000,A46)) | N46: =IF(A46="","",SUMPRODUCT((kb_minuta_recomendacion!$D$2:$D$2000=A46)/COUNTIFS(kb_minuta_recomendacion!$D$2:$D$2000,kb_minuta_recomendacion!$D$2:$D$2000&"",kb_minuta_recomendacion!$A$2:$A$2000,kb_minuta_recomendacion!$A$2:$A$2000&""))) | O46: =IF(A46="","",COUNTIF(kb_minuta_hallazgo!$F$2:$F$2000,A46))
A47: R39 | B47: Equipamiento | C47: Equipo de pedidos adicional por piso | D47: P10 > 1 y un solo equipo para tomar pedidos | E47: {"gt":["$P10",1]} | F47: Hay más de un piso y un solo equipo para tomar pedidos. | G47: Contar con una tablet o monitor de pedidos adicional en el otro piso para agilizar el ingreso de órdenes. | H47: Cliente | I47: Baja | K47: Minutas RKT Calle 8 y Malala | L47: SI | M47: =IF(A47="","",COUNTIF(kb_minuta_recomendacion!$D$2:$D$2000,A47)) | N47: =IF(A47="","",SUMPRODUCT((kb_minuta_recomendacion!$D$2:$D$2000=A47)/COUNTIFS(kb_minuta_recomendacion!$D$2:$D$2000,kb_minuta_recomendacion!$D$2:$D$2000&"",kb_minuta_recomendacion!$A$2:$A$2000,kb_minuta_recomendacion!$A$2:$A$2000&""))) | O47: =IF(A47="","",COUNTIF(kb_minuta_hallazgo!$F$2:$F$2000,A47))
A48: A08 | B48: Acción estándar | C48: Confirmar fecha de inicio con IDPos | D48: El técnico indica una fecha de inicio (P50b) | E48: {"notEmpty":"$P50b"} | G48: Confirmar la fecha de inicio con IDPos. | H48: Cliente | I48: Alta | K48: Minutas Gelato Alore | L48: SI | M48: =IF(A48="","",COUNTIF(kb_minuta_recomendacion!$D$2:$D$2000,A48)) | N48: =IF(A48="","",SUMPRODUCT((kb_minuta_recomendacion!$D$2:$D$2000=A48)/COUNTIFS(kb_minuta_recomendacion!$D$2:$D$2000,kb_minuta_recomendacion!$D$2:$D$2000&"",kb_minuta_recomendacion!$A$2:$A$2000,kb_minuta_recomendacion!$A$2:$A$2000&""))) | O48: =IF(A48="","",COUNTIF(kb_minuta_hallazgo!$F$2:$F$2000,A48))
A49: A09 | B49: Acción estándar | C49: Seguimiento al local | D49: Estado del local En obra o Por inaugurar, o hay trabajos pendientes | E49: {"in":["$P08",["EN_OBRA","POR_INAUGURAR"]]} | G49: Dar seguimiento a la red del local (remoto o videollamada) después de la visita. | H49: ID | I49: Media | K49: Minutas Dorcher San Miguel y Hotel La Confianza | L49: SI | M49: =IF(A49="","",COUNTIF(kb_minuta_recomendacion!$D$2:$D$2000,A49)) | N49: =IF(A49="","",SUMPRODUCT((kb_minuta_recomendacion!$D$2:$D$2000=A49)/COUNTIFS(kb_minuta_recomendacion!$D$2:$D$2000,kb_minuta_recomendacion!$D$2:$D$2000&"",kb_minuta_recomendacion!$A$2:$A$2000,kb_minuta_recomendacion!$A$2:$A$2000&""))) | O49: =IF(A49="","",COUNTIF(kb_minuta_hallazgo!$F$2:$F$2000,A49))
A50: A10 | B50: Acción estándar | C50: Configurar el sistema de impresiones | D50: Hay controlador de impresiones por instalar (PC, laptop o Raspberry) | E50: {"manual":"controlador por instalar"} | G50: Configurar el sistema de impresiones en la PC de caja o el Raspberry. | H50: ID | I50: Alta | K50: Minuta RKT Hacienda | L50: SI | M50: =IF(A50="","",COUNTIF(kb_minuta_recomendacion!$D$2:$D$2000,A50)) | N50: =IF(A50="","",SUMPRODUCT((kb_minuta_recomendacion!$D$2:$D$2000=A50)/COUNTIFS(kb_minuta_recomendacion!$D$2:$D$2000,kb_minuta_recomendacion!$D$2:$D$2000&"",kb_minuta_recomendacion!$A$2:$A$2000,kb_minuta_recomendacion!$A$2:$A$2000&""))) | O50: =IF(A50="","",COUNTIF(kb_minuta_hallazgo!$F$2:$F$2000,A50))
A51: A11 | B51: Acción estándar | C51: Cotizar o confirmar compra de equipos | D51: Hay equipos recomendados | E51: {"manual":"equipos recomendados"} | G51: Solicitar o confirmar la cotización de los equipos recomendados. | H51: Cliente | I51: Media | K51: Minutas RKT y Gelato Alore | L51: SI | M51: =IF(A51="","",COUNTIF(kb_minuta_recomendacion!$D$2:$D$2000,A51)) | N51: =IF(A51="","",SUMPRODUCT((kb_minuta_recomendacion!$D$2:$D$2000=A51)/COUNTIFS(kb_minuta_recomendacion!$D$2:$D$2000,kb_minuta_recomendacion!$D$2:$D$2000&"",kb_minuta_recomendacion!$A$2:$A$2000,kb_minuta_recomendacion!$A$2:$A$2000&""))) | O51: =IF(A51="","",COUNTIF(kb_minuta_hallazgo!$F$2:$F$2000,A51))
A52: A12 | B52: Acción estándar | C52: Avisar cuando la instalación esté lista | D52: Hay trabajos pendientes del cliente (punto de red, switch, impresora) | E52: {"manual":"trabajo pendiente del cliente"} | G52: Avisar a ID cuando el punto de red, el switch o la impresora estén instalados para configurarlos. | H52: Cliente | I52: Media | K52: Minutas RKT Banchero, Villa Flores y Zárate | L52: SI | M52: =IF(A52="","",COUNTIF(kb_minuta_recomendacion!$D$2:$D$2000,A52)) | N52: =IF(A52="","",SUMPRODUCT((kb_minuta_recomendacion!$D$2:$D$2000=A52)/COUNTIFS(kb_minuta_recomendacion!$D$2:$D$2000,kb_minuta_recomendacion!$D$2:$D$2000&"",kb_minuta_recomendacion!$A$2:$A$2000,kb_minuta_recomendacion!$A$2:$A$2000&""))) | O52: =IF(A52="","",COUNTIF(kb_minuta_hallazgo!$F$2:$F$2000,A52))
A53: R40 | B53: Impresión | C53: Controlador de impresiones en la PC o laptop | D53: P12a = Sí y P22 = PC o Laptop | E53: {"and":[{"eq":["$derived.necesitaComandas",true]},{"eq":["$P22","SI"]}]} | F53: El negocio necesita comandas y hay PC o laptop en caja. | G53: Instalar el controlador (sistema de impresiones) en la PC o laptop de caja. Con él, la impresora USB de caja imprime comandas, pre-cuentas y comprobantes, y las impresoras de red de otras áreas también imprimen las tres. | H53: ID | I53: Alta | K53: Regla de negocio IDPos (2026-10-06); minuta RKT Hacienda | L53: SI | M53: =IF(A53="","",COUNTIF(kb_minuta_recomendacion!$D$2:$D$2000,A53)) | N53: =IF(A53="","",SUMPRODUCT((kb_minuta_recomendacion!$D$2:$D$2000=A53)/COUNTIFS(kb_minuta_recomendacion!$D$2:$D$2000,kb_minuta_recomendacion!$D$2:$D$2000&"",kb_minuta_recomendacion!$A$2:$A$2000,kb_minuta_recomendacion!$A$2:$A$2000&""))) | O53: =IF(A53="","",COUNTIF(kb_minuta_hallazgo!$F$2:$F$2000,A53))
A54: R41 | B54: Impresión | C54: Laptop o PC básica con USB, sin controlador | D54: P12a = No y P22 = No hay | E54: {"and":[{"eq":["$derived.necesitaComandas",false]},{"eq":["$P12b","NO"]},{"in":["$P22",["NO","NO_SE","OTRO"]]}]} | F54: El negocio solo imprimirá pre-cuentas y comprobantes y no tiene PC ni laptop en caja. | G54: Adquirir una laptop o PC básica con puerto USB para la impresora de caja. Como no necesita comandas, no hace falta controlador de impresiones ni Raspberry. | H54: Cliente | I54: Alta | J54: EQ-PC-BASICA | K54: Regla de negocio IDPos (2026-10-06) | L54: SI | M54: =IF(A54="","",COUNTIF(kb_minuta_recomendacion!$D$2:$D$2000,A54)) | N54: =IF(A54="","",SUMPRODUCT((kb_minuta_recomendacion!$D$2:$D$2000=A54)/COUNTIFS(kb_minuta_recomendacion!$D$2:$D$2000,kb_minuta_recomendacion!$D$2:$D$2000&"",kb_minuta_recomendacion!$A$2:$A$2000,kb_minuta_recomendacion!$A$2:$A$2000&""))) | O54: =IF(A54="","",COUNTIF(kb_minuta_hallazgo!$F$2:$F$2000,A54))
A55: R43 | B55: Impresión | C55: Impresora USB en caja: laptop o PC con controlador | D55: Necesita comandas (deducido), P22 = No, No sé u Otro y la impresora de caja es USB (deducido de P27 + P30) | E55: {"and":[{"eq":["$derived.necesitaComandas",true]},{"in":["$P22",["NO","NO_SE","OTRO"]]},{"eq":["$derived.conexionImpresoraCaja","USB"]}]} | F55: El negocio necesita comandas, no hay PC ni laptop y la impresora de caja es USB. | G55: Adquirir una laptop o PC para instalar el controlador de impresiones: la impresora USB solo funciona con laptop o PC, no con Raspberry. Alternativa: cambiar la impresora de caja por una de red y usar un Raspberry. | H55: Cliente | I55: Alta | J55: EQ-PC-BASICA | K55: Regla de negocio IDPos (2026-10-06) | L55: SI | M55: =IF(A55="","",COUNTIF(kb_minuta_recomendacion!$D$2:$D$2000,A55)) | N55: =IF(A55="","",SUMPRODUCT((kb_minuta_recomendacion!$D$2:$D$2000=A55)/COUNTIFS(kb_minuta_recomendacion!$D$2:$D$2000,kb_minuta_recomendacion!$D$2:$D$2000&"",kb_minuta_recomendacion!$A$2:$A$2000,kb_minuta_recomendacion!$A$2:$A$2000&""))) | O55: =IF(A55="","",COUNTIF(kb_minuta_hallazgo!$F$2:$F$2000,A55))
A56: R44 | B56: Impresión | C56: Sunmi cuando la comanda sale solo en caja | D56: No hay áreas de preparación (deducido de P11) y la comanda sale en caja (P12b = Sí) | E56: {"and":[{"eq":["$derived.necesitaComandas",false]},{"eq":["$P12b","SI"]}]} | F56: No hay áreas de preparación fuera de caja: la comanda se imprime en caja. | G56: Recomendar un equipo Sunmi con chip: imprime comprobantes, pre-cuentas y comandas. Antes, validar con un celular que el chip tenga señal en el local. El Sunmi se compra directamente al equipo de Desarrollo de Negocios, pidiendo cotización. | H56: Cliente | I56: Alta | J56: EQ-SUNMI | K56: Regla de negocio IDPos (2026-10-06); minuta Malala (monitor Sunmi con chip) | L56: SI | M56: =IF(A56="","",COUNTIF(kb_minuta_recomendacion!$D$2:$D$2000,A56)) | N56: =IF(A56="","",SUMPRODUCT((kb_minuta_recomendacion!$D$2:$D$2000=A56)/COUNTIFS(kb_minuta_recomendacion!$D$2:$D$2000,kb_minuta_recomendacion!$D$2:$D$2000&"",kb_minuta_recomendacion!$A$2:$A$2000,kb_minuta_recomendacion!$A$2:$A$2000&""))) | O56: =IF(A56="","",COUNTIF(kb_minuta_hallazgo!$F$2:$F$2000,A56))
A57: R45 | B57: Internet | C57: Router con chip cuando no hay fibra ni coaxial | D57: P14 = No tiene o No sé (se toma como sin internet), necesita comandas y P14b = Entel, Claro o Ambos | E57: {"and":[{"in":["$P14",["NO_TIENE","NO_SE"]]},{"eq":["$derived.necesitaComandas",true]},{"in":["$P14b",["ENTEL","CLARO","AMBOS"]]}]} | F57: El local no tiene internet por fibra ni cable coaxial (o el técnico no sabe, y se toma como sin internet) y el negocio necesita comandas. | G57: Recomendar un router con chip del proveedor que tuvo señal en la prueba con el celular (Entel o Claro) como internet del local. | H57: Cliente | I57: Alta | J57: EQ-ROUTER-4G | K57: Regla de negocio IDPos (2026-10-06); minutas Malala y Sicilia | L57: NO (unificada en R56) | M57: =IF(A57="","",COUNTIF(kb_minuta_recomendacion!$D$2:$D$2000,A57)) | N57: =IF(A57="","",SUMPRODUCT((kb_minuta_recomendacion!$D$2:$D$2000=A57)/COUNTIFS(kb_minuta_recomendacion!$D$2:$D$2000,kb_minuta_recomendacion!$D$2:$D$2000&"",kb_minuta_recomendacion!$A$2:$A$2000,kb_minuta_recomendacion!$A$2:$A$2000&""))) | O57: =IF(A57="","",COUNTIF(kb_minuta_hallazgo!$F$2:$F$2000,A57))
A58: R46 | B58: Internet | C58: Sin señal de chip ni fibra | D58: P14 = No tiene o No sé y P14b = Ninguno | E58: {"and":[{"in":["$P14",["NO_TIENE","NO_SE"]]},{"eq":["$P14b","NINGUNO"]}]} | F58: No hay fibra, cable coaxial ni señal de chip en el local. | G58: Avisar que no hay conectividad viable para el sistema; evaluar internet satelital (Starlink) y agendar una segunda visita. | H58: ID | I58: Alta | K58: Propuesta (no indicada por el equipo); relacionada con R33 y la minuta Hotel La Confianza | L58: SI | M58: =IF(A58="","",COUNTIF(kb_minuta_recomendacion!$D$2:$D$2000,A58)) | N58: =IF(A58="","",SUMPRODUCT((kb_minuta_recomendacion!$D$2:$D$2000=A58)/COUNTIFS(kb_minuta_recomendacion!$D$2:$D$2000,kb_minuta_recomendacion!$D$2:$D$2000&"",kb_minuta_recomendacion!$A$2:$A$2000,kb_minuta_recomendacion!$A$2:$A$2000&""))) | O58: =IF(A58="","",COUNTIF(kb_minuta_hallazgo!$F$2:$F$2000,A58))
A59: R47 | B59: Impresión | C59: Tablet en caja: Raspberry obligatorio | D59: En caja hay una tablet o el negocio solo trabaja con tablets (P22 = Tablet) | E59: {"eq":["$P22","TABLET"]} | F59: La caja es una tablet (o el negocio solo usa tablets): no puede alojar el controlador de impresiones. | G59: Es obligatorio adquirir un kit Raspberry para el controlador de impresiones; las impresoras deben ser de red. El kit se cotiza con el equipo de Desarrollo de Negocios. | H59: Cliente | I59: Alta | J59: EQ-RASPBERRY | K59: Regla de negocio IDPos (2026-10-06); minutas Gelato Alore (la tablet es la caja) | L59: SI | M59: =IF(A59="","",COUNTIF(kb_minuta_recomendacion!$D$2:$D$2000,A59)) | N59: =IF(A59="","",SUMPRODUCT((kb_minuta_recomendacion!$D$2:$D$2000=A59)/COUNTIFS(kb_minuta_recomendacion!$D$2:$D$2000,kb_minuta_recomendacion!$D$2:$D$2000&"",kb_minuta_recomendacion!$A$2:$A$2000,kb_minuta_recomendacion!$A$2:$A$2000&""))) | O59: =IF(A59="","",COUNTIF(kb_minuta_hallazgo!$F$2:$F$2000,A59))
A60: A13 | B60: Acción estándar | C60: Cotizar Raspberry o Sunmi con Desarrollo de Negocios | D60: Se recomendó Raspberry (R02) o Sunmi (R44) | E60: {"manual":"R02 o R44 aplicadas"} | G60: Pedir la cotización del kit Raspberry o del Sunmi al equipo de Desarrollo de Negocios (el Sunmi se compra directamente a ese equipo). | H60: ID | I60: Alta | K60: Regla de negocio IDPos (2026-10-06) | L60: SI | M60: =IF(A60="","",COUNTIF(kb_minuta_recomendacion!$D$2:$D$2000,A60)) | N60: =IF(A60="","",SUMPRODUCT((kb_minuta_recomendacion!$D$2:$D$2000=A60)/COUNTIFS(kb_minuta_recomendacion!$D$2:$D$2000,kb_minuta_recomendacion!$D$2:$D$2000&"",kb_minuta_recomendacion!$A$2:$A$2000,kb_minuta_recomendacion!$A$2:$A$2000&""))) | O60: =IF(A60="","",COUNTIF(kb_minuta_hallazgo!$F$2:$F$2000,A60))
A61: R42 | B61: Impresión | C61: Sin comandas: impresora USB directa | D61: P12a = No y P22 = PC o Laptop | E61: {"and":[{"eq":["$derived.necesitaComandas",false]},{"eq":["$P12b","NO"]},{"eq":["$P22","SI"]}]} | F61: El negocio solo imprimirá pre-cuentas y comprobantes y ya tiene PC o laptop. | G61: Usar la impresora USB directo desde la PC o laptop de caja. No hace falta instalar el controlador de impresiones ni una impresora de red. | H61: ID | I61: Media | K61: Regla de negocio IDPos (2026-10-06) | L61: SI | M61: =IF(A61="","",COUNTIF(kb_minuta_recomendacion!$D$2:$D$2000,A61)) | N61: =IF(A61="","",SUMPRODUCT((kb_minuta_recomendacion!$D$2:$D$2000=A61)/COUNTIFS(kb_minuta_recomendacion!$D$2:$D$2000,kb_minuta_recomendacion!$D$2:$D$2000&"",kb_minuta_recomendacion!$A$2:$A$2000,kb_minuta_recomendacion!$A$2:$A$2000&""))) | O61: =IF(A61="","",COUNTIF(kb_minuta_hallazgo!$F$2:$F$2000,A61))
A62: R48 | B62: Cableado | C62: Switch por falta de puertos en el router | D62: Equipos por cable (impresoras de red + PC/laptop + Raspberry + access point/repetidor principal) > puertos LAN libres del router (deducido de la foto E2; P18a solo de respaldo) | E62: {"gt":["$derived.equiposCableados","$derived.puertosLibresRouter"]} | F62: El router no tiene puertos libres suficientes para todos los equipos que van por cable. | G62: Implementar un switch y los puntos de red que faltan: un extremo de cada cable en el router/switch (la central) y el otro junto a cada equipo (impresora, PC, Raspberry). Indicar al cliente cuántos puntos de red debe implementar y el tamaño del switch (5, 8, 16 o 24 puertos). | H62: Cliente | I62: Alta | J62: EQ-SWITCH-NM | K62: Regla de negocio IDPos (2026-10-06); minutas RKT Villa Flores, Gelato Alore Ejército y Malala | L62: SI | M62: =IF(A62="","",COUNTIF(kb_minuta_recomendacion!$D$2:$D$2000,A62)) | N62: =IF(A62="","",SUMPRODUCT((kb_minuta_recomendacion!$D$2:$D$2000=A62)/COUNTIFS(kb_minuta_recomendacion!$D$2:$D$2000,kb_minuta_recomendacion!$D$2:$D$2000&"",kb_minuta_recomendacion!$A$2:$A$2000,kb_minuta_recomendacion!$A$2:$A$2000&""))) | O62: =IF(A62="","",COUNTIF(kb_minuta_hallazgo!$F$2:$F$2000,A62))
A63: R49 | B63: Energía | C63: Punto de energía junto a cada equipo de red | D63: Equipo nuevo o existente (switch, Raspberry, impresora de red, access point, repetidor) sin toma cerca (U5 = No) | E63: {"eq":["$U5","NO"]} | F63: Un equipo de red no tiene una toma de energía cerca. | G63: Habilitar un punto de energía junto a cada equipo de red (switch, Raspberry, impresora de red, access point, repetidor). Si no es posible, indicar que necesitará un punto de energía adicional o una extensión. | H63: Cliente | I63: Alta | K63: Regla de negocio IDPos (2026-10-06); subflujo U | L63: SI | M63: =IF(A63="","",COUNTIF(kb_minuta_recomendacion!$D$2:$D$2000,A63)) | N63: =IF(A63="","",SUMPRODUCT((kb_minuta_recomendacion!$D$2:$D$2000=A63)/COUNTIFS(kb_minuta_recomendacion!$D$2:$D$2000,kb_minuta_recomendacion!$D$2:$D$2000&"",kb_minuta_recomendacion!$A$2:$A$2000,kb_minuta_recomendacion!$A$2:$A$2000&""))) | O63: =IF(A63="","",COUNTIF(kb_minuta_hallazgo!$F$2:$F$2000,A63))
A64: R50 | B64: WiFi | C64: Repetidores: el primero con red y energía, el segundo solo energía | D64: Se recomiendan repetidores o access points (R19) | E64: {"notEmpty":"$P46"} | F64: Hay que extender la señal WiFi con repetidores o access points. | G64: El access point o el primer repetidor necesita punto de red y punto de energía cerca. Un segundo repetidor que se conecta por WiFi al primero solo necesita punto de energía. | H64: Cliente | I64: Media | K64: Regla de negocio IDPos (2026-10-06); minutas RKT Calle 8, Mariscal y Zárate (repetidores) | L64: SI | M64: =IF(A64="","",COUNTIF(kb_minuta_recomendacion!$D$2:$D$2000,A64)) | N64: =IF(A64="","",SUMPRODUCT((kb_minuta_recomendacion!$D$2:$D$2000=A64)/COUNTIFS(kb_minuta_recomendacion!$D$2:$D$2000,kb_minuta_recomendacion!$D$2:$D$2000&"",kb_minuta_recomendacion!$A$2:$A$2000,kb_minuta_recomendacion!$A$2:$A$2000&""))) | O64: =IF(A64="","",COUNTIF(kb_minuta_hallazgo!$F$2:$F$2000,A64))
A65: R51 | B65: Impresión | C65: Impresoras de áreas de preparación: siempre de red | D65: Impresora en un área de preparación (P27 sin CAJA) con conexión USB, WiFi o Bluetooth (P30/P32c) | E65: {"and":[{"eq":["$derived.impresoraEnAreaPreparacion",true]},{"in":["$P30",["USB","WIFI","BLUETOOTH"]]}]} | F65: Una impresora de un área de preparación no está conectada por cable de red. | G65: Las impresoras de áreas de preparación (cocina, bar, jugos, brasas…) deben ser de red, conectadas por cable. Si es USB o Bluetooth, cambiarla por una impresora de red; si es WiFi, conectarla por cable. | H65: Cliente | I65: Alta | K65: Regla de negocio IDPos (2026-10-06); minutas RKT (impresoras de cocina y brasas por red) | L65: SI | M65: =IF(A65="","",COUNTIF(kb_minuta_recomendacion!$D$2:$D$2000,A65)) | N65: =IF(A65="","",SUMPRODUCT((kb_minuta_recomendacion!$D$2:$D$2000=A65)/COUNTIFS(kb_minuta_recomendacion!$D$2:$D$2000,kb_minuta_recomendacion!$D$2:$D$2000&"",kb_minuta_recomendacion!$A$2:$A$2000,kb_minuta_recomendacion!$A$2:$A$2000&""))) | O65: =IF(A65="","",COUNTIF(kb_minuta_hallazgo!$F$2:$F$2000,A65))
A66: R52 | B66: Cajas | C66: Confirmar el equipo de caja | D66: P22 = No sé u Otro | E66: {"in":["$P22",["NO_SE","OTRO"]]} | F66: No se sabe con certeza qué equipo habrá en caja. | G66: Confirmar con el cliente qué equipo usará en caja. Mientras tanto, la recomendación se calcula como si no hubiera PC ni laptop. | H66: ID | I66: Media | K66: Regla de negocio IDPos (2026-10-06) | L66: SI | M66: =IF(A66="","",COUNTIF(kb_minuta_recomendacion!$D$2:$D$2000,A66)) | N66: =IF(A66="","",SUMPRODUCT((kb_minuta_recomendacion!$D$2:$D$2000=A66)/COUNTIFS(kb_minuta_recomendacion!$D$2:$D$2000,kb_minuta_recomendacion!$D$2:$D$2000&"",kb_minuta_recomendacion!$A$2:$A$2000,kb_minuta_recomendacion!$A$2:$A$2000&""))) | O66: =IF(A66="","",COUNTIF(kb_minuta_hallazgo!$F$2:$F$2000,A66))
A67: R53 | B67: Internet | C67: Cámaras: plan de 1000 Mbps y red separada | D67: P47 = Sí o el escáner de IP (E8) muestra cámaras | E67: {"or":[{"eq":["$P47","SI"]},{"eq":["$derived.camarasEnEscaner",true]}]} | F67: Hay cámaras de seguridad: consumen ancho de banda y compiten con el sistema de impresiones. | G67: Contratar un plan de 1000 Mbps y separar la red de cámaras de la red de PC, sistema de impresiones e impresoras de red (VLAN o router aparte), para que las cámaras no consuman la velocidad del sistema. | H67: Cliente | I67: Alta | J67: EQ-SWITCH-ADM | K67: Regla de negocio IDPos (2026-10-08) | L67: SI | M67: =IF(A67="","",COUNTIF(kb_minuta_recomendacion!$D$2:$D$2000,A67)) | N67: =IF(A67="","",SUMPRODUCT((kb_minuta_recomendacion!$D$2:$D$2000=A67)/COUNTIFS(kb_minuta_recomendacion!$D$2:$D$2000,kb_minuta_recomendacion!$D$2:$D$2000&"",kb_minuta_recomendacion!$A$2:$A$2000,kb_minuta_recomendacion!$A$2:$A$2000&""))) | O67: =IF(A67="","",COUNTIF(kb_minuta_hallazgo!$F$2:$F$2000,A67))
A68: R54 | B68: Internet | C68: Plan insuficiente: 200 Mbps por salón | D68: Plan contratado (P15) < 200 Mbps × número de salones (Salón 1, Salón 2, Terraza…) | E68: {"lt":["$P15","$derived.planRequerido"]} | F68: El plan no alcanza 200 Mbps por salón; con salones por repetir la señal llega débil y soporta pocos dispositivos. | G68: Aumentar el plan a 200 Mbps por salón (mínimo unos 500 Mbps si hay que repetir señal) para mejorar la señal repetida y la conexión de más dispositivos. | H68: Cliente | I68: Alta | K68: Regla de negocio IDPos (2026-10-08) | L68: SI | M68: =IF(A68="","",COUNTIF(kb_minuta_recomendacion!$D$2:$D$2000,A68)) | N68: =IF(A68="","",SUMPRODUCT((kb_minuta_recomendacion!$D$2:$D$2000=A68)/COUNTIFS(kb_minuta_recomendacion!$D$2:$D$2000,kb_minuta_recomendacion!$D$2:$D$2000&"",kb_minuta_recomendacion!$A$2:$A$2000,kb_minuta_recomendacion!$A$2:$A$2000&""))) | O68: =IF(A68="","",COUNTIF(kb_minuta_hallazgo!$F$2:$F$2000,A68))
A69: R55 | B69: Impresión | C69: Impresoras en el segmento del router | D69: La IP del autotest (E5) no está en el segmento de la puerta de enlace del ipconfig (E4) | E69: {"eq":["$derived.impresoraFueraDeSegmento",true]} | F69: Una impresora está en otro segmento de red que el router; el sistema no la alcanza. | G69: Cambiar la IP de la impresora a una del segmento del router (ej. router 192.168.1.1 → impresora 192.168.1.50), con DHCP desactivado, y volver a subir el autotest. | H69: ID | I69: Alta | K69: Regla de negocio IDPos (2026-10-10); validación V04; minuta Dorcher (equipos en redes distintas) | L69: SI | M69: =IF(A69="","",COUNTIF(kb_minuta_recomendacion!$D$2:$D$2000,A69)) | N69: =IF(A69="","",SUMPRODUCT((kb_minuta_recomendacion!$D$2:$D$2000=A69)/COUNTIFS(kb_minuta_recomendacion!$D$2:$D$2000,kb_minuta_recomendacion!$D$2:$D$2000&"",kb_minuta_recomendacion!$A$2:$A$2000,kb_minuta_recomendacion!$A$2:$A$2000&""))) | O69: =IF(A69="","",COUNTIF(kb_minuta_hallazgo!$F$2:$F$2000,A69))
A70: R56 | B70: Internet | C70: Red independiente con TP-Link y chip | D70: Cualquier rubro si: hay caídas de internet (P17 = Sí), no tiene proveedor (P14 = No tiene o No sé) o la dirección (P03) menciona el patio de comidas de un centro comercial grande (Refugio, Larcomar, Real Plaza, Jockey…) | E70: {"or":[{"eq":["$P17","SI"]},{"in":["$P14",["NO_TIENE","NO_SE"]]},{"eq":["$derived.centroComercial",true]}]} | F70: El local tiene caídas de internet, no tiene proveedor o usa el internet compartido del patio de comidas de un centro comercial. | G70: Independizar la red con un TP-Link con chip y plan básico, solo para las impresoras y el equipo donde va el sistema de impresiones. Reemplaza al internet del local para la impresión (no es un respaldo); el chip (Entel o Claro) sale de la prueba de señal. | H70: Cliente | I70: Alta | J70: EQ-ROUTER-4G | K70: Regla de negocio IDPos (2026-10-10). Unifica R01 (respaldo por caídas) y R45 (sin fibra ni coaxial). El chip sale de la prueba de señal (P14b). Minutas Sicilia, Saltao, Bros, Malala, Don Chalán | L70: SI | M70: =IF(A70="","",COUNTIF(kb_minuta_recomendacion!$D$2:$D$2000,A70)) | N70: =IF(A70="","",SUMPRODUCT((kb_minuta_recomendacion!$D$2:$D$2000=A70)/COUNTIFS(kb_minuta_recomendacion!$D$2:$D$2000,kb_minuta_recomendacion!$D$2:$D$2000&"",kb_minuta_recomendacion!$A$2:$A$2000,kb_minuta_recomendacion!$A$2:$A$2000&""))) | O70: =IF(A70="","",COUNTIF(kb_minuta_hallazgo!$F$2:$F$2000,A70))
A71: R57 | B71: Impresión | C71: Raspberry junto al router o switch | D71: Se recomienda o ya hay Raspberry | E71: {"manual":"ubicación del raspberry"} | F71: El Raspberry está lejos del router o en una zona caliente. | G71: Ubicar el Raspberry junto al router o switch, con un cable corto, en un lugar ventilado y lejos del calor y la grasa de la cocina o la parrilla. | H71: ID | I71: Media | J71: EQ-RASPBERRY | K71: Regla de negocio IDPos (2026-10-10); caso Anticuchería Susy | L71: SI | M71: =IF(A71="","",COUNTIF(kb_minuta_recomendacion!$D$2:$D$2000,A71)) | N71: =IF(A71="","",SUMPRODUCT((kb_minuta_recomendacion!$D$2:$D$2000=A71)/COUNTIFS(kb_minuta_recomendacion!$D$2:$D$2000,kb_minuta_recomendacion!$D$2:$D$2000&"",kb_minuta_recomendacion!$A$2:$A$2000,kb_minuta_recomendacion!$A$2:$A$2000&""))) | O71: =IF(A71="","",COUNTIF(kb_minuta_hallazgo!$F$2:$F$2000,A71))
A72: R58 | B72: Red | C72: Switch de 1000 Mbps | D72: El switch principal es de 10/100 Mbps | E72: {"manual":"switch 10/100"} | F72: El switch es de 10/100 Mbps y limita la velocidad de las impresoras y la PC de caja. | G72: Cambiar el switch por uno de 10/100/1000 Mbps (gigabit) con los puertos necesarios. | H72: Cliente | I72: Media | J72: EQ-SWITCH-NM | K72: PROPUESTA por confirmar (2026-10-10). Minutas Shimaya (6) y El Chito | L72: SI | M72: =IF(A72="","",COUNTIF(kb_minuta_recomendacion!$D$2:$D$2000,A72)) | N72: =IF(A72="","",SUMPRODUCT((kb_minuta_recomendacion!$D$2:$D$2000=A72)/COUNTIFS(kb_minuta_recomendacion!$D$2:$D$2000,kb_minuta_recomendacion!$D$2:$D$2000&"",kb_minuta_recomendacion!$A$2:$A$2000,kb_minuta_recomendacion!$A$2:$A$2000&""))) | O72: =IF(A72="","",COUNTIF(kb_minuta_hallazgo!$F$2:$F$2000,A72))
A73: R59 | B73: Cableado | C73: Ponchar los cables con la norma B | D73: Cable de red mal ponchado o cruzado (norma A) entre router, switch e impresora | E73: {"manual":"cable mal ponchado"} | F73: Un cable de red está ponchado como cruzado (norma A) y el equipo pierde conexión. | G73: Ponchar de nuevo el cable con la norma T568B en ambos extremos (router → switch → impresora) y probar la conexión. | H73: ID | I73: Alta | J73: EQ-CABLE-CAT6 | K73: PROPUESTA por confirmar (2026-10-10). Minuta Shimaya Los Olivos | L73: SI | M73: =IF(A73="","",COUNTIF(kb_minuta_recomendacion!$D$2:$D$2000,A73)) | N73: =IF(A73="","",SUMPRODUCT((kb_minuta_recomendacion!$D$2:$D$2000=A73)/COUNTIFS(kb_minuta_recomendacion!$D$2:$D$2000,kb_minuta_recomendacion!$D$2:$D$2000&"",kb_minuta_recomendacion!$A$2:$A$2000,kb_minuta_recomendacion!$A$2:$A$2000&""))) | O73: =IF(A73="","",COUNTIF(kb_minuta_hallazgo!$F$2:$F$2000,A73))
A74: R60 | B74: Cajas | C74: PC o laptop temporal: Raspberry | D74: P22g = No (la PC o laptop no se queda en el local) | E74: {"eq":["$P22g","NO"]} | F74: La PC o laptop de caja no estará siempre en el local. | G74: Tomarlo como si no hubiera PC: recomendar el kit Raspberry para el sistema de impresiones (o una PC fija del local). | H74: Cliente | I74: Alta | J74: EQ-RASPBERRY | K74: PROPUESTA por confirmar (2026-10-10). Minutas Mala Vida y Omakase | L74: SI | M74: =IF(A74="","",COUNTIF(kb_minuta_recomendacion!$D$2:$D$2000,A74)) | N74: =IF(A74="","",SUMPRODUCT((kb_minuta_recomendacion!$D$2:$D$2000=A74)/COUNTIFS(kb_minuta_recomendacion!$D$2:$D$2000,kb_minuta_recomendacion!$D$2:$D$2000&"",kb_minuta_recomendacion!$A$2:$A$2000,kb_minuta_recomendacion!$A$2:$A$2000&""))) | O74: =IF(A74="","",COUNTIF(kb_minuta_hallazgo!$F$2:$F$2000,A74))
A75: R61 | B75: Red | C75: Probar los puertos del router | D75: Un puerto del router no da conexión | E75: {"manual":"puerto del router dañado"} | F75: Un puerto del router no da conexión a la impresora. | G75: Probar cada puerto del router, anotar en qué puerto queda cada impresora y no cambiarla de puerto. | H75: ID | I75: Media | K75: PROPUESTA por confirmar (2026-10-10). Minuta Belgofre | L75: SI | M75: =IF(A75="","",COUNTIF(kb_minuta_recomendacion!$D$2:$D$2000,A75)) | N75: =IF(A75="","",SUMPRODUCT((kb_minuta_recomendacion!$D$2:$D$2000=A75)/COUNTIFS(kb_minuta_recomendacion!$D$2:$D$2000,kb_minuta_recomendacion!$D$2:$D$2000&"",kb_minuta_recomendacion!$A$2:$A$2000,kb_minuta_recomendacion!$A$2:$A$2000&""))) | O75: =IF(A75="","",COUNTIF(kb_minuta_hallazgo!$F$2:$F$2000,A75))
A76: R62 | B76: Cableado | C76: Cables de cámaras lejos de la corriente | D76: Cable de red de cámaras junto a cables de corriente o equipos con motor | E76: {"manual":"cable junto a corriente o motores"} | F76: El cable de las cámaras pasa junto a la corriente o bajo un equipo con motor y genera ruido que llega al router. | G76: Canaletear el cable de red lejos de los cables de corriente y de los equipos con motor (por tubo desde el techo o por el piso). | H76: Cliente | I76: Media | K76: PROPUESTA por confirmar (2026-10-10). Minuta Modonese Arica | L76: SI | M76: =IF(A76="","",COUNTIF(kb_minuta_recomendacion!$D$2:$D$2000,A76)) | N76: =IF(A76="","",SUMPRODUCT((kb_minuta_recomendacion!$D$2:$D$2000=A76)/COUNTIFS(kb_minuta_recomendacion!$D$2:$D$2000,kb_minuta_recomendacion!$D$2:$D$2000&"",kb_minuta_recomendacion!$A$2:$A$2000,kb_minuta_recomendacion!$A$2:$A$2000&""))) | O76: =IF(A76="","",COUNTIF(kb_minuta_hallazgo!$F$2:$F$2000,A76))
A77: R63 | B77: Retail | C77: Periféricos de caja y pruebas de funcionamiento | D77: P09 = Retail – Supermercado | E77: {"eq":["$P09","RETAIL"]} | F77: La caja usa periféricos (balanza, escáner, gaveta, impresora de etiquetas, POS) que deben integrarse al sistema. | G77: Probar en cada caja la impresión, la gaveta, el escáner, la balanza, la impresora de etiquetas y el POS de pago antes del inicio; definir qué balanza queda operativa. | H77: ID | I77: Alta | K77: PROPUESTA por confirmar (2026-10-10). Minuta Flora y Fauna | L77: SI | M77: =IF(A77="","",COUNTIF(kb_minuta_recomendacion!$D$2:$D$2000,A77)) | N77: =IF(A77="","",SUMPRODUCT((kb_minuta_recomendacion!$D$2:$D$2000=A77)/COUNTIFS(kb_minuta_recomendacion!$D$2:$D$2000,kb_minuta_recomendacion!$D$2:$D$2000&"",kb_minuta_recomendacion!$A$2:$A$2000,kb_minuta_recomendacion!$A$2:$A$2000&""))) | O77: =IF(A77="","",COUNTIF(kb_minuta_hallazgo!$F$2:$F$2000,A77))
A78: R64 | B78: Cableado | C78: Reestructurar el cableado de red | D78: Cableado de red desordenado o improvisado | E78: {"manual":"cableado desordenado"} | F78: El cableado de red está desordenado o improvisado. | G78: Reestructurar el cableado de red con canaletas y rotulado. No impide el inicio. | H78: Cliente | I78: Baja | J78: EQ-CABLE-CAT6 | K78: PROPUESTA por confirmar (2026-10-10). Minutas La Carpita del Sabor y Don Chalán | L78: SI | M78: =IF(A78="","",COUNTIF(kb_minuta_recomendacion!$D$2:$D$2000,A78)) | N78: =IF(A78="","",SUMPRODUCT((kb_minuta_recomendacion!$D$2:$D$2000=A78)/COUNTIFS(kb_minuta_recomendacion!$D$2:$D$2000,kb_minuta_recomendacion!$D$2:$D$2000&"",kb_minuta_recomendacion!$A$2:$A$2000,kb_minuta_recomendacion!$A$2:$A$2000&""))) | O78: =IF(A78="","",COUNTIF(kb_minuta_hallazgo!$F$2:$F$2000,A78))
A79: R65 | B79: Internet | C79: Velocidad limitada a 100 Mbps | D79: Prueba por cable entre 85 y 95 Mbps con un plan contratado mayor | E79: {"and":[{"gte":["$E1.bajadaMbps",85]},{"lte":["$E1.bajadaMbps",95]},{"gt":["$P15",100]}]} | F79: La velocidad medida parece limitada a 100 Mbps por un switch 10/100, un puerto de 100 Mbps o el cable. | G79: Repetir la prueba directo al router principal, con cable Cat6 y en un puerto RJ45 gigabit (10/100/1000) en el router y en la PC o laptop; si se confirma, cambiar el switch o el cable. | H79: ID | I79: Media | J79: EQ-CABLE-CAT6 | K79: Regla definida 2026-10-11; minutas Dorcher, RKT Bayóvar, Mariscal, Hacienda, Gelato Ejército (~94 Mbps) | L79: SI | M79: =IF(A79="","",COUNTIF(kb_minuta_recomendacion!$D$2:$D$2000,A79)) | N79: =IF(A79="","",SUMPRODUCT((kb_minuta_recomendacion!$D$2:$D$2000=A79)/COUNTIFS(kb_minuta_recomendacion!$D$2:$D$2000,kb_minuta_recomendacion!$D$2:$D$2000&"",kb_minuta_recomendacion!$A$2:$A$2000,kb_minuta_recomendacion!$A$2:$A$2000&""))) | O79: =IF(A79="","",COUNTIF(kb_minuta_hallazgo!$F$2:$F$2000,A79))
A80: R66 | B80: Internet | C80: Saturación de la red con carga | D80: Ping durante la descarga o la subida > 300 ms | E80: {"gt":["$derived.pingConCargaMax",300]} | F80: La red se satura cuando hay mucho uso: en horas punta las comandas pueden demorar. | G80: Separar el WiFi de clientes de la red del punto de venta, conectar la PC de caja por cable y, si el router lo permite, priorizar el tráfico del punto de venta. | H80: Cliente | I80: Media | K80: Regla definida 2026-10-11 (pruebas de speedtest del equipo) | L80: SI | M80: =IF(A80="","",COUNTIF(kb_minuta_recomendacion!$D$2:$D$2000,A80)) | N80: =IF(A80="","",SUMPRODUCT((kb_minuta_recomendacion!$D$2:$D$2000=A80)/COUNTIFS(kb_minuta_recomendacion!$D$2:$D$2000,kb_minuta_recomendacion!$D$2:$D$2000&"",kb_minuta_recomendacion!$A$2:$A$2000,kb_minuta_recomendacion!$A$2:$A$2000&""))) | O80: =IF(A80="","",COUNTIF(kb_minuta_hallazgo!$F$2:$F$2000,A80))
A81: R67 | B81: Internet | C81: El internet no llega a lo contratado | D81: Mejor prueba por cable < 70 % del plan contratado | E81: {"lt":["$derived.porcentajePlanCable",70]} | F81: La velocidad medida por cable junto al router está por debajo de lo contratado. | G81: Revisar el servicio con el proveedor de internet (o el router) y repetir la prueba por cable. | H81: Cliente | I81: Alta | K81: Propuesta 2026-10-11 (umbral 70 % por confirmar) | L81: SI | M81: =IF(A81="","",COUNTIF(kb_minuta_recomendacion!$D$2:$D$2000,A81)) | N81: =IF(A81="","",SUMPRODUCT((kb_minuta_recomendacion!$D$2:$D$2000=A81)/COUNTIFS(kb_minuta_recomendacion!$D$2:$D$2000,kb_minuta_recomendacion!$D$2:$D$2000&"",kb_minuta_recomendacion!$A$2:$A$2000,kb_minuta_recomendacion!$A$2:$A$2000&""))) | O81: =IF(A81="","",COUNTIF(kb_minuta_hallazgo!$F$2:$F$2000,A81))
M82: =IF(A82="","",COUNTIF(kb_minuta_recomendacion!$D$2:$D$2000,A82)) | N82: =IF(A82="","",SUMPRODUCT((kb_minuta_recomendacion!$D$2:$D$2000=A82)/COUNTIFS(kb_minuta_recomendacion!$D$2:$D$2000,kb_minuta_recomendacion!$D$2:$D$2000&"",kb_minuta_recomendacion!$A$2:$A$2000,kb_minuta_recomendacion!$A$2:$A$2000&""))) | O82: =IF(A82="","",COUNTIF(kb_minuta_hallazgo!$F$2:$F$2000,A82))
M83: =IF(A83="","",COUNTIF(kb_minuta_recomendacion!$D$2:$D$2000,A83)) | N83: =IF(A83="","",SUMPRODUCT((kb_minuta_recomendacion!$D$2:$D$2000=A83)/COUNTIFS(kb_minuta_recomendacion!$D$2:$D$2000,kb_minuta_recomendacion!$D$2:$D$2000&"",kb_minuta_recomendacion!$A$2:$A$2000,kb_minuta_recomendacion!$A$2:$A$2000&""))) | O83: =IF(A83="","",COUNTIF(kb_minuta_hallazgo!$F$2:$F$2000,A83))
M84: =IF(A84="","",COUNTIF(kb_minuta_recomendacion!$D$2:$D$2000,A84)) | N84: =IF(A84="","",SUMPRODUCT((kb_minuta_recomendacion!$D$2:$D$2000=A84)/COUNTIFS(kb_minuta_recomendacion!$D$2:$D$2000,kb_minuta_recomendacion!$D$2:$D$2000&"",kb_minuta_recomendacion!$A$2:$A$2000,kb_minuta_recomendacion!$A$2:$A$2000&""))) | O84: =IF(A84="","",COUNTIF(kb_minuta_hallazgo!$F$2:$F$2000,A84))
M85: =IF(A85="","",COUNTIF(kb_minuta_recomendacion!$D$2:$D$2000,A85)) | N85: =IF(A85="","",SUMPRODUCT((kb_minuta_recomendacion!$D$2:$D$2000=A85)/COUNTIFS(kb_minuta_recomendacion!$D$2:$D$2000,kb_minuta_recomendacion!$D$2:$D$2000&"",kb_minuta_recomendacion!$A$2:$A$2000,kb_minuta_recomendacion!$A$2:$A$2000&""))) | O85: =IF(A85="","",COUNTIF(kb_minuta_hallazgo!$F$2:$F$2000,A85))
M86: =IF(A86="","",COUNTIF(kb_minuta_recomendacion!$D$2:$D$2000,A86)) | N86: =IF(A86="","",SUMPRODUCT((kb_minuta_recomendacion!$D$2:$D$2000=A86)/COUNTIFS(kb_minuta_recomendacion!$D$2:$D$2000,kb_minuta_recomendacion!$D$2:$D$2000&"",kb_minuta_recomendacion!$A$2:$A$2000,kb_minuta_recomendacion!$A$2:$A$2000&""))) | O86: =IF(A86="","",COUNTIF(kb_minuta_hallazgo!$F$2:$F$2000,A86))
M87: =IF(A87="","",COUNTIF(kb_minuta_recomendacion!$D$2:$D$2000,A87)) | N87: =IF(A87="","",SUMPRODUCT((kb_minuta_recomendacion!$D$2:$D$2000=A87)/COUNTIFS(kb_minuta_recomendacion!$D$2:$D$2000,kb_minuta_recomendacion!$D$2:$D$2000&"",kb_minuta_recomendacion!$A$2:$A$2000,kb_minuta_recomendacion!$A$2:$A$2000&""))) | O87: =IF(A87="","",COUNTIF(kb_minuta_hallazgo!$F$2:$F$2000,A87))
M88: =IF(A88="","",COUNTIF(kb_minuta_recomendacion!$D$2:$D$2000,A88)) | N88: =IF(A88="","",SUMPRODUCT((kb_minuta_recomendacion!$D$2:$D$2000=A88)/COUNTIFS(kb_minuta_recomendacion!$D$2:$D$2000,kb_minuta_recomendacion!$D$2:$D$2000&"",kb_minuta_recomendacion!$A$2:$A$2000,kb_minuta_recomendacion!$A$2:$A$2000&""))) | O88: =IF(A88="","",COUNTIF(kb_minuta_hallazgo!$F$2:$F$2000,A88))
M89: =IF(A89="","",COUNTIF(kb_minuta_recomendacion!$D$2:$D$2000,A89)) | N89: =IF(A89="","",SUMPRODUCT((kb_minuta_recomendacion!$D$2:$D$2000=A89)/COUNTIFS(kb_minuta_recomendacion!$D$2:$D$2000,kb_minuta_recomendacion!$D$2:$D$2000&"",kb_minuta_recomendacion!$A$2:$A$2000,kb_minuta_recomendacion!$A$2:$A$2000&""))) | O89: =IF(A89="","",COUNTIF(kb_minuta_hallazgo!$F$2:$F$2000,A89))
M90: =IF(A90="","",COUNTIF(kb_minuta_recomendacion!$D$2:$D$2000,A90)) | N90: =IF(A90="","",SUMPRODUCT((kb_minuta_recomendacion!$D$2:$D$2000=A90)/COUNTIFS(kb_minuta_recomendacion!$D$2:$D$2000,kb_minuta_recomendacion!$D$2:$D$2000&"",kb_minuta_recomendacion!$A$2:$A$2000,kb_minuta_recomendacion!$A$2:$A$2000&""))) | O90: =IF(A90="","",COUNTIF(kb_minuta_hallazgo!$F$2:$F$2000,A90))
M91: =IF(A91="","",COUNTIF(kb_minuta_recomendacion!$D$2:$D$2000,A91)) | N91: =IF(A91="","",SUMPRODUCT((kb_minuta_recomendacion!$D$2:$D$2000=A91)/COUNTIFS(kb_minuta_recomendacion!$D$2:$D$2000,kb_minuta_recomendacion!$D$2:$D$2000&"",kb_minuta_recomendacion!$A$2:$A$2000,kb_minuta_recomendacion!$A$2:$A$2000&""))) | O91: =IF(A91="","",COUNTIF(kb_minuta_hallazgo!$F$2:$F$2000,A91))
M92: =IF(A92="","",COUNTIF(kb_minuta_recomendacion!$D$2:$D$2000,A92)) | N92: =IF(A92="","",SUMPRODUCT((kb_minuta_recomendacion!$D$2:$D$2000=A92)/COUNTIFS(kb_minuta_recomendacion!$D$2:$D$2000,kb_minuta_recomendacion!$D$2:$D$2000&"",kb_minuta_recomendacion!$A$2:$A$2000,kb_minuta_recomendacion!$A$2:$A$2000&""))) | O92: =IF(A92="","",COUNTIF(kb_minuta_hallazgo!$F$2:$F$2000,A92))
M93: =IF(A93="","",COUNTIF(kb_minuta_recomendacion!$D$2:$D$2000,A93)) | N93: =IF(A93="","",SUMPRODUCT((kb_minuta_recomendacion!$D$2:$D$2000=A93)/COUNTIFS(kb_minuta_recomendacion!$D$2:$D$2000,kb_minuta_recomendacion!$D$2:$D$2000&"",kb_minuta_recomendacion!$A$2:$A$2000,kb_minuta_recomendacion!$A$2:$A$2000&""))) | O93: =IF(A93="","",COUNTIF(kb_minuta_hallazgo!$F$2:$F$2000,A93))
... M121: =IF(A121="","",COUNTIF(kb_minuta_recomendacion!$D$2:$D$2000,A121)) | N121: =IF(A121="","",SUMPRODUCT((kb_minuta_recomendacion!$D$2:$D$2000=A121)/COUNTIFS(kb_minuta_recomendacion!$D$2:$D$2000,kb_minuta_recomendacion!$D$2:$D$2000&"",kb_minuta_recomendacion!$A$2:$A$2000,kb_minuta_recomendacion!$A$2:$A$2000&""))) | O121: =IF(A121="","",COUNTIF(kb_minuta_hallazgo!$F$2:$F$2000,A121))

Sheet kb_regla_validacion
A1: validacion_id | B1: regla | C1: evidencias | D1: condicion | E1: estados | F1: texto_corto
A2: V01 | B2: Velocidad por cable ≥ 70 % del plan contratado | C2: E1 (por cable, P19a) | D2: mejor de 2 pruebas por cable ≥ PLAN_MIN_PORCENTAJE_CABLE % de P15; sin prueba por cable = SIN VERIFICAR | E2: CUMPLE / OBSERVADO / SIN VERIFICAR | F2: el internet no llega a lo contratado
A3: V02 | B3: Saturación: ping con carga ≤ 300 ms | C3: E1 | D3: max(ping descarga, ping subida) ≤ PING_CARGA_SATURACION_MS; si no, observación (no impide el inicio) | E3: CUMPLE / OBSERVACIÓN | F3: la red se satura con carga
A4: V03 | B4: PC de caja conectada por cable | C4: E4, P23 | D4: P23 ≠ WiFi y adaptador ≠ WiFi | E4: CUMPLE / OBSERVADO | F4: la PC de caja conectada por WiFi
A5: V04 | B5: Impresora de red con IP fija dentro del segmento del router | C5: E5, E4 (o E3/E8) | D5: DHCP desactivado e IP en el segmento de la puerta de enlace del ipconfig (E4); sin PC: IP de gestión E3 o gateway del escáner E8. Se valida al subir el autotest | E5: CUMPLE / OBSERVADO | F5: la impresora fuera del segmento del router
A6: V05 | B6: MAC de la impresora coincide con el escáner | C6: E5, E8 | D6: MAC del ticket presente en el escáner | E6: VERIFICADO / OBSERVADO | F6: una impresora que no aparece en el escáner
A7: V06 | B7: Todos los equipos de la red documentados | C7: E8 | D7: Cada IP del escáner está documentada | E7: CUMPLE / OBSERVADO | F7: equipos sin documentar
A8: V07 | B8: Proveedor consistente entre evidencias | C8: E1, P13 | D8: Proveedor del speedtest = P13 | E8: CUMPLE / REVISAR | F8: el proveedor distinto entre evidencias
A9: V08 | B9: Impresión sin punto único de falla | C9: P30 | D9: Ninguna impresora USB | E9: OBSERVADO | F9: la dependencia de la impresora USB
A10: V09 | B10: Credenciales fuera del documento | C10: E3 | D10: Datos sensibles de la etiqueta ocultos | E10: APLICADO
A11: V10 | B11: Datos obligatorios completos | C11: — | D11: 0 campos pendientes | E11: CUMPLE / INCOMPLETO

Sheet kb_equipo
A1: equipo_id | B1: categoria | C1: nombre | D1: descripcion | E1: ejemplos_en_minutas | F1: reglas
A2: EQ-RASPBERRY | B2: computer | C2: Kit Raspberry para impresiones | D2: Equipo dedicado al sistema de impresiones (reemplaza programas de impresión en una PC) | E2: Raspberry (Don Oscar) | F2: R02, R34, R47, R57, R60
A3: EQ-ROUTER-4G | B3: router | C3: Router 4G de respaldo con chip | D3: Respaldo de internet ante caídas del enlace principal; chip de datos exclusivo | E3: TP-Link 4G (Don Oscar, recomendado en Sicilia) | F3: R01, R45, R56
A4: EQ-UPS | B4: ups | C4: UPS | D4: Energía de respaldo para router, switch e impresoras | F4: R04, R25
A5: EQ-SUPRESOR | B5: energia | C5: Supresor de picos | D5: Supresor exclusivo para los equipos de red / gabinete | E5: Recomendado en Sicilia y Don Oscar | F5: R03
A6: EQ-SWITCH-NM | B6: switch | C6: Switch no administrable 4–8 puertos | D6: Ampliar un punto de red en un área (barra, terraza) | E6: Recomendado en Sicilia (terraza) y Barrio Pesquero (barra, 3 unidades) | F6: R05, R12, R31, R48, R58
A7: EQ-SWITCH-ADM | B7: switch | C7: Switch administrable | D7: Switch de 24 puertos con soporte VLAN | E7: Motor actual (proposal.py) | F7: R18, R21, R53
A8: EQ-SWITCH-POE | B8: switch | C8: Switch PoE administrable | D8: Alimenta cámaras y access points por el mismo cable | E8: Motor actual (proposal.py) | F8: R20
A9: EQ-AP-WIFI6 | B9: access_point | C9: Access Point WiFi 6 | D9: Punto de acceso administrable para ampliar cobertura | E9: Motor actual (proposal.py) | F9: R19
A10: EQ-ROUTER-EMP | B10: router | C10: Router empresarial | D10: Router con firewall y administración centralizada | E10: Motor actual (proposal.py) | F10: R14, R28
A11: EQ-GABINETE-4RU | B11: gabinete | C11: Gabinete de pared 4 RU | D11: Gabinete Nacional de pared 4 RU (24 alto x 36 ancho x 35 prof.), a 1.65 m del piso | E11: Recomendado en Don Oscar | F11: R07
A12: EQ-CABLE-CAT6 | B12: cableado | C12: Cable UTP Cat6 | D12: Cable más resistente al calor; armado a medida y rotulado | E12: Instalado en Don Oscar | F12: R09, R37, R59, R64, R65
A13: EQ-SUNMI | B13: pos | C13: Equipo Sunmi con chip | D13: Terminal con chip que imprime comprobantes, pre-cuentas y comandas. Se compra al equipo de Desarrollo de Negocios | E13: Monitor Sunmi con chip Entel (Malala) | F13: R44
A14: EQ-PC-BASICA | B14: computer | C14: Laptop o PC básica con puerto USB | D14: Equipo de caja para imprimir pre-cuentas y comprobantes por USB, sin controlador de impresiones | E14: Regla de negocio IDPos | F14: R41, R43

Sheet kb_umbral
A1: clave | B1: valor | C1: unidad | D1: descripcion | E1: origen
A2: MIN_SPEED_MBPS | B2: 50 | C2: Mbps | D2: Velocidad medida mínima para POS y tablets | E2: API: app/chat/checks.py
A3: MAX_LATENCY_MS | B3: 100 | C3: ms | D3: Latencia máxima con la red en uso | E3: API: app/chat/checks.py
A4: BANDWIDTH_MBPS_PER_POS | B4: 2 | C4: Mbps | D4: Demanda estimada por POS | E4: API: app/chat/proposal.py
A5: BANDWIDTH_MBPS_PER_CAMERA | B5: 4 | C5: Mbps | D5: Demanda estimada por cámara | E5: API: app/chat/proposal.py
A6: BANDWIDTH_MBPS_PER_WIFI_CLIENT | B6: 5 | C6: Mbps | D6: Demanda estimada por cliente WiFi | E6: API: app/chat/proposal.py
A7: BANDWIDTH_HEADROOM | B7: 0.7 | C7: fracción | D7: El plan debe cubrir la demanda con holgura | E7: API: app/chat/proposal.py
A8: MAX_CABLE_RUN_M | B8: 100 | C8: m | D8: Límite de cobre TIA/EIA-568 | E8: API: app/chat/proposal.py
A9: CABLE_WARNING_M | B9: 90 | C9: m | D9: Margen antes del límite de cobre | E9: API: app/chat/proposal.py
A10: POE_BUDGET_W | B10: 130 | C10: W | D10: Presupuesto típico de switch PoE | E10: API: app/chat/proposal.py
A11: CAMERA_POE_W | B11: 7 | C11: W | D11: Consumo PoE por cámara | E11: API: app/chat/proposal.py
A12: AP_POE_W | B12: 15 | C12: W | D12: Consumo PoE por access point | E12: API: app/chat/proposal.py
A13: REDUNDANCY_POS_THRESHOLD | B13: 3 | C13: POS | D13: Desde aquí un solo enlace es riesgo | E13: API: app/chat/proposal.py
... A28: ZONA_MIN_SENAL_DBM | B28: -75 | C28: dBm | D28: WiFi por zona: por debajo es 'Mala' (≥−60 excelente, −60 a −67 buena, −67 a −75 regular) | E28: Propuesto (2026-10-11)

Sheet ref_preguntas
A1: pregunta_id | B1: bloque | C1: texto | D1: tipo_entrada | E1: opciones (valor = etiqueta)
A2: P01 | B2: A | C2: ¿Cuál es el nombre del cliente o razón social? | D2: TEXT
A3: P02 | B3: A | C3: ¿Cuál es el nombre del local o sede? | D3: TEXT
A4: P03 | B4: A | C4: ¿Cuál es la dirección del local? | D4: TEXT
A5: P04 | B5: A | C5: ¿Quién es el contacto en el local? (nombre y cargo) | D5: TEXT
A6: P05 | B6: A | C6: ¿Cuál es el teléfono del contacto? | D6: TEXT
A7: P06 | B7: A | C7: Fecha de la visita | D7: TEXT
A8: P07 | B8: A | C8: Técnico responsable | D8: TEXT
A9: P08 | B9: A | C9: ¿Cuál es el estado del local? (OPCIONES PROPUESTAS) | D9: CHOICE | E9: EN_OPERACION = En operación · EN_OBRA = En obra · POR_INAUGURAR = Por inaugurar · SISTEMA_ANTERIOR = Ya cuenta con un sistema de punto de venta anterior · OTRO = Otro (escribir)
A10: P08a | B10: A | C10: Escribe cuál es el estado del local (PROPUESTA) | D10: TEXT
A11: P09 | B11: B | C11: ¿Qué tipo de negocio es? (OPCIONES PROPUESTAS) | D11: CHOICE | E11: REST_PESCADOS = Restaurante – Pescados y mariscos · REST_ORIENTAL = Restaurante – Comida oriental (makis, ramen, sushi) · RESTAURANTE = Restaurante (otro tipo de comida) · CHIFA = Chifa · PIZZERIA = Pizzería · PARRILLA = Parrilla / Anticuchería · POLLERIA = Pollería · FAST_FOOD = Fast food · RESTOBAR = Restobar · DISCOTECA_BAR = Discoteca o bar · CAFETERIA = Cafetería · HELADERIA = Heladería · HOSPEDAJE = Hotel · RETAIL = Retail – Supermercado · OTRO = Otro (escribir)
A12: P09a | B12: B | C12: Solo si P09 = Otro: ¿qué tipo de negocio es? (PROPUESTA: aún no está en el flujo) | D12: TEXT
A13: P09c | B13: B | C13: Solo Fast food, Cafetería y Heladería: ¿hay mozos que toman pedidos con tablet o celular? (PROPUESTA: aún no está en el flujo) | D13: YES_NO | E13: SI · NO
A14: P10 | B14: B | C14: ¿Cuántos pisos tiene el negocio? | D14: NUMBER
A15: P11 | B15: B | C15: ¿Qué áreas tiene el local? | D15: MULTI_SELECT | E15: SALON_1 = Salón 1 · SALON_2 = Salón 2 · TERRAZA = Terraza · BAR = Bar · CAJA = Caja · COCINA = Cocina · DESPACHO = Despacho · PIZZA = Pizza · BRASAS = Brasas · JUGOS = Jugos · CAFETERIA = Cafetería · PARRILLA = Parrillas · MAKIS = Makis · RAMEN = Ramen · PANADERIA = Panadería · ALMACEN = Almacén · OFICINA = Oficina · OTRO = Otro · FRITURAS = Frituras (propuesta) · SALTEADOS = Salteados (propuesta) · HELADOS = Barra de helados (propuesta) · EMPAQUETADO = Empaquetados (propuesta) · BARRA_1 = Barra 1 (propuesta) · BARRA_2 = Barra 2 (propuesta) · BARRA_3 = Barra 3 (propuesta) · COCINA_1 = Cocina 1 (propuesta) · COCINA_2 = Cocina 2 (propuesta) · SALON_3 = Salón 3 (propuesta) · BALCON = Balcón (propuesta) · PRIVADO = Privado (propuesta) · PATIO = Patio (propuesta) · PISTA = Pista de baile (propuesta) · FRENTE_LOCAL = Frente del local (propuesta) · AREAS_COMUNES = Áreas comunes (propuesta) · PARA_LLEVAR = Para llevar (sin WiFi) (propuesta) · DELIVERY = Delivery (sin WiFi) (propuesta) · RECEPCION = Recepción (propuesta)
A16: P11e | B16: B | C16: Un {rubro} normalmente tiene: {areas sugeridas}. ¿Es así? (PROPUESTA: aún no está en el flujo) | D16: CHOICE | E16: CONFIRMAR = Sí, es correcto · EDITAR = Agregar o quitar áreas
A17: P11f | B17: B | C17: ¿Qué canales de atención tiene el local? Puedes elegir varios. (PROPUESTA: aún no está en el flujo) | D17: MULTI_SELECT | E17: MESA = Mesa · RECOJO = Recojo · PARA_LLEVAR = Para llevar · BACKOFFICE = Backoffice · DELIVERY = Delivery · OTRO = Otro (escribir)
A18: P11g | B18: B | C18: Por cada canal: ¿qué zonas de atención tiene {canal}? (sugeridas + Otro, varias veces) (PROPUESTA: aún no está en el flujo) | D18: MULTI_SELECT
A19: P11b | B19: B | C19: Solo si P11 incluye Otro: escribe el nombre del área (ej. Cocina 2, Barra 2, Barra 3) (PROPUESTA: aún no está en el flujo) | D19: TEXT
A20: P11c | B20: B | C20: {area}: ¿es un área de preparación (salen comandas ahí)? (PROPUESTA: aún no está en el flujo) | D20: YES_NO | E20: SI · NO
A21: P11a | B21: B | C21: ¿En qué piso está el área {item.label}? | D21: CHOICE | E21: Dinámico: rango de pisos
A22: P11d | B22: B | C22: Solo si en P11a eligió Otro: ¿dónde está {area}? (escribe la ubicación) (PROPUESTA: aún no está en el flujo) | D22: TEXT
A23: P12 | B23: B | C23: ¿Cuántas cajas hay? | D23: NUMBER
A24: P12a | B24: B | C24: [Derivado de P11] ¿Hay áreas de preparación fuera de caja que necesitan comandas? (PROPUESTA: aún no está en el flujo) | D24: YES_NO | E24: SI · NO
A25: P12b | B25: B | C25: ¿En caja saldrán comandas? (PROPUESTA: aún no está en el flujo) | D25: YES_NO | E25: SI · NO
A26: P12c | B26: B | C26: Solo si P12 > 1, por cada barra: ¿a qué caja está asociada {barra}? (PROPUESTA: aún no está en el flujo) | D26: CHOICE
A27: P12d | B27: B | C27: Solo si en P12c eligió Otro: ¿a qué está asociada {barra}? (PROPUESTA: aún no está en el flujo) | D27: TEXT
A28: P12e | B28: B | C28: ¿La caja comparte lugar con alguna área de preparación? (PROPUESTA: aún no está en el flujo) | D28: CHOICE | E28: NO = No, la caja está aparte · BAR = Barra · PARRILLA = Parrilla · COCINA = Cocina · OTRO = Otro (escribir)
A29: P12b | B29: B | C29: ¿En caja saldrán comandas? | D29: YES_NO | E29: SI · NO
A30: P13 | B30: C | C30: ¿Quién es el proveedor de internet? | D30: CHOICE | E30: MOVISTAR = Movistar · CLARO = Claro · ENTEL = Entel · WIN = Win · OTRO = Otro
A31: P13a | B31: C | C31: Solo si P13 = Otro: ¿cuál es el nombre del proveedor de internet? (PROPUESTA: aún no está en el flujo) | D31: TEXT
A32: P14 | B32: C | C32: ¿Qué tipo de conexión de internet tiene? (OPCIONES PROPUESTAS) | D32: CHOICE | E32: FIBRA = Fibra óptica · COAXIAL = Cable coaxial · NO_SE = No sé · NO_TIENE = No tiene · CHIP = Internet con chip
A33: P14b | B33: C | C33: Solo si P14 = No tiene o No sé (sin internet), o si va Sunmi. Prueba con un celular: ¿qué chip tiene señal en el local? (PROPUESTA: aún no está en el flujo) | D33: CHOICE
A34: E1b | B34: C | C34: Captura del speedtest hecho desde el celular con el chip (PROPUESTA: aún no está en el flujo) | D34: EVIDENCE
A35: P14b | B35: C | C35: Pon el chip en un celular dentro del local. ¿Qué chip tiene señal? | D35: CHOICE | E35: ENTEL = Entel · CLARO = Claro · AMBOS = Ambos · NINGUNO = Ninguno
A36: E1b | B36: C | C36: Sube la captura del speedtest hecho desde el celular con el chip. | D36: EVIDENCE
A37: P15 | B37: C | C37: ¿Cuál es la velocidad contratada? (Mbps) | D37: NUMBER
A38: P16 | B38: C | C38: ¿Hay una segunda línea de internet de respaldo? | D38: YES_NO | E38: SI · NO
A39: P17 | B39: C | C39: ¿Hubo caídas de internet en el último mes? | D39: YES_NO | E39: SI · NO
A40: P18 | B40: C | C40: ¿En qué área está el router? | D40: CHOICE | E40: Dinámico: $P11
A41: P18a | B41: C | C41: Solo si la foto del router (E2) no se puede leer: ¿cuántos puertos LAN libres tiene el router? (PROPUESTA: aún no está en el flujo) | D41: NUMBER
A42: P19 | B42: C | C42: Sube la captura del speedtest (hecho desde el local). | D42: EVIDENCE
A43: P19a | B43: C | C43: ¿Desde qué equipo hiciste el speedtest? (PROPUESTA: aún no está en el flujo) | D43: CHOICE | E43: PC_CAJA_CABLE = PC de caja por cable al router · LAPTOP_CABLE = Laptop por cable al router · WIFI = Por WiFi
A44: P20 | B44: C | C44: Sube una foto del router donde se vea su ubicación. | D44: EVIDENCE
A45: P18a | B45: C | C45: No se pudieron leer los puertos en la foto del router. ¿Cuántos puertos LAN libres tiene? | D45: NUMBER
A46: P21 | B46: C | C46: Sube una foto de la etiqueta del router o switch. | D46: EVIDENCE
A47: P22 | B47: D | C47: Caja {i}: ¿hay una PC o laptop? (OPCIONES PROPUESTAS) | D47: CHOICE | E47: SI = Sí · NO = No · TABLET = Tablet · NO_SE = No sé · OTRO = Otro (indicar cuál es el equipo)
A48: P22f | B48: D | C48: Caja {i}: ¿qué equipo hay en caja? (PROPUESTA: aún no está en el flujo) | D48: TEXT
A49: P22g | B49: D | C49: Caja {i}: ¿la PC o laptop se queda en el local de forma permanente? (PROPUESTA: aún no está en el flujo) | D49: YES_NO | E49: SI · NO
A50: P22h | B50: D | C50: Solo Retail – Caja {i}: ¿qué periféricos tiene? (PROPUESTA: aún no está en el flujo) | D50: MULTI_SELECT | E50: BALANZA = Balanza · ESCANER = Escáner de códigos · GAVETA = Gaveta · IMPRESORA_ETIQUETAS = Impresora de etiquetas · POS_PAGO = POS de pago (Niubiz, Izipay…) · OTRO = Otro (escribir)
A51: P22f | B51: D | C51: Caja {i}: ¿qué equipo hay en caja? | D51: TEXT
A52: P22a | B52: D | C52: ¿El cliente ya cuenta con un Raspberry? | D52: YES_NO | E52: SI · NO
A53: P22b | B53: D | C53: ¿Qué adquirirá el cliente para el sistema de impresiones? | D53: CHOICE | E53: RASPBERRY = Raspberry · LAPTOP = Laptop · PC = PC
A54: P22c | B54: D | C54: ¿Cómo se conecta el Raspberry a la red? | D54: CHOICE | E54: CABLE_RED = Cable de red · WIFI = WiFi
A55: P23 | B55: D | C55: Caja {i}: ¿la computadora va por cable o por WiFi? | D55: CHOICE | E55: CABLE_RED = Cable de red · WIFI = WiFi
A56: P24 | B56: D | C56: Caja {i}: sube la captura de ipconfig. | D56: EVIDENCE
A57: P25 | B57: E | C57: ¿Qué áreas necesitan imprimir comandas o tickets? | D57: MULTI_SELECT | E57: Dinámico: $P11
A58: P26 | B58: E | C58: ¿Cuántas impresoras hay actualmente? | D58: NUMBER
A59: P27 | B59: E | C59: Impresora {i}: ¿qué áreas imprimen en esta impresora? | D59: MULTI_SELECT | E59: Dinámico: $derived.areasSinImpresora
A60: P28 | B60: E | C60: Impresora {i}: ¿en qué área está físicamente? | D60: CHOICE | E60: Dinámico: $P27
A61: P28a | B61: E | C61: Solo si P28 = Otra: ¿en qué área o ubicación está la impresora? (PROPUESTA: aún no está en el flujo) | D61: TEXT
A62: P29 | B62: E | C62: Impresora {i}: ¿cuál es la marca? | D62: CHOICE | E62: EPSON = Epson · BIXOLON = Bixolon · STAR = Star · OTRO = Otro
A63: P29a | B63: E | C63: Solo si P29 = Otro: ¿cuál es la marca de la impresora? (PROPUESTA: aún no está en el flujo) | D63: TEXT
A64: P30 | B64: E | C64: Impresora {i}: ¿cómo se conecta? | D64: CHOICE | E64: CABLE_RED = Cable de red · USB = USB · WIFI = WiFi · BLUETOOTH = Bluetooth
A65: P31 | B65: E | C65: Impresora {i}: sube el ticket de autotest o la etiqueta. | D65: EVIDENCE
A66: P32 | B66: E | C66: {item.label}: ¿cómo se resolverá la impresión? | D66: CHOICE | E66: COMPARTIR = Compartirá una impresora existente · NUEVA = Se instalará una impresora nueva
A67: P32a | B67: E | C67: {item.label}: ¿con qué impresora compartirá? | D67: CHOICE | E67: Dinámico: $registry.printers
A68: P32b | B68: E | C68: {item.label}: ¿en qué área se colocará la impresora nueva? | D68: CHOICE | E68: Dinámico: $P11
A69: P32c | B69: E | C69: ¿Cómo se conectará la impresora nueva? | D69: CHOICE | E69: CABLE_RED = Cable de red · USB = USB · WIFI = WiFi
A70: P33 | B70: F | C70: ¿Hay tomas de energía cerca de los equipos de red? | D70: YES_NO | E70: SI · NO
A71: P34 | B71: F | C71: ¿Los equipos comparten una misma toma? | D71: YES_NO | E71: SI · NO
A72: P35 | B72: F | C72: ¿Se cuenta con energía de respaldo, como un UPS? | D72: YES_NO | E72: SI · NO
A73: P36 | B73: F | C73: ¿Hay extensiones donde va conectado algún equipo de red o impresora? | D73: YES_NO | E73: SI · NO
A74: P36a | B74: F | C74: ¿Qué equipos están conectados a la extensión? | D74: MULTI_SELECT | E74: ROUTER = Router · SWITCH = Switch · ACCESS_POINT = Access point · IMPRESORA = Impresora · PC = PC · RASPBERRY = Raspberry
A75: P37 | B75: G | C75: ¿Cuántos puntos de red hay? | D75: NUMBER
A76: P38 | B76: G | C76: ¿Los puntos de red llegan a todas las áreas que se necesitan? | D76: YES_NO | E76: SI · NO
A77: P38a | B77: G | C77: ¿Qué áreas no tienen punto de red? | D77: MULTI_SELECT | E77: Dinámico: $P11
A78: P39 | B78: G | C78: ¿Qué cable de red usan? | D78: CHOICE | E78: CAT5E_INT = Interior Cat5e · CAT6_INT = Interior Cat6 · EXTERIOR = Cable exterior · NO_SE = No sé
A79: P39a | B79: G | C79: ¿Cómo pasa el cable de red entre pisos? | D79: CHOICE | E79: DUCTO = Por ducto o canaleta · EXPUESTO = Expuesto por pared o escalera · WIFI = No pasa, el otro piso va por WiFi · NO_SE = No sé
A80: P40 | B80: G | C80: ¿Cómo está el gabinete? | D80: CHOICE | E80: NO_HAY = No hay · ORDENADO = Ordenado · ORDENADO_ROTULADO = Ordenado y rotulado · DESORDENADO = Desordenado o con cables
A81: P41 | B81: G | C81: ¿Algún equipo está expuesto a calor o grasa? | D81: YES_NO | E81: SI · NO
A82: P42 | B82: G | C82: Sube fotos de los puntos de red y las tomas. | D82: EVIDENCE
A83: P43 | B83: G | C83: ¿Dónde está la extensión de energía? | D83: CHOICE | E83: Dinámico: $P11
A84: P44 | B84: G | C84: Sube una foto de la extensión de energía. | D84: EVIDENCE
A85: P45 | B85: H | C85: ¿Hay access points o repetidores? | D85: YES_NO | E85: SI · NO
A86: P46 | B86: H | C86: ¿Hay zonas sin señal WiFi? | D86: MULTI_SELECT | E86: Dinámico: $P11
A87: P46a | B87: H | C87: Para las zonas sin señal, ¿qué se instalará? (PROPUESTA: aún no está en el flujo) | D87: CHOICE
A88: P46a | B88: H | C88: Sugerencia: {derived.sugerenciaWifi}. ¿Qué se instalará en las zonas sin señal? | D88: CHOICE | E88: REPETIDOR = Repetidor · ACCESS_POINT = Access point · AMBOS = Ambos
A89: P47 | B89: H | C89: ¿Hay cámaras de seguridad conectadas a la red? | D89: YES_NO | E89: SI · NO
A90: P48 | B90: H | C90: Sube la captura del escáner de IP. | D90: EVIDENCE
A91: P49 | B91: I | C91: Sube fotos generales del local. | D91: EVIDENCE
A92: E9a | B92: I | C92: Obligatoria: foto del frontis del local. (PROPUESTA: aún no está en el flujo) | D92: EVIDENCE
A93: E9b | B93: I | C93: Obligatoria, una por cada lugar de preparación, zona de atención y caja indicados en el chat: foto de {área}. (PROPUESTA: aún no está en el flujo) | D93: EVIDENCE
A94: P49a | B94: I | C94: Anexos – video del local (apartado fijo, no es pregunta): graba parte del local y dónde están los equipos de red (router, impresoras) y dónde se colocaría el sistema de impresiones. Pega aquí el enlace (Drive, YouTube…); puedes agregar varios. Si no hay enlace, puedes continuar. (PROPUESTA: aún no está en el flujo) | D94: URL_LIST
A95: P50 | B95: I | C95: ¿Considerar agendar una segunda visita? | D95: YES_NO | E95: SI · NO
A96: P50b | B96: I | C96: ¿Hay una fecha de inicio acordada con el cliente? (opcional) (PROPUESTA: aún no está en el flujo) | D96: DATE
A97: P50a | B97: I | C97: ¿Por qué se debe agendar una segunda visita? | D97: TEXT
A98: P51 | B98: I | C98: ¿Quiénes asistieron a la visita? | D98: TEXT
A99: P52 | B99: I | C99: Acuerdos y siguientes acciones | D99: TEXT
A100: P52a | B100: I | C100: Estos son los pasos a seguir. ¿Quieres quitar, editar o agregar alguno? (PROPUESTA: aún no está en el flujo) | D100: EDITABLE_LIST
...

Sheet kb_decision_impresion
A1: caso_id | B1: necesita_comandas | C1: equipo_caja | D1: impresoras | E1: que_imprime | F1: requiere_controlador | G1: donde_va_el_controlador | H1: recomendacion | I1: regla_id
A2: D1 | B2: SI | C2: PC o laptop | D2: USB en caja | E2: Comandas, pre-cuentas y comprobantes | F2: SI | G2: PC o laptop de caja | H2: Instalar el controlador en la PC o laptop y conectar ahí la impresora USB. | I2: R40
A3: D2 | B3: SI | C3: PC o laptop | D3: De red en otras áreas (cocina, bar, brasas…) | E3: Comandas, pre-cuentas y comprobantes | F3: SI | G3: PC o laptop de caja | H3: Instalar el controlador en la PC o laptop; las impresoras de red imprimen las tres. | I3: R40
A4: D3 | B4: SI | C4: No / No sé / Otro | D4: Solo de red (ninguna USB) | E4: Comandas, pre-cuentas y comprobantes | F4: SI | G4: Kit Raspberry | H4: Recomendar al cliente un kit Raspberry para instalar el controlador. | I4: R02
A5: D3b | B5: SI | C5: No / No sé / Otro | D5: USB en caja | E5: Comandas, pre-cuentas y comprobantes | F5: SI | G5: Laptop o PC (a adquirir) | H5: No sirve Raspberry: recomendar una laptop o PC con el controlador. Alternativa: cambiar la USB por una de red y usar Raspberry. | I5: R43
A6: D8 | B6: Cualquiera | C6: Tablet (o solo tablets) | D6: De red | E6: Comandas, pre-cuentas y comprobantes | F6: SI | G6: Kit Raspberry (obligatorio) | H6: Raspberry obligatorio; las impresoras deben ser de red. Cotizar con Desarrollo de Negocios. | I6: R47
A7: D7 | B7: SOLO EN CAJA | C7: Cualquiera | D7: Sunmi (impresora integrada) | E7: Comprobantes, pre-cuentas y comandas | F7: NO | G7: — | H7: Recomendar un Sunmi con chip (validar señal del chip con un celular). Cotizar con Desarrollo de Negocios. | I7: R44
A8: D4 | B8: NO | C8: PC o laptop | D8: USB en caja | E8: Pre-cuentas y comprobantes | F8: NO | G8: — | H8: Usar la impresora USB directo desde la PC o laptop; no instalar controlador. | I8: R42
A9: D5 | B9: NO | C9: No / No sé / Otro | D9: USB en caja | E9: Pre-cuentas y comprobantes | F9: NO | G9: — | H9: Recomendar una laptop o PC básica con puerto USB; no hace falta Raspberry. | I9: R41
A10: D6 | B10: NO | C10: Cualquiera | D10: Solo de red | E10: Pre-cuentas y comprobantes | F10: NO | G10: — | H10: No hace falta impresora de red: basta una impresora USB en caja conectada a la laptop o PC. | I10: R42
A11: D9 | B11: SI | C11: Cualquiera | D11: Impresora en área de preparación (cocina, bar, jugos…) | E11: Comandas (y pre-cuentas si aplica) | F11: SI | G11: PC, laptop o Raspberry | H11: Debe ser impresora de red por cable. USB o Bluetooth no sirven en áreas de preparación. | I11: R51

Sheet kb_decision_internet
A1: caso_id | B1: conexion_actual_P14 | C1: necesita_comandas | D1: senal_chip | E1: recomendacion | F1: regla_id
A2: I1 | B2: Fibra óptica o Cable coaxial | C2: Cualquiera | D2: — (solo si va Sunmi) | E2: Mantener la conexión. No se hace prueba de chip salvo que vaya Sunmi. | F2: R33
A3: I1b | B3: Internet con chip | C3: Cualquiera | D3: Se mide con el speedtest E1 | E3: Si necesita comandas, el chip debe ir en un router (no un celular compartiendo datos). | F3: R56
A4: I2 | B4: No tiene o No sé (= sin internet) | C4: SI | D4: Entel, Claro o ambos | E4: Router (TP-Link) con chip del proveedor que tuvo señal en la prueba con el celular. | F4: R56
A5: I3 | B5: No tiene o No sé (= sin internet) | C5: NO | D5: — | E5: No se recomienda router con chip. Si se usa Sunmi, validar igual la señal del chip. | F5: R44
A6: I4 | B6: No tiene o No sé (= sin internet) | C6: Cualquiera | D6: Ninguno | E6: Sin conectividad viable: evaluar satelital (Starlink) y segunda visita. (Propuesta) | F6: R46

Sheet kb_area_preparacion
A1: area | B1: etiqueta | C1: es_preparacion | D1: ya_esta_en_P11
A2: BAR | B2: Bar / barra | C2: SI | D2: SI
A3: COCINA | B3: Cocina | C3: SI | D3: SI
A4: PIZZA | B4: Pizza | C4: SI | D4: SI
A5: BRASAS | B5: Brasas | C5: SI | D5: SI
A6: JUGOS | B6: Jugos | C6: SI | D6: SI
A7: CAFETERIA | B7: Cafetería | C7: SI | D7: NO (agregar)
A8: PARRILLA | B8: Parrillas | C8: SI | D8: NO (agregar)
A9: MAKIS | B9: Makis | C9: SI | D9: NO (agregar)
A10: RAMEN | B10: Ramen | C10: SI | D10: NO (agregar)
A11: PANADERIA | B11: Panadería | C11: SI | D11: NO (agregar)
A12: CAJA | B12: Caja | C12: NO | D12: SI
... A38: RECEPCION | B38: Recepción | C38: NO (caja) | D38: NO (agregar; perfiles por rubro)

Sheet kb_requisito_equipo
A1: equipo | B1: necesita_punto_red_cerca | C1: necesita_energia_cerca | D1: nota
A2: Router principal | B2: — (es la central) | C2: SI | D2: Los cables de red de los demás equipos salen de aquí (o del switch).
A3: Switch | B3: SI (cable hacia el router) | C3: SI | D3: Si no hay toma cerca: punto de energía adicional o extensión.
A4: PC o laptop de caja | B4: SI (recomendado por cable) | C4: SI | D4: Por WiFi funciona, pero se recomienda cable (R11).
A5: Raspberry | B5: SI | C5: SI | D5: Solo trabaja con impresoras de red.
A6: Impresora de red | B6: SI | C6: SI | D6: Un extremo del cable en el router/switch y el otro junto a la impresora.
A7: Impresora USB | B7: NO (va por USB a la PC o laptop) | C7: SI | D7: Debe estar junto a la PC o laptop.
A8: Access point | B8: SI | C8: SI | D8: Se conecta por cable al router o switch.
A9: Repetidor principal (1.º) | B9: SI | C9: SI | D9: El primer repetidor va cableado al router o switch.
A10: Repetidor secundario (WiFi) | B10: NO | C10: SI | D10: Se conecta por WiFi al primer repetidor: solo necesita energía.
A11: Sunmi | B11: NO (chip o WiFi) | C11: SI | D11: Validar señal del chip (R44).
A12: Tablet / celular de mesero | B12: NO (WiFi) | C12: Carga | D12: Necesita cobertura WiFi en todas las zonas de atención (R19).

Sheet kb_tramo_plan
A1: tramo | B1: desde_mbps | C1: hasta_mbps | D1: puntaje_conectividad | E1: fuente
A2: T0 | B2: 0 | C2: 0 | D2: 0 | E2: Equipo: sin internet (P14 = No tiene o No sé) = 0 %
A3: T1 | B3: 1 | C3: 399 | D3: 30 | E3: Equipo: 200 Mbps = 30 %. Supuesto: hasta 399 Mbps y menos de 200 también 30 % (por confirmar)
A4: T2 | B4: 400 | C4: 699 | D4: 60 | E4: Equipo: 400 a 600 Mbps = 60 %. Supuesto: 601–699 también 60 %
A5: T3 | B5: 700 | C5: 899 | D5: 80 | E5: Equipo: 700 a 800 Mbps = 80 %. Supuesto: 801–899 también 80 %
A6: T4 | B6: 900 | C6: 100000 | D6: 100 | E6: Equipo: 900 a 1000 Mbps o más = 100 %

Sheet kb_puntaje_conectividad
A1: caso | B1: situacion | C1: plan_contratado | D1: puntaje_conectividad | E1: estado_minuta | F1: recomendacion | G1: regla_id
A2: C0 | B2: Sin internet (P14 = No tiene o No sé) | C2: — | D2: 0 % | E2: OBSERVADO | F2: Prueba de chip y TP-Link con chip (red independiente). | G2: R56
A3: C1 | B3: Todas las áreas de atención con WiFi y el plan alcanza (200 Mbps por salón) | C3: Cualquiera | D3: Puntaje del tramo | E3: Según las demás reglas | F3: — | G3: —
A4: C2 | B4: Falta WiFi en una o más áreas de atención | C4: Cualquiera | D4: Puntaje del tramo − 10 (una sola vez): 30→20, 60→50, 80→70, 100→90 | E4: OBSERVADO | F4: Implementar repetidor, mesh o access point en las zonas sin señal. | G4: R19
A5: C3 | B5: El plan no alcanza 200 Mbps por salón | C5: Menor a 200 × salones | D5: Se mantiene (más −10 si además falta WiFi) | E5: OBSERVADO | F5: Subir el plan a 200 Mbps por salón (mínimo ~500 Mbps si hay que repetir señal). | G5: R54
A6: C4 | B6: Hay cámaras de seguridad (P47 = Sí o el escáner E8 muestra cámaras) | C6: Menos de 1000 Mbps | D6: Se mantiene | E6: OBSERVADO | F6: Contratar un plan de 1000 Mbps y separar la red de cámaras de la red de PC, sistema de impresiones e impresoras de red. | G6: R53
A7: C5 | B7: Hay cámaras de seguridad | C7: 1000 Mbps o más | D7: Se mantiene | E7: Según las demás reglas | F7: Separar la red de cámaras de la red de PC, sistema de impresiones e impresoras de red. | G7: R53

Sheet kb_texto_minuta
A1: clave | B1: seccion_minuta | C1: texto | D1: cuando_se_muestra
A2: AVISO_VIABILIDAD | B2: Siguientes acciones / Resumen ejecutivo | C2: Si no se siguen las recomendaciones de esta minuta, no es viable la implementación del punto de venta en el local. | D2: Siempre que la minuta tenga al menos una recomendación
A3: ANTECEDENTES | B3: Antecedentes | C3: La visita se realiza para la implementación del punto de venta, donde el local se encuentra en estado de "{estado}". En la visita se realizarán acciones como validar los equipos tecnológicos y de red y el estado de los mismos, y se le recomendará una mejor infraestructura si lo necesitara. | D3: Siempre. {estado} = etiqueta de P08 (En operación, En obra, Por inaugurar, Ya cuenta con un sistema de punto de venta anterior) o el texto escrito en P08a si es Otro
A4: METODO_PAGO | B4: Observaciones | C4: El método de pago que utilizan en el local es el siguiente: {métodos}. | D4: Si el técnico marcó Método de pago. {métodos} = Niubiz, Izipay, Culqi o el texto escrito en Otro (varios separados por coma y 'y')
A5: ANEXOS_VIDEO | B5: Anexos | C5: Video del local: {enlace} ({zona}). | D5: Solo si el técnico pegó al menos un enlace. Si no hay enlaces, la sección Anexos NO aparece en el PDF (ni título ni 'No hay video')

Sheet kb_accion_siguiente
A1: paso_id | B1: para | C1: texto_plantilla | D1: cuando_se_agrega | E1: regla_id | F1: minutas_que_lo_traen
A2: S01 | B2: ID | C2: Compartir la minuta de visita técnica. | D2: Siempre | E2: A01 | F2: 36
A3: S02 | B3: CLIENTE | C3: Confirmar la recepción de la minuta. | D3: Siempre | E3: A02 | F3: 36
A4: S03 | B4: CLIENTE | C4: Solicitar la cotización de los equipos recomendados: {lista de equipos con cantidad}. | D4: Hay equipos recomendados (sale de las recomendaciones y su equipo_id) | E4: A11 | F4: 7
